Workbook

Sheet Área
A1: Local | B1: =Dashboard!V6 -> FIBRA | C1: Cabo | D1: Start | E1: Corresp | F1: Tipo | G1: Formação | H1: Tensão | I1: Isolamento | J1: Lances Totais | K1: Lances Realizados | L1: Compr. Prev. | M1: Compr. Real | N1: Compr. Lançado | O1: %Lanç | P1: DE | Q1: PARA | R1: Teste de Continuidade | S1: Born a Born | T1: Megger | U1: Hipot | V1: QTDE Teste | W1: % de Testes Realizados | X1: Terminações | Y1: Ligações | Z1: Disponibilidade
C2: =IF($B$1="Geral",Tabela1[[#This Row],[Tag do Cabo]],IFERROR(INDEX(INDIRECT("BD!$A"&D2&":$A100000"),E2,1),"")) -> 1HVBUS3-ER1HV-001C | D2: 1 | E2: =IFERROR(MATCH($B$1,INDIRECT("BD!$J"&D2&":$J100000"),0),"") -> 4 | F2: =IFERROR(VLOOKUP(Tabela4[[#This Row],[Cabo]],BD!A:V,2,0),"") -> FO | G2: =IFERROR(VLOOKUP(Tabela4[[#This Row],[Cabo]],BD!A:V,5,0),"") -> CORDÃO ÓPTICO | H2: =IFERROR(VLOOKUP(Tabela4[[#This Row],[Cabo]],BD!A:V,3,0),"") -> - | I2: =IFERROR(VLOOKUP(Tabela4[[#This Row],[Cabo]],BD!A:V,4,0),"") -> - | J2: =IFERROR(VLOOKUP(Tabela4[[#This Row],[Cabo]],BD!A:V,7,0),"") -> 1 | K2: =IFERROR(IF(ROUNDDOWN(Tabela4[[#This Row],[%Lanç]]*Tabela4[[#This Row],[Lances Totais]],0)>Tabela4[[#This Row],[Lances Totais]],Tabela4[[#This Row],[Lances Totais]],ROUNDDOWN(Tabela4[[#This Row],[%Lanç]]*Tabela4[[#This Row],[Lances Totais]],0)),"") -> 1 | L2: =IFERROR(VLOOKUP(Tabela4[[#This Row],[Cabo]],BD!A:V,9,0),"") -> 40 | M2: =IFERROR(VLOOKUP(Tabela4[[#This Row],[Cabo]],BD!A:AD,30,0),"") -> 40 | N2: =IF(SUMIF('Lançamento de Cabos'!B:B,Tabela4[[#This Row],[Cabo]],'Lançamento de Cabos'!C:C)=0,"",SUMIF('Lançamento de Cabos'!B:B,Tabela4[[#This Row],[Cabo]],'Lançamento de Cabos'!C:C)) -> 40 | O2: =IFERROR(IF(Tabela4[[#This Row],[Compr. Lançado]]/Tabela4[[#This Row],[Compr. Prev.]]>1,1,Tabela4[[#This Row],[Compr. Lançado]]/Tabela4[[#This Row],[Compr. Prev.]]),"") -> 1 | P2: =IFERROR(VLOOKUP(Tabela4[[#This Row],[Cabo]],BD!A:V,11,0),"") -> 1HV-BUS3 | Q2: =IFERROR(VLOOKUP(Tabela4[[#This Row],[Cabo]],BD!A:V,12,0),"") -> ER-3 | R2: =IF(Tabela4[[#This Row],[Cabo]]<>"",IFERROR(VLOOKUP(Tabela4[[#This Row],[Cabo]]&"-1",'Lançamento de Cabos'!$S:$T,2,0),IF(VLOOKUP(Tabela4[[#This Row],[Cabo]],BD!A:V,13,0)="---","---","")),"") -> --- | S2: =IF(Tabela4[[#This Row],[Cabo]]<>"",IFERROR(VLOOKUP(Tabela4[[#This Row],[Cabo]]&"-2",'Lançamento de Cabos'!$S:$T,2,0),IF(VLOOKUP(Tabela4[[#This Row],[Cabo]],BD!A:V,14,0)="---","---","")),"") -> --- | T2: =IF(Tabela4[[#This Row],[Cabo]]<>"",IFERROR(VLOOKUP(Tabela4[[#This Row],[Cabo]]&"-3",'Lançamento de Cabos'!$S:$T,2,0),IF(VLOOKUP(Tabela4[[#This Row],[Cabo]],BD!A:V,15,0)="---","---","")),"") -> --- | U2: =IF(Tabela4[[#This Row],[Cabo]]<>"",IFERROR(VLOOKUP(Tabela4[[#This Row],[Cabo]]&"-4",'Lançamento de Cabos'!$S:$T,2,0),IF(VLOOKUP(Tabela4[[#This Row],[Cabo]],BD!A:V,16,0)="---","---","")),"") -> --- | V2: =IF(Tabela4[[#This Row],[Cabo]]<>"",4-COUNTIF(Tabela4[[#This Row],[Teste de Continuidade]:[Hipot]],"---"),"") -> 0 | W2: =IF(Tabela4[[#This Row],[Cabo]]<>"",(COUNTIF(Tabela4[[#This Row],[Teste de Continuidade]:[Hipot]],"OK"))/(4-COUNTIF(Tabela4[[#This Row],[Teste de Continuidade]:[Hipot]],"---")),"") -> #DIV/0! | X2: =IF(Tabela4[[#This Row],[Cabo]]<>"",SUMIFS('Lançamento de Cabos'!$AF:$AF,'Lançamento de Cabos'!AE:AE,Tabela4[[#This Row],[Cabo]],'Lançamento de Cabos'!AJ:AJ,Área!$B$1),"") -> 0 | Y2: =IF(Tabela4[[#This Row],[Cabo]]<>"",SUMIFS('Lançamento de Cabos'!$AG:$AG,'Lançamento de Cabos'!AE:AE,Tabela4[[#This Row],[Cabo]],'Lançamento de Cabos'!AJ:AJ,Área!$B$1),"") -> 0 | Z2: =VLOOKUP(Tabela4[[#This Row],[Cabo]],BD!A:AB,28,0) -> Disponível
C3: =IF($B$1="Geral",Tabela1[[#This Row],[Tag do Cabo]],IFERROR(INDEX(INDIRECT("BD!$A"&D3&":$A100000"),E3,1),"")) -> 1HVBUS3-ER1HV-002C | D3: =IFERROR(D2+E2,"") -> 5 | E3: =IFERROR(MATCH($B$1,INDIRECT("BD!$J"&D3&":$J100000"),0),"") -> 1 | F3: =IFERROR(VLOOKUP(Tabela4[[#This Row],[Cabo]],BD!A:V,2,0),"") -> FO | G3: =IFERROR(VLOOKUP(Tabela4[[#This Row],[Cabo]],BD!A:V,5,0),"") -> CORDÃO ÓPTICO | H3: =IFERROR(VLOOKUP(Tabela4[[#This Row],[Cabo]],BD!A:V,3,0),"") -> - | I3: =IFERROR(VLOOKUP(Tabela4[[#This Row],[Cabo]],BD!A:V,4,0),"") -> - | J3: =IFERROR(VLOOKUP(Tabela4[[#This Row],[Cabo]],BD!A:V,7,0),"") -> 1 | K3: =IFERROR(IF(ROUNDDOWN(Tabela4[[#This Row],[%Lanç]]*Tabela4[[#This Row],[Lances Totais]],0)>Tabela4[[#This Row],[Lances Totais]],Tabela4[[#This Row],[Lances Totais]],ROUNDDOWN(Tabela4[[#This Row],[%Lanç]]*Tabela4[[#This Row],[Lances Totais]],0)),"") -> 1 | L3: =IFERROR(VLOOKUP(Tabela4[[#This Row],[Cabo]],BD!A:V,9,0),"") -> 40 | M3: =IFERROR(VLOOKUP(Tabela4[[#This Row],[Cabo]],BD!A:AD,30,0),"") -> 40 | N3: =IF(SUMIF('Lançamento de Cabos'!B:B,Tabela4[[#This Row],[Cabo]],'Lançamento de Cabos'!C:C)=0,"",SUMIF('Lançamento de Cabos'!B:B,Tabela4[[#This Row],[Cabo]],'Lançamento de Cabos'!C:C)) -> 40 | O3: =IFERROR(IF(Tabela4[[#This Row],[Compr. Lançado]]/Tabela4[[#This Row],[Compr. Prev.]]>1,1,Tabela4[[#This Row],[Compr. Lançado]]/Tabela4[[#This Row],[Compr. Prev.]]),"") -> 1 | P3: =IFERROR(VLOOKUP(Tabela4[[#This Row],[Cabo]],BD!A:V,11,0),"") -> 1HV-BUS3 | Q3: =IFERROR(VLOOKUP(Tabela4[[#This Row],[Cabo]],BD!A:V,12,0),"") -> ER-3 | R3: =IF(Tabela4[[#This Row],[Cabo]]<>"",IFERROR(VLOOKUP(Tabela4[[#This Row],[Cabo]]&"-1",'Lançamento de Cabos'!$S:$T,2,0),IF(VLOOKUP(Tabela4[[#This Row],[Cabo]],BD!A:V,13,0)="---","---","")),"") -> --- | S3: =IF(Tabela4[[#This Row],[Cabo]]<>"",IFERROR(VLOOKUP(Tabela4[[#This Row],[Cabo]]&"-2",'Lançamento de Cabos'!$S:$T,2,0),IF(VLOOKUP(Tabela4[[#This Row],[Cabo]],BD!A:V,14,0)="---","---","")),"") -> --- | T3: =IF(Tabela4[[#This Row],[Cabo]]<>"",IFERROR(VLOOKUP(Tabela4[[#This Row],[Cabo]]&"-3",'Lançamento de Cabos'!$S:$T,2,0),IF(VLOOKUP(Tabela4[[#This Row],[Cabo]],BD!A:V,15,0)="---","---","")),"") -> --- | U3: =IF(Tabela4[[#This Row],[Cabo]]<>"",IFERROR(VLOOKUP(Tabela4[[#This Row],[Cabo]]&"-4",'Lançamento de Cabos'!$S:$T,2,0),IF(VLOOKUP(Tabela4[[#This Row],[Cabo]],BD!A:V,16,0)="---","---","")),"") -> --- | V3: =IF(Tabela4[[#This Row],[Cabo]]<>"",4-COUNTIF(Tabela4[[#This Row],[Teste de Continuidade]:[Hipot]],"---"),"") -> 0 | W3: =IF(Tabela4[[#This Row],[Cabo]]<>"",(COUNTIF(Tabela4[[#This Row],[Teste de Continuidade]:[Hipot]],"OK"))/(4-COUNTIF(Tabela4[[#This Row],[Teste de Continuidade]:[Hipot]],"---")),"") -> #DIV/0! | X3: =IF(Tabela4[[#This Row],[Cabo]]<>"",SUMIFS('Lançamento de Cabos'!$AF:$AF,'Lançamento de Cabos'!AE:AE,Tabela4[[#This Row],[Cabo]],'Lançamento de Cabos'!AJ:AJ,Área!$B$1),"") -> 0 | Y3: =IF(Tabela4[[#This Row],[Cabo]]<>"",SUMIFS('Lançamento de Cabos'!$AG:$AG,'Lançamento de Cabos'!AE:AE,Tabela4[[#This Row],[Cabo]],'Lançamento de Cabos'!AJ:AJ,Área!$B$1),"") -> 0 | Z3: =VLOOKUP(Tabela4[[#This Row],[Cabo]],BD!A:AB,28,0) -> Disponível
C4: =IF($B$1="Geral",Tabela1[[#This Row],[Tag do Cabo]],IFERROR(INDEX(INDIRECT("BD!$A"&D4&":$A100000"),E4,1),"")) -> 1HVBUS3-ER1HV-003C | D4: =IFERROR(D3+E3,"") -> 6 | E4: =IFERROR(MATCH($B$1,INDIRECT("BD!$J"&D4&":$J100000"),0),"") -> 1 | F4: =IFERROR(VLOOKUP(Tabela4[[#This Row],[Cabo]],BD!A:V,2,0),"") -> FO | G4: =IFERROR(VLOOKUP(Tabela4[[#This Row],[Cabo]],BD!A:V,5,0),"") -> CORDÃO ÓPTICO | H4: =IFERROR(VLOOKUP(Tabela4[[#This Row],[Cabo]],BD!A:V,3,0),"") -> - | I4: =IFERROR(VLOOKUP(Tabela4[[#This Row],[Cabo]],BD!A:V,4,0),"") -> - | J4: =IFERROR(VLOOKUP(Tabela4[[#This Row],[Cabo]],BD!A:V,7,0),"") -> 1 | K4: =IFERROR(IF(ROUNDDOWN(Tabela4[[#This Row],[%Lanç]]*Tabela4[[#This Row],[Lances Totais]],0)>Tabela4[[#This Row],[Lances Totais]],Tabela4[[#This Row],[Lances Totais]],ROUNDDOWN(Tabela4[[#This Row],[%Lanç]]*Tabela4[[#This Row],[Lances Totais]],0)),"") -> 1 | L4: =IFERROR(VLOOKUP(Tabela4[[#This Row],[Cabo]],BD!A:V,9,0),"") -> 40 | M4: =IFERROR(VLOOKUP(Tabela4[[#This Row],[Cabo]],BD!A:AD,30,0),"") -> 40 | N4: =IF(SUMIF('Lançamento de Cabos'!B:B,Tabela4[[#This Row],[Cabo]],'Lançamento de Cabos'!C:C)=0,"",SUMIF('Lançamento de Cabos'!B:B,Tabela4[[#This Row],[Cabo]],'Lançamento de Cabos'!C:C)) -> 40 | O4: =IFERROR(IF(Tabela4[[#This Row],[Compr. Lançado]]/Tabela4[[#This Row],[Compr. Prev.]]>1,1,Tabela4[[#This Row],[Compr. Lançado]]/Tabela4[[#This Row],[Compr. Prev.]]),"") -> 1 | P4: =IFERROR(VLOOKUP(Tabela4[[#This Row],[Cabo]],BD!A:V,11,0),"") -> 1HV-BUS3 | Q4: =IFERROR(VLOOKUP(Tabela4[[#This Row],[Cabo]],BD!A:V,12,0),"") -> ER-3 | R4: =IF(Tabela4[[#This Row],[Cabo]]<>"",IFERROR(VLOOKUP(Tabela4[[#This Row],[Cabo]]&"-1",'Lançamento de Cabos'!$S:$T,2,0),IF(VLOOKUP(Tabela4[[#This Row],[Cabo]],BD!A:V,13,0)="---","---","")),"") -> --- | S4: =IF(Tabela4[[#This Row],[Cabo]]<>"",IFERROR(VLOOKUP(Tabela4[[#This Row],[Cabo]]&"-2",'Lançamento de Cabos'!$S:$T,2,0),IF(VLOOKUP(Tabela4[[#This Row],[Cabo]],BD!A:V,14,0)="---","---","")),"") -> --- | T4: =IF(Tabela4[[#This Row],[Cabo]]<>"",IFERROR(VLOOKUP(Tabela4[[#This Row],[Cabo]]&"-3",'Lançamento de Cabos'!$S:$T,2,0),IF(VLOOKUP(Tabela4[[#This Row],[Cabo]],BD!A:V,15,0)="---","---","")),"") -> --- | U4: =IF(Tabela4[[#This Row],[Cabo]]<>"",IFERROR(VLOOKUP(Tabela4[[#This Row],[Cabo]]&"-4",'Lançamento de Cabos'!$S:$T,2,0),IF(VLOOKUP(Tabela4[[#This Row],[Cabo]],BD!A:V,16,0)="---","---","")),"") -> --- | V4: =IF(Tabela4[[#This Row],[Cabo]]<>"",4-COUNTIF(Tabela4[[#This Row],[Teste de Continuidade]:[Hipot]],"---"),"") -> 0 | W4: =IF(Tabela4[[#This Row],[Cabo]]<>"",(COUNTIF(Tabela4[[#This Row],[Teste de Continuidade]:[Hipot]],"OK"))/(4-COUNTIF(Tabela4[[#This Row],[Teste de Continuidade]:[Hipot]],"---")),"") -> #DIV/0! | X4: =IF(Tabela4[[#This Row],[Cabo]]<>"",SUMIFS('Lançamento de Cabos'!$AF:$AF,'Lançamento de Cabos'!AE:AE,Tabela4[[#This Row],[Cabo]],'Lançamento de Cabos'!AJ:AJ,Área!$B$1),"") -> 0 | Y4: =IF(Tabela4[[#This Row],[Cabo]]<>"",SUMIFS('Lançamento de Cabos'!$AG:$AG,'Lançamento de Cabos'!AE:AE,Tabela4[[#This Row],[Cabo]],'Lançamento de Cabos'!AJ:AJ,Área!$B$1),"") -> 0 | Z4: =VLOOKUP(Tabela4[[#This Row],[Cabo]],BD!A:AB,28,0) -> Disponível
C5: =IF($B$1="Geral",Tabela1[[#This Row],[Tag do Cabo]],IFERROR(INDEX(INDIRECT("BD!$A"&D5&":$A100000"),E5,1),"")) -> 1HVBUS3-ER1HV-004C | D5: =IFERROR(D4+E4,"") -> 7 | E5: =IFERROR(MATCH($B$1,INDIRECT("BD!$J"&D5&":$J100000"),0),"") -> 1 | F5: =IFERROR(VLOOKUP(Tabela4[[#This Row],[Cabo]],BD!A:V,2,0),"") -> FO | G5: =IFERROR(VLOOKUP(Tabela4[[#This Row],[Cabo]],BD!A:V,5,0),"") -> CORDÃO ÓPTICO | H5: =IFERROR(VLOOKUP(Tabela4[[#This Row],[Cabo]],BD!A:V,3,0),"") -> - | I5: =IFERROR(VLOOKUP(Tabela4[[#This Row],[Cabo]],BD!A:V,4,0),"") -> - | J5: =IFERROR(VLOOKUP(Tabela4[[#This Row],[Cabo]],BD!A:V,7,0),"") -> 1 | K5: =IFERROR(IF(ROUNDDOWN(Tabela4[[#This Row],[%Lanç]]*Tabela4[[#This Row],[Lances Totais]],0)>Tabela4[[#This Row],[Lances Totais]],Tabela4[[#This Row],[Lances Totais]],ROUNDDOWN(Tabela4[[#This Row],[%Lanç]]*Tabela4[[#This Row],[Lances Totais]],0)),"") -> 1 | L5: =IFERROR(VLOOKUP(Tabela4[[#This Row],[Cabo]],BD!A:V,9,0),"") -> 40 | M5: =IFERROR(VLOOKUP(Tabela4[[#This Row],[Cabo]],BD!A:AD,30,0),"") -> 40 | N5: =IF(SUMIF('Lançamento de Cabos'!B:B,Tabela4[[#This Row],[Cabo]],'Lançamento de Cabos'!C:C)=0,"",SUMIF('Lançamento de Cabos'!B:B,Tabela4[[#This Row],[Cabo]],'Lançamento de Cabos'!C:C)) -> 40 | O5: =IFERROR(IF(Tabela4[[#This Row],[Compr. Lançado]]/Tabela4[[#This Row],[Compr. Prev.]]>1,1,Tabela4[[#This Row],[Compr. Lançado]]/Tabela4[[#This Row],[Compr. Prev.]]),"") -> 1 | P5: =IFERROR(VLOOKUP(Tabela4[[#This Row],[Cabo]],BD!A:V,11,0),"") -> 1HV-BUS3 | Q5: =IFERROR(VLOOKUP(Tabela4[[#This Row],[Cabo]],BD!A:V,12,0),"") -> ER-3 | R5: =IF(Tabela4[[#This Row],[Cabo]]<>"",IFERROR(VLOOKUP(Tabela4[[#This Row],[Cabo]]&"-1",'Lançamento de Cabos'!$S:$T,2,0),IF(VLOOKUP(Tabela4[[#This Row],[Cabo]],BD!A:V,13,0)="---","---","")),"") -> --- | S5: =IF(Tabela4[[#This Row],[Cabo]]<>"",IFERROR(VLOOKUP(Tabela4[[#This Row],[Cabo]]&"-2",'Lançamento de Cabos'!$S:$T,2,0),IF(VLOOKUP(Tabela4[[#This Row],[Cabo]],BD!A:V,14,0)="---","---","")),"") -> --- | T5: =IF(Tabela4[[#This Row],[Cabo]]<>"",IFERROR(VLOOKUP(Tabela4[[#This Row],[Cabo]]&"-3",'Lançamento de Cabos'!$S:$T,2,0),IF(VLOOKUP(Tabela4[[#This Row],[Cabo]],BD!A:V,15,0)="---","---","")),"") -> --- | U5: =IF(Tabela4[[#This Row],[Cabo]]<>"",IFERROR(VLOOKUP(Tabela4[[#This Row],[Cabo]]&"-4",'Lançamento de Cabos'!$S:$T,2,0),IF(VLOOKUP(Tabela4[[#This Row],[Cabo]],BD!A:V,16,0)="---","---","")),"") -> --- | V5: =IF(Tabela4[[#This Row],[Cabo]]<>"",4-COUNTIF(Tabela4[[#This Row],[Teste de Continuidade]:[Hipot]],"---"),"") -> 0 | W5: =IF(Tabela4[[#This Row],[Cabo]]<>"",(COUNTIF(Tabela4[[#This Row],[Teste de Continuidade]:[Hipot]],"OK"))/(4-COUNTIF(Tabela4[[#This Row],[Teste de Continuidade]:[Hipot]],"---")),"") -> #DIV/0! | X5: =IF(Tabela4[[#This Row],[Cabo]]<>"",SUMIFS('Lançamento de Cabos'!$AF:$AF,'Lançamento de Cabos'!AE:AE,Tabela4[[#This Row],[Cabo]],'Lançamento de Cabos'!AJ:AJ,Área!$B$1),"") -> 0 | Y5: =IF(Tabela4[[#This Row],[Cabo]]<>"",SUMIFS('Lançamento de Cabos'!$AG:$AG,'Lançamento de Cabos'!AE:AE,Tabela4[[#This Row],[Cabo]],'Lançamento de Cabos'!AJ:AJ,Área!$B$1),"") -> 0 | Z5: =VLOOKUP(Tabela4[[#This Row],[Cabo]],BD!A:AB,28,0) -> Disponível
C6: =IF($B$1="Geral",Tabela1[[#This Row],[Tag do Cabo]],IFERROR(INDEX(INDIRECT("BD!$A"&D6&":$A100000"),E6,1),"")) -> 1HVBUS3-ER1HV-005C | D6: =IFERROR(D5+E5,"") -> 8 | E6: =IFERROR(MATCH($B$1,INDIRECT("BD!$J"&D6&":$J100000"),0),"") -> 1 | F6: =IFERROR(VLOOKUP(Tabela4[[#This Row],[Cabo]],BD!A:V,2,0),"") -> FO | G6: =IFERROR(VLOOKUP(Tabela4[[#This Row],[Cabo]],BD!A:V,5,0),"") -> CORDÃO ÓPTICO | H6: =IFERROR(VLOOKUP(Tabela4[[#This Row],[Cabo]],BD!A:V,3,0),"") -> - | I6: =IFERROR(VLOOKUP(Tabela4[[#This Row],[Cabo]],BD!A:V,4,0),"") -> - | J6: =IFERROR(VLOOKUP(Tabela4[[#This Row],[Cabo]],BD!A:V,7,0),"") -> 1 | K6: =IFERROR(IF(ROUNDDOWN(Tabela4[[#This Row],[%Lanç]]*Tabela4[[#This Row],[Lances Totais]],0)>Tabela4[[#This Row],[Lances Totais]],Tabela4[[#This Row],[Lances Totais]],ROUNDDOWN(Tabela4[[#This Row],[%Lanç]]*Tabela4[[#This Row],[Lances Totais]],0)),"") -> 1 | L6: =IFERROR(VLOOKUP(Tabela4[[#This Row],[Cabo]],BD!A:V,9,0),"") -> 40 | M6: =IFERROR(VLOOKUP(Tabela4[[#This Row],[Cabo]],BD!A:AD,30,0),"") -> 40 | N6: =IF(SUMIF('Lançamento de Cabos'!B:B,Tabela4[[#This Row],[Cabo]],'Lançamento de Cabos'!C:C)=0,"",SUMIF('Lançamento de Cabos'!B:B,Tabela4[[#This Row],[Cabo]],'Lançamento de Cabos'!C:C)) -> 40 | O6: =IFERROR(IF(Tabela4[[#This Row],[Compr. Lançado]]/Tabela4[[#This Row],[Compr. Prev.]]>1,1,Tabela4[[#This Row],[Compr. Lançado]]/Tabela4[[#This Row],[Compr. Prev.]]),"") -> 1 | P6: =IFERROR(VLOOKUP(Tabela4[[#This Row],[Cabo]],BD!A:V,11,0),"") -> 1HV-BUS3 | Q6: =IFERROR(VLOOKUP(Tabela4[[#This Row],[Cabo]],BD!A:V,12,0),"") -> ER-3 | R6: =IF(Tabela4[[#This Row],[Cabo]]<>"",IFERROR(VLOOKUP(Tabela4[[#This Row],[Cabo]]&"-1",'Lançamento de Cabos'!$S:$T,2,0),IF(VLOOKUP(Tabela4[[#This Row],[Cabo]],BD!A:V,13,0)="---","---","")),"") -> --- | S6: =IF(Tabela4[[#This Row],[Cabo]]<>"",IFERROR(VLOOKUP(Tabela4[[#This Row],[Cabo]]&"-2",'Lançamento de Cabos'!$S:$T,2,0),IF(VLOOKUP(Tabela4[[#This Row],[Cabo]],BD!A:V,14,0)="---","---","")),"") -> --- | T6: =IF(Tabela4[[#This Row],[Cabo]]<>"",IFERROR(VLOOKUP(Tabela4[[#This Row],[Cabo]]&"-3",'Lançamento de Cabos'!$S:$T,2,0),IF(VLOOKUP(Tabela4[[#This Row],[Cabo]],BD!A:V,15,0)="---","---","")),"") -> --- | U6: =IF(Tabela4[[#This Row],[Cabo]]<>"",IFERROR(VLOOKUP(Tabela4[[#This Row],[Cabo]]&"-4",'Lançamento de Cabos'!$S:$T,2,0),IF(VLOOKUP(Tabela4[[#This Row],[Cabo]],BD!A:V,16,0)="---","---","")),"") -> --- | V6: =IF(Tabela4[[#This Row],[Cabo]]<>"",4-COUNTIF(Tabela4[[#This Row],[Teste de Continuidade]:[Hipot]],"---"),"") -> 0 | W6: =IF(Tabela4[[#This Row],[Cabo]]<>"",(COUNTIF(Tabela4[[#This Row],[Teste de Continuidade]:[Hipot]],"OK"))/(4-COUNTIF(Tabela4[[#This Row],[Teste de Continuidade]:[Hipot]],"---")),"") -> #DIV/0! | X6: =IF(Tabela4[[#This Row],[Cabo]]<>"",SUMIFS('Lançamento de Cabos'!$AF:$AF,'Lançamento de Cabos'!AE:AE,Tabela4[[#This Row],[Cabo]],'Lançamento de Cabos'!AJ:AJ,Área!$B$1),"") -> 0 | Y6: =IF(Tabela4[[#This Row],[Cabo]]<>"",SUMIFS('Lançamento de Cabos'!$AG:$AG,'Lançamento de Cabos'!AE:AE,Tabela4[[#This Row],[Cabo]],'Lançamento de Cabos'!AJ:AJ,Área!$B$1),"") -> 0 | Z6: =VLOOKUP(Tabela4[[#This Row],[Cabo]],BD!A:AB,28,0) -> Disponível
C7: =IF($B$1="Geral",Tabela1[[#This Row],[Tag do Cabo]],IFERROR(INDEX(INDIRECT("BD!$A"&D7&":$A100000"),E7,1),"")) -> CBO001-SEL | D7: =IFERROR(D6+E6,"") -> 9 | E7: =IFERROR(MATCH($B$1,INDIRECT("BD!$J"&D7&":$J100000"),0),"") -> 12 | F7: =IFERROR(VLOOKUP(Tabela4[[#This Row],[Cabo]],BD!A:V,2,0),"") -> FO | G7: =IFERROR(VLOOKUP(Tabela4[[#This Row],[Cabo]],BD!A:V,5,0),"") -> CORDÃO ÓPTICO | H7: =IFERROR(VLOOKUP(Tabela4[[#This Row],[Cabo]],BD!A:V,3,0),"") -> - | I7: =IFERROR(VLOOKUP(Tabela4[[#This Row],[Cabo]],BD!A:V,4,0),"") -> - | J7: =IFERROR(VLOOKUP(Tabela4[[#This Row],[Cabo]],BD!A:V,7,0),"") -> 1 | K7: =IFERROR(IF(ROUNDDOWN(Tabela4[[#This Row],[%Lanç]]*Tabela4[[#This Row],[Lances Totais]],0)>Tabela4[[#This Row],[Lances Totais]],Tabela4[[#This Row],[Lances Totais]],ROUNDDOWN(Tabela4[[#This Row],[%Lanç]]*Tabela4[[#This Row],[Lances Totais]],0)),"") | L7: =IFERROR(VLOOKUP(Tabela4[[#This Row],[Cabo]],BD!A:V,9,0),"") -> 20 | M7: =IFERROR(VLOOKUP(Tabela4[[#This Row],[Cabo]],BD!A:AD,30,0),"") -> 20 | N7: =IF(SUMIF('Lançamento de Cabos'!B:B,Tabela4[[#This Row],[Cabo]],'Lançamento de Cabos'!C:C)=0,"",SUMIF('Lançamento de Cabos'!B:B,Tabela4[[#This Row],[Cabo]],'Lançamento de Cabos'!C:C)) | O7: =IFERROR(IF(Tabela4[[#This Row],[Compr. Lançado]]/Tabela4[[#This Row],[Compr. Prev.]]>1,1,Tabela4[[#This Row],[Compr. Lançado]]/Tabela4[[#This Row],[Compr. Prev.]]),"") | P7: =IFERROR(VLOOKUP(Tabela4[[#This Row],[Cabo]],BD!A:V,11,0),"") -> ER-3 | Q7: =IFERROR(VLOOKUP(Tabela4[[#This Row],[Cabo]],BD!A:V,12,0),"") -> ER-4 | R7: =IF(Tabela4[[#This Row],[Cabo]]<>"",IFERROR(VLOOKUP(Tabela4[[#This Row],[Cabo]]&"-1",'Lançamento de Cabos'!$S:$T,2,0),IF(VLOOKUP(Tabela4[[#This Row],[Cabo]],BD!A:V,13,0)="---","---","")),"") -> --- | S7: =IF(Tabela4[[#This Row],[Cabo]]<>"",IFERROR(VLOOKUP(Tabela4[[#This Row],[Cabo]]&"-2",'Lançamento de Cabos'!$S:$T,2,0),IF(VLOOKUP(Tabela4[[#This Row],[Cabo]],BD!A:V,14,0)="---","---","")),"") -> --- | T7: =IF(Tabela4[[#This Row],[Cabo]]<>"",IFERROR(VLOOKUP(Tabela4[[#This Row],[Cabo]]&"-3",'Lançamento de Cabos'!$S:$T,2,0),IF(VLOOKUP(Tabela4[[#This Row],[Cabo]],BD!A:V,15,0)="---","---","")),"") -> --- | U7: =IF(Tabela4[[#This Row],[Cabo]]<>"",IFERROR(VLOOKUP(Tabela4[[#This Row],[Cabo]]&"-4",'Lançamento de Cabos'!$S:$T,2,0),IF(VLOOKUP(Tabela4[[#This Row],[Cabo]],BD!A:V,16,0)="---","---","")),"") -> --- | V7: =IF(Tabela4[[#This Row],[Cabo]]<>"",4-COUNTIF(Tabela4[[#This Row],[Teste de Continuidade]:[Hipot]],"---"),"") -> 0 | W7: =IF(Tabela4[[#This Row],[Cabo]]<>"",(COUNTIF(Tabela4[[#This Row],[Teste de Continuidade]:[Hipot]],"OK"))/(4-COUNTIF(Tabela4[[#This Row],[Teste de Continuidade]:[Hipot]],"---")),"") -> #DIV/0! | X7: =IF(Tabela4[[#This Row],[Cabo]]<>"",SUMIFS('Lançamento de Cabos'!$AF:$AF,'Lançamento de Cabos'!AE:AE,Tabela4[[#This Row],[Cabo]],'Lançamento de Cabos'!AJ:AJ,Área!$B$1),"") -> 0 | Y7: =IF(Tabela4[[#This Row],[Cabo]]<>"",SUMIFS('Lançamento de Cabos'!$AG:$AG,'Lançamento de Cabos'!AE:AE,Tabela4[[#This Row],[Cabo]],'Lançamento de Cabos'!AJ:AJ,Área!$B$1),"") -> 0 | Z7: =VLOOKUP(Tabela4[[#This Row],[Cabo]],BD!A:AB,28,0) -> Pend. Compra
C8: =IF($B$1="Geral",Tabela1[[#This Row],[Tag do Cabo]],IFERROR(INDEX(INDIRECT("BD!$A"&D8&":$A100000"),E8,1),"")) -> CDC-02290 | D8: =IFERROR(D7+E7,"") -> 21 | E8: =IFERROR(MATCH($B$1,INDIRECT("BD!$J"&D8&":$J100000"),0),"") -> 38 | F8: =IFERROR(VLOOKUP(Tabela4[[#This Row],[Cabo]],BD!A:V,2,0),"") -> FO | G8: =IFERROR(VLOOKUP(Tabela4[[#This Row],[Cabo]],BD!A:V,5,0),"") -> CORDÃO ÓPTICO | H8: =IFERROR(VLOOKUP(Tabela4[[#This Row],[Cabo]],BD!A:V,3,0),"") -> - | I8: =IFERROR(VLOOKUP(Tabela4[[#This Row],[Cabo]],BD!A:V,4,0),"") -> - | J8: =IFERROR(VLOOKUP(Tabela4[[#This Row],[Cabo]],BD!A:V,7,0),"") -> 1 | K8: =IFERROR(IF(ROUNDDOWN(Tabela4[[#This Row],[%Lanç]]*Tabela4[[#This Row],[Lances Totais]],0)>Tabela4[[#This Row],[Lances Totais]],Tabela4[[#This Row],[Lances Totais]],ROUNDDOWN(Tabela4[[#This Row],[%Lanç]]*Tabela4[[#This Row],[Lances Totais]],0)),"") -> 1 | L8: =IFERROR(VLOOKUP(Tabela4[[#This Row],[Cabo]],BD!A:V,9,0),"") -> 2.5 | M8: =IFERROR(VLOOKUP(Tabela4[[#This Row],[Cabo]],BD!A:AD,30,0),"") -> 2.5 | N8: =IF(SUMIF('Lançamento de Cabos'!B:B,Tabela4[[#This Row],[Cabo]],'Lançamento de Cabos'!C:C)=0,"",SUMIF('Lançamento de Cabos'!B:B,Tabela4[[#This Row],[Cabo]],'Lançamento de Cabos'!C:C)) -> 2.5 | O8: =IFERROR(IF(Tabela4[[#This Row],[Compr. Lançado]]/Tabela4[[#This Row],[Compr. Prev.]]>1,1,Tabela4[[#This Row],[Compr. Lançado]]/Tabela4[[#This Row],[Compr. Prev.]]),"") -> 1 | P8: =IFERROR(VLOOKUP(Tabela4[[#This Row],[Cabo]],BD!A:V,11,0),"") -> DIO-120-104 (30LV) | Q8: =IFERROR(VLOOKUP(Tabela4[[#This Row],[Cabo]],BD!A:V,12,0),"") -> SWT-120-105 (30LV) | R8: =IF(Tabela4[[#This Row],[Cabo]]<>"",IFERROR(VLOOKUP(Tabela4[[#This Row],[Cabo]]&"-1",'Lançamento de Cabos'!$S:$T,2,0),IF(VLOOKUP(Tabela4[[#This Row],[Cabo]],BD!A:V,13,0)="---","---","")),"") -> --- | S8: =IF(Tabela4[[#This Row],[Cabo]]<>"",IFERROR(VLOOKUP(Tabela4[[#This Row],[Cabo]]&"-2",'Lançamento de Cabos'!$S:$T,2,0),IF(VLOOKUP(Tabela4[[#This Row],[Cabo]],BD!A:V,14,0)="---","---","")),"") -> --- | T8: =IF(Tabela4[[#This Row],[Cabo]]<>"",IFERROR(VLOOKUP(Tabela4[[#This Row],[Cabo]]&"-3",'Lançamento de Cabos'!$S:$T,2,0),IF(VLOOKUP(Tabela4[[#This Row],[Cabo]],BD!A:V,15,0)="---","---","")),"") -> --- | U8: =IF(Tabela4[[#This Row],[Cabo]]<>"",IFERROR(VLOOKUP(Tabela4[[#This Row],[Cabo]]&"-4",'Lançamento de Cabos'!$S:$T,2,0),IF(VLOOKUP(Tabela4[[#This Row],[Cabo]],BD!A:V,16,0)="---","---","")),"") -> --- | V8: =IF(Tabela4[[#This Row],[Cabo]]<>"",4-COUNTIF(Tabela4[[#This Row],[Teste de Continuidade]:[Hipot]],"---"),"") -> 0 | W8: =IF(Tabela4[[#This Row],[Cabo]]<>"",(COUNTIF(Tabela4[[#This Row],[Teste de Continuidade]:[Hipot]],"OK"))/(4-COUNTIF(Tabela4[[#This Row],[Teste de Continuidade]:[Hipot]],"---")),"") -> #DIV/0! | X8: =IF(Tabela4[[#This Row],[Cabo]]<>"",SUMIFS('Lançamento de Cabos'!$AF:$AF,'Lançamento de Cabos'!AE:AE,Tabela4[[#This Row],[Cabo]],'Lançamento de Cabos'!AJ:AJ,Área!$B$1),"") -> 0 | Y8: =IF(Tabela4[[#This Row],[Cabo]]<>"",SUMIFS('Lançamento de Cabos'!$AG:$AG,'Lançamento de Cabos'!AE:AE,Tabela4[[#This Row],[Cabo]],'Lançamento de Cabos'!AJ:AJ,Área!$B$1),"") -> 0 | Z8: =VLOOKUP(Tabela4[[#This Row],[Cabo]],BD!A:AB,28,0) -> Disponível
C9: =IF($B$1="Geral",Tabela1[[#This Row],[Tag do Cabo]],IFERROR(INDEX(INDIRECT("BD!$A"&D9&":$A100000"),E9,1),"")) -> CDC-02331 | D9: =IFERROR(D8+E8,"") -> 59 | E9: =IFERROR(MATCH($B$1,INDIRECT("BD!$J"&D9&":$J100000"),0),"") -> 1 | F9: =IFERROR(VLOOKUP(Tabela4[[#This Row],[Cabo]],BD!A:V,2,0),"") -> FO | G9: =IFERROR(VLOOKUP(Tabela4[[#This Row],[Cabo]],BD!A:V,5,0),"") -> CORDÃO ÓPTICO | H9: =IFERROR(VLOOKUP(Tabela4[[#This Row],[Cabo]],BD!A:V,3,0),"") -> - | I9: =IFERROR(VLOOKUP(Tabela4[[#This Row],[Cabo]],BD!A:V,4,0),"") -> - | J9: =IFERROR(VLOOKUP(Tabela4[[#This Row],[Cabo]],BD!A:V,7,0),"") -> 1 | K9: =IFERROR(IF(ROUNDDOWN(Tabela4[[#This Row],[%Lanç]]*Tabela4[[#This Row],[Lances Totais]],0)>Tabela4[[#This Row],[Lances Totais]],Tabela4[[#This Row],[Lances Totais]],ROUNDDOWN(Tabela4[[#This Row],[%Lanç]]*Tabela4[[#This Row],[Lances Totais]],0)),"") -> 1 | L9: =IFERROR(VLOOKUP(Tabela4[[#This Row],[Cabo]],BD!A:V,9,0),"") -> 5 | M9: =IFERROR(VLOOKUP(Tabela4[[#This Row],[Cabo]],BD!A:AD,30,0),"") -> 5 | N9: =IF(SUMIF('Lançamento de Cabos'!B:B,Tabela4[[#This Row],[Cabo]],'Lançamento de Cabos'!C:C)=0,"",SUMIF('Lançamento de Cabos'!B:B,Tabela4[[#This Row],[Cabo]],'Lançamento de Cabos'!C:C)) -> 5 | O9: =IFERROR(IF(Tabela4[[#This Row],[Compr. Lançado]]/Tabela4[[#This Row],[Compr. Prev.]]>1,1,Tabela4[[#This Row],[Compr. Lançado]]/Tabela4[[#This Row],[Compr. Prev.]]),"") -> 1 | P9: =IFERROR(VLOOKUP(Tabela4[[#This Row],[Cabo]],BD!A:V,11,0),"") -> PI-1205 (ACESSO REMOTO) | Q9: =IFERROR(VLOOKUP(Tabela4[[#This Row],[Cabo]],BD!A:V,12,0),"") -> SWT-120-105 (30LV) | R9: =IF(Tabela4[[#This Row],[Cabo]]<>"",IFERROR(VLOOKUP(Tabela4[[#This Row],[Cabo]]&"-1",'Lançamento de Cabos'!$S:$T,2,0),IF(VLOOKUP(Tabela4[[#This Row],[Cabo]],BD!A:V,13,0)="---","---","")),"") -> --- | S9: =IF(Tabela4[[#This Row],[Cabo]]<>"",IFERROR(VLOOKUP(Tabela4[[#This Row],[Cabo]]&"-2",'Lançamento de Cabos'!$S:$T,2,0),IF(VLOOKUP(Tabela4[[#This Row],[Cabo]],BD!A:V,14,0)="---","---","")),"") -> --- | T9: =IF(Tabela4[[#This Row],[Cabo]]<>"",IFERROR(VLOOKUP(Tabela4[[#This Row],[Cabo]]&"-3",'Lançamento de Cabos'!$S:$T,2,0),IF(VLOOKUP(Tabela4[[#This Row],[Cabo]],BD!A:V,15,0)="---","---","")),"") -> --- | U9: =IF(Tabela4[[#This Row],[Cabo]]<>"",IFERROR(VLOOKUP(Tabela4[[#This Row],[Cabo]]&"-4",'Lançamento de Cabos'!$S:$T,2,0),IF(VLOOKUP(Tabela4[[#This Row],[Cabo]],BD!A:V,16,0)="---","---","")),"") -> --- | V9: =IF(Tabela4[[#This Row],[Cabo]]<>"",4-COUNTIF(Tabela4[[#This Row],[Teste de Continuidade]:[Hipot]],"---"),"") -> 0 | W9: =IF(Tabela4[[#This Row],[Cabo]]<>"",(COUNTIF(Tabela4[[#This Row],[Teste de Continuidade]:[Hipot]],"OK"))/(4-COUNTIF(Tabela4[[#This Row],[Teste de Continuidade]:[Hipot]],"---")),"") -> #DIV/0! | X9: =IF(Tabela4[[#This Row],[Cabo]]<>"",SUMIFS('Lançamento de Cabos'!$AF:$AF,'Lançamento de Cabos'!AE:AE,Tabela4[[#This Row],[Cabo]],'Lançamento de Cabos'!AJ:AJ,Área!$B$1),"") -> 0 | Y9: =IF(Tabela4[[#This Row],[Cabo]]<>"",SUMIFS('Lançamento de Cabos'!$AG:$AG,'Lançamento de Cabos'!AE:AE,Tabela4[[#This Row],[Cabo]],'Lançamento de Cabos'!AJ:AJ,Área!$B$1),"") -> 0 | Z9: =VLOOKUP(Tabela4[[#This Row],[Cabo]],BD!A:AB,28,0) -> Disponível
C10: =IF($B$1="Geral",Tabela1[[#This Row],[Tag do Cabo]],IFERROR(INDEX(INDIRECT("BD!$A"&D10&":$A100000"),E10,1),"")) -> 7HV-1HV-001C | D10: =IFERROR(D9+E9,"") -> 60 | E10: =IFERROR(MATCH($B$1,INDIRECT("BD!$J"&D10&":$J100000"),0),"") -> 112 | F10: =IFERROR(VLOOKUP(Tabela4[[#This Row],[Cabo]],BD!A:V,2,0),"") -> FO | G10: =IFERROR(VLOOKUP(Tabela4[[#This Row],[Cabo]],BD!A:V,5,0),"") -> CABO ÓPTICO 4 VIAS | H10: =IFERROR(VLOOKUP(Tabela4[[#This Row],[Cabo]],BD!A:V,3,0),"") -> - | I10: =IFERROR(VLOOKUP(Tabela4[[#This Row],[Cabo]],BD!A:V,4,0),"") -> - | J10: =IFERROR(VLOOKUP(Tabela4[[#This Row],[Cabo]],BD!A:V,7,0),"") -> 1 | K10: =IFERROR(IF(ROUNDDOWN(Tabela4[[#This Row],[%Lanç]]*Tabela4[[#This Row],[Lances Totais]],0)>Tabela4[[#This Row],[Lances Totais]],Tabela4[[#This Row],[Lances Totais]],ROUNDDOWN(Tabela4[[#This Row],[%Lanç]]*Tabela4[[#This Row],[Lances Totais]],0)),"") -> 1 | L10: =IFERROR(VLOOKUP(Tabela4[[#This Row],[Cabo]],BD!A:V,9,0),"") -> 450 | M10: =IFERROR(VLOOKUP(Tabela4[[#This Row],[Cabo]],BD!A:AD,30,0),"") -> 450 | N10: =IF(SUMIF('Lançamento de Cabos'!B:B,Tabela4[[#This Row],[Cabo]],'Lançamento de Cabos'!C:C)=0,"",SUMIF('Lançamento de Cabos'!B:B,Tabela4[[#This Row],[Cabo]],'Lançamento de Cabos'!C:C)) -> 450 | O10: =IFERROR(IF(Tabela4[[#This Row],[Compr. Lançado]]/Tabela4[[#This Row],[Compr. Prev.]]>1,1,Tabela4[[#This Row],[Compr. Lançado]]/Tabela4[[#This Row],[Compr. Prev.]]),"") -> 1 | P10: =IFERROR(VLOOKUP(Tabela4[[#This Row],[Cabo]],BD!A:V,11,0),"") -> 7HV | Q10: =IFERROR(VLOOKUP(Tabela4[[#This Row],[Cabo]],BD!A:V,12,0),"") -> REMOTA 1HV | R10: =IF(Tabela4[[#This Row],[Cabo]]<>"",IFERROR(VLOOKUP(Tabela4[[#This Row],[Cabo]]&"-1",'Lançamento de Cabos'!$S:$T,2,0),IF(VLOOKUP(Tabela4[[#This Row],[Cabo]],BD!A:V,13,0)="---","---","")),"") -> --- | S10: =IF(Tabela4[[#This Row],[Cabo]]<>"",IFERROR(VLOOKUP(Tabela4[[#This Row],[Cabo]]&"-2",'Lançamento de Cabos'!$S:$T,2,0),IF(VLOOKUP(Tabela4[[#This Row],[Cabo]],BD!A:V,14,0)="---","---","")),"") -> --- | T10: =IF(Tabela4[[#This Row],[Cabo]]<>"",IFERROR(VLOOKUP(Tabela4[[#This Row],[Cabo]]&"-3",'Lançamento de Cabos'!$S:$T,2,0),IF(VLOOKUP(Tabela4[[#This Row],[Cabo]],BD!A:V,15,0)="---","---","")),"") -> --- | U10: =IF(Tabela4[[#This Row],[Cabo]]<>"",IFERROR(VLOOKUP(Tabela4[[#This Row],[Cabo]]&"-4",'Lançamento de Cabos'!$S:$T,2,0),IF(VLOOKUP(Tabela4[[#This Row],[Cabo]],BD!A:V,16,0)="---","---","")),"") -> --- | V10: =IF(Tabela4[[#This Row],[Cabo]]<>"",4-COUNTIF(Tabela4[[#This Row],[Teste de Continuidade]:[Hipot]],"---"),"") -> 0 | W10: =IF(Tabela4[[#This Row],[Cabo]]<>"",(COUNTIF(Tabela4[[#This Row],[Teste de Continuidade]:[Hipot]],"OK"))/(4-COUNTIF(Tabela4[[#This Row],[Teste de Continuidade]:[Hipot]],"---")),"") -> #DIV/0! | X10: =IF(Tabela4[[#This Row],[Cabo]]<>"",SUMIFS('Lançamento de Cabos'!$AF:$AF,'Lançamento de Cabos'!AE:AE,Tabela4[[#This Row],[Cabo]],'Lançamento de Cabos'!AJ:AJ,Área!$B$1),"") -> 0 | Y10: =IF(Tabela4[[#This Row],[Cabo]]<>"",SUMIFS('Lançamento de Cabos'!$AG:$AG,'Lançamento de Cabos'!AE:AE,Tabela4[[#This Row],[Cabo]],'Lançamento de Cabos'!AJ:AJ,Área!$B$1),"") -> 0 | Z10: =VLOOKUP(Tabela4[[#This Row],[Cabo]],BD!A:AB,28,0) -> Disponível
C11: =IF($B$1="Geral",Tabela1[[#This Row],[Tag do Cabo]],IFERROR(INDEX(INDIRECT("BD!$A"&D11&":$A100000"),E11,1),"")) -> CBO005-RS | D11: =IFERROR(D10+E10,"") -> 172 | E11: =IFERROR(MATCH($B$1,INDIRECT("BD!$J"&D11&":$J100000"),0),"") -> 1 | F11: =IFERROR(VLOOKUP(Tabela4[[#This Row],[Cabo]],BD!A:V,2,0),"") -> FO | G11: =IFERROR(VLOOKUP(Tabela4[[#This Row],[Cabo]],BD!A:V,5,0),"") -> CABO ÓPTICO 4 VIAS | H11: =IFERROR(VLOOKUP(Tabela4[[#This Row],[Cabo]],BD!A:V,3,0),"") -> - | I11: =IFERROR(VLOOKUP(Tabela4[[#This Row],[Cabo]],BD!A:V,4,0),"") -> - | J11: =IFERROR(VLOOKUP(Tabela4[[#This Row],[Cabo]],BD!A:V,7,0),"") -> 1 | K11: =IFERROR(IF(ROUNDDOWN(Tabela4[[#This Row],[%Lanç]]*Tabela4[[#This Row],[Lances Totais]],0)>Tabela4[[#This Row],[Lances Totais]],Tabela4[[#This Row],[Lances Totais]],ROUNDDOWN(Tabela4[[#This Row],[%Lanç]]*Tabela4[[#This Row],[Lances Totais]],0)),"") -> 1 | L11: =IFERROR(VLOOKUP(Tabela4[[#This Row],[Cabo]],BD!A:V,9,0),"") -> 450 | M11: =IFERROR(VLOOKUP(Tabela4[[#This Row],[Cabo]],BD!A:AD,30,0),"") -> 450 | N11: =IF(SUMIF('Lançamento de Cabos'!B:B,Tabela4[[#This Row],[Cabo]],'Lançamento de Cabos'!C:C)=0,"",SUMIF('Lançamento de Cabos'!B:B,Tabela4[[#This Row],[Cabo]],'Lançamento de Cabos'!C:C)) -> 450 | O11: =IFERROR(IF(Tabela4[[#This Row],[Compr. Lançado]]/Tabela4[[#This Row],[Compr. Prev.]]>1,1,Tabela4[[#This Row],[Compr. Lançado]]/Tabela4[[#This Row],[Compr. Prev.]]),"") -> 1 | P11: =IFERROR(VLOOKUP(Tabela4[[#This Row],[Cabo]],BD!A:V,11,0),"") -> PSDC2-DIO | Q11: =IFERROR(VLOOKUP(Tabela4[[#This Row],[Cabo]],BD!A:V,12,0),"") -> PSDC4-DIO1 | R11: =IF(Tabela4[[#This Row],[Cabo]]<>"",IFERROR(VLOOKUP(Tabela4[[#This Row],[Cabo]]&"-1",'Lançamento de Cabos'!$S:$T,2,0),IF(VLOOKUP(Tabela4[[#This Row],[Cabo]],BD!A:V,13,0)="---","---","")),"") -> --- | S11: =IF(Tabela4[[#This Row],[Cabo]]<>"",IFERROR(VLOOKUP(Tabela4[[#This Row],[Cabo]]&"-2",'Lançamento de Cabos'!$S:$T,2,0),IF(VLOOKUP(Tabela4[[#This Row],[Cabo]],BD!A:V,14,0)="---","---","")),"") -> --- | T11: =IF(Tabela4[[#This Row],[Cabo]]<>"",IFERROR(VLOOKUP(Tabela4[[#This Row],[Cabo]]&"-3",'Lançamento de Cabos'!$S:$T,2,0),IF(VLOOKUP(Tabela4[[#This Row],[Cabo]],BD!A:V,15,0)="---","---","")),"") -> --- | U11: =IF(Tabela4[[#This Row],[Cabo]]<>"",IFERROR(VLOOKUP(Tabela4[[#This Row],[Cabo]]&"-4",'Lançamento de Cabos'!$S:$T,2,0),IF(VLOOKUP(Tabela4[[#This Row],[Cabo]],BD!A:V,16,0)="---","---","")),"") -> --- | V11: =IF(Tabela4[[#This Row],[Cabo]]<>"",4-COUNTIF(Tabela4[[#This Row],[Teste de Continuidade]:[Hipot]],"---"),"") -> 0 | W11: =IF(Tabela4[[#This Row],[Cabo]]<>"",(COUNTIF(Tabela4[[#This Row],[Teste de Continuidade]:[Hipot]],"OK"))/(4-COUNTIF(Tabela4[[#This Row],[Teste de Continuidade]:[Hipot]],"---")),"") -> #DIV/0! | X11: =IF(Tabela4[[#This Row],[Cabo]]<>"",SUMIFS('Lançamento de Cabos'!$AF:$AF,'Lançamento de Cabos'!AE:AE,Tabela4[[#This Row],[Cabo]],'Lançamento de Cabos'!AJ:AJ,Área!$B$1),"") -> 0 | Y11: =IF(Tabela4[[#This Row],[Cabo]]<>"",SUMIFS('Lançamento de Cabos'!$AG:$AG,'Lançamento de Cabos'!AE:AE,Tabela4[[#This Row],[Cabo]],'Lançamento de Cabos'!AJ:AJ,Área!$B$1),"") -> 8 | Z11: =VLOOKUP(Tabela4[[#This Row],[Cabo]],BD!A:AB,28,0) -> Disponível
C12: =IF($B$1="Geral",Tabela1[[#This Row],[Tag do Cabo]],IFERROR(INDEX(INDIRECT("BD!$A"&D12&":$A100000"),E12,1),"")) -> CDC-12009 | D12: =IFERROR(D11+E11,"") -> 173 | E12: =IFERROR(MATCH($B$1,INDIRECT("BD!$J"&D12&":$J100000"),0),"") -> 2 | F12: =IFERROR(VLOOKUP(Tabela4[[#This Row],[Cabo]],BD!A:V,2,0),"") -> FO | G12: =IFERROR(VLOOKUP(Tabela4[[#This Row],[Cabo]],BD!A:V,5,0),"") -> FIBRA OPTICA SM 6 PARES | H12: =IFERROR(VLOOKUP(Tabela4[[#This Row],[Cabo]],BD!A:V,3,0),"") -> - | I12: =IFERROR(VLOOKUP(Tabela4[[#This Row],[Cabo]],BD!A:V,4,0),"") -> - | J12: =IFERROR(VLOOKUP(Tabela4[[#This Row],[Cabo]],BD!A:V,7,0),"") -> 1 | K12: =IFERROR(IF(ROUNDDOWN(Tabela4[[#This Row],[%Lanç]]*Tabela4[[#This Row],[Lances Totais]],0)>Tabela4[[#This Row],[Lances Totais]],Tabela4[[#This Row],[Lances Totais]],ROUNDDOWN(Tabela4[[#This Row],[%Lanç]]*Tabela4[[#This Row],[Lances Totais]],0)),"") -> 1 | L12: =IFERROR(VLOOKUP(Tabela4[[#This Row],[Cabo]],BD!A:V,9,0),"") -> 125 | M12: =IFERROR(VLOOKUP(Tabela4[[#This Row],[Cabo]],BD!A:AD,30,0),"") -> 148 | N12: =IF(SUMIF('Lançamento de Cabos'!B:B,Tabela4[[#This Row],[Cabo]],'Lançamento de Cabos'!C:C)=0,"",SUMIF('Lançamento de Cabos'!B:B,Tabela4[[#This Row],[Cabo]],'Lançamento de Cabos'!C:C)) -> 148 | O12: =IFERROR(IF(Tabela4[[#This Row],[Compr. Lançado]]/Tabela4[[#This Row],[Compr. Prev.]]>1,1,Tabela4[[#This Row],[Compr. Lançado]]/Tabela4[[#This Row],[Compr. Prev.]]),"") -> 1 | P12: =IFERROR(VLOOKUP(Tabela4[[#This Row],[Cabo]],BD!A:V,11,0),"") -> RACK 7HV - RCK-120-102 | Q12: =IFERROR(VLOOKUP(Tabela4[[#This Row],[Cabo]],BD!A:V,12,0),"") -> RCK-120-103 - RACK 30LV | R12: =IF(Tabela4[[#This Row],[Cabo]]<>"",IFERROR(VLOOKUP(Tabela4[[#This Row],[Cabo]]&"-1",'Lançamento de Cabos'!$S:$T,2,0),IF(VLOOKUP(Tabela4[[#This Row],[Cabo]],BD!A:V,13,0)="---","---","")),"") -> --- | S12: =IF(Tabela4[[#This Row],[Cabo]]<>"",IFERROR(VLOOKUP(Tabela4[[#This Row],[Cabo]]&"-2",'Lançamento de Cabos'!$S:$T,2,0),IF(VLOOKUP(Tabela4[[#This Row],[Cabo]],BD!A:V,14,0)="---","---","")),"") -> --- | T12: =IF(Tabela4[[#This Row],[Cabo]]<>"",IFERROR(VLOOKUP(Tabela4[[#This Row],[Cabo]]&"-3",'Lançamento de Cabos'!$S:$T,2,0),IF(VLOOKUP(Tabela4[[#This Row],[Cabo]],BD!A:V,15,0)="---","---","")),"") -> --- | U12: =IF(Tabela4[[#This Row],[Cabo]]<>"",IFERROR(VLOOKUP(Tabela4[[#This Row],[Cabo]]&"-4",'Lançamento de Cabos'!$S:$T,2,0),IF(VLOOKUP(Tabela4[[#This Row],[Cabo]],BD!A:V,16,0)="---","---","")),"") -> --- | V12: =IF(Tabela4[[#This Row],[Cabo]]<>"",4-COUNTIF(Tabela4[[#This Row],[Teste de Continuidade]:[Hipot]],"---"),"") -> 0 | W12: =IF(Tabela4[[#This Row],[Cabo]]<>"",(COUNTIF(Tabela4[[#This Row],[Teste de Continuidade]:[Hipot]],"OK"))/(4-COUNTIF(Tabela4[[#This Row],[Teste de Continuidade]:[Hipot]],"---")),"") -> #DIV/0! | X12: =IF(Tabela4[[#This Row],[Cabo]]<>"",SUMIFS('Lançamento de Cabos'!$AF:$AF,'Lançamento de Cabos'!AE:AE,Tabela4[[#This Row],[Cabo]],'Lançamento de Cabos'!AJ:AJ,Área!$B$1),"") -> 0 | Y12: =IF(Tabela4[[#This Row],[Cabo]]<>"",SUMIFS('Lançamento de Cabos'!$AG:$AG,'Lançamento de Cabos'!AE:AE,Tabela4[[#This Row],[Cabo]],'Lançamento de Cabos'!AJ:AJ,Área!$B$1),"") -> 0 | Z12: =VLOOKUP(Tabela4[[#This Row],[Cabo]],BD!A:AB,28,0) -> Disponível
C13: =IF($B$1="Geral",Tabela1[[#This Row],[Tag do Cabo]],IFERROR(INDEX(INDIRECT("BD!$A"&D13&":$A100000"),E13,1),"")) -> CDC-12007 | D13: =IFERROR(D12+E12,"") -> 175 | E13: =IFERROR(MATCH($B$1,INDIRECT("BD!$J"&D13&":$J100000"),0),"") -> 31 | F13: =IFERROR(VLOOKUP(Tabela4[[#This Row],[Cabo]],BD!A:V,2,0),"") -> FO | G13: =IFERROR(VLOOKUP(Tabela4[[#This Row],[Cabo]],BD!A:V,5,0),"") -> FIBRA OPTICA SM 6 PARES | H13: =IFERROR(VLOOKUP(Tabela4[[#This Row],[Cabo]],BD!A:V,3,0),"") -> - | I13: =IFERROR(VLOOKUP(Tabela4[[#This Row],[Cabo]],BD!A:V,4,0),"") -> - | J13: =IFERROR(VLOOKUP(Tabela4[[#This Row],[Cabo]],BD!A:V,7,0),"") -> 1 | K13: =IFERROR(IF(ROUNDDOWN(Tabela4[[#This Row],[%Lanç]]*Tabela4[[#This Row],[Lances Totais]],0)>Tabela4[[#This Row],[Lances Totais]],Tabela4[[#This Row],[Lances Totais]],ROUNDDOWN(Tabela4[[#This Row],[%Lanç]]*Tabela4[[#This Row],[Lances Totais]],0)),"") -> 1 | L13: =IFERROR(VLOOKUP(Tabela4[[#This Row],[Cabo]],BD!A:V,9,0),"") -> 220 | M13: =IFERROR(VLOOKUP(Tabela4[[#This Row],[Cabo]],BD!A:AD,30,0),"") -> 350 | N13: =IF(SUMIF('Lançamento de Cabos'!B:B,Tabela4[[#This Row],[Cabo]],'Lançamento de Cabos'!C:C)=0,"",SUMIF('Lançamento de Cabos'!B:B,Tabela4[[#This Row],[Cabo]],'Lançamento de Cabos'!C:C)) -> 350 | O13: =IFERROR(IF(Tabela4[[#This Row],[Compr. Lançado]]/Tabela4[[#This Row],[Compr. Prev.]]>1,1,Tabela4[[#This Row],[Compr. Lançado]]/Tabela4[[#This Row],[Compr. Prev.]]),"") -> 1 | P13: =IFERROR(VLOOKUP(Tabela4[[#This Row],[Cabo]],BD!A:V,11,0),"") -> DIO-120-104 (RCK-120-102) / ELETROCENTRO MOTORIZAÇÃO | Q13: =IFERROR(VLOOKUP(Tabela4[[#This Row],[Cabo]],BD!A:V,12,0),"") -> DIO-CCP-104 (RCK-CCP-101) / CCP | R13: =IF(Tabela4[[#This Row],[Cabo]]<>"",IFERROR(VLOOKUP(Tabela4[[#This Row],[Cabo]]&"-1",'Lançamento de Cabos'!$S:$T,2,0),IF(VLOOKUP(Tabela4[[#This Row],[Cabo]],BD!A:V,13,0)="---","---","")),"") -> --- | S13: =IF(Tabela4[[#This Row],[Cabo]]<>"",IFERROR(VLOOKUP(Tabela4[[#This Row],[Cabo]]&"-2",'Lançamento de Cabos'!$S:$T,2,0),IF(VLOOKUP(Tabela4[[#This Row],[Cabo]],BD!A:V,14,0)="---","---","")),"") -> --- | T13: =IF(Tabela4[[#This Row],[Cabo]]<>"",IFERROR(VLOOKUP(Tabela4[[#This Row],[Cabo]]&"-3",'Lançamento de Cabos'!$S:$T,2,0),IF(VLOOKUP(Tabela4[[#This Row],[Cabo]],BD!A:V,15,0)="---","---","")),"") -> --- | U13: =IF(Tabela4[[#This Row],[Cabo]]<>"",IFERROR(VLOOKUP(Tabela4[[#This Row],[Cabo]]&"-4",'Lançamento de Cabos'!$S:$T,2,0),IF(VLOOKUP(Tabela4[[#This Row],[Cabo]],BD!A:V,16,0)="---","---","")),"") -> --- | V13: =IF(Tabela4[[#This Row],[Cabo]]<>"",4-COUNTIF(Tabela4[[#This Row],[Teste de Continuidade]:[Hipot]],"---"),"") -> 0 | W13: =IF(Tabela4[[#This Row],[Cabo]]<>"",(COUNTIF(Tabela4[[#This Row],[Teste de Continuidade]:[Hipot]],"OK"))/(4-COUNTIF(Tabela4[[#This Row],[Teste de Continuidade]:[Hipot]],"---")),"") -> #DIV/0! | X13: =IF(Tabela4[[#This Row],[Cabo]]<>"",SUMIFS('Lançamento de Cabos'!$AF:$AF,'Lançamento de Cabos'!AE:AE,Tabela4[[#This Row],[Cabo]],'Lançamento de Cabos'!AJ:AJ,Área!$B$1),"") -> 0 | Y13: =IF(Tabela4[[#This Row],[Cabo]]<>"",SUMIFS('Lançamento de Cabos'!$AG:$AG,'Lançamento de Cabos'!AE:AE,Tabela4[[#This Row],[Cabo]],'Lançamento de Cabos'!AJ:AJ,Área!$B$1),"") -> 0 | Z13: =VLOOKUP(Tabela4[[#This Row],[Cabo]],BD!A:AB,28,0) -> Disponível
C14: =IF($B$1="Geral",Tabela1[[#This Row],[Tag do Cabo]],IFERROR(INDEX(INDIRECT("BD!$A"&D14&":$A100000"),E14,1),"")) -> CDC-12010 | D14: =IFERROR(D13+E13,"") -> 206 | E14: =IFERROR(MATCH($B$1,INDIRECT("BD!$J"&D14&":$J100000"),0),"") -> 1 | F14: =IFERROR(VLOOKUP(Tabela4[[#This Row],[Cabo]],BD!A:V,2,0),"") -> FO | G14: =IFERROR(VLOOKUP(Tabela4[[#This Row],[Cabo]],BD!A:V,5,0),"") -> FIBRA OPTICA SM 6 PARES | H14: =IFERROR(VLOOKUP(Tabela4[[#This Row],[Cabo]],BD!A:V,3,0),"") -> - | I14: =IFERROR(VLOOKUP(Tabela4[[#This Row],[Cabo]],BD!A:V,4,0),"") -> - | J14: =IFERROR(VLOOKUP(Tabela4[[#This Row],[Cabo]],BD!A:V,7,0),"") -> 1 | K14: =IFERROR(IF(ROUNDDOWN(Tabela4[[#This Row],[%Lanç]]*Tabela4[[#This Row],[Lances Totais]],0)>Tabela4[[#This Row],[Lances Totais]],Tabela4[[#This Row],[Lances Totais]],ROUNDDOWN(Tabela4[[#This Row],[%Lanç]]*Tabela4[[#This Row],[Lances Totais]],0)),"") -> 1 | L14: =IFERROR(VLOOKUP(Tabela4[[#This Row],[Cabo]],BD!A:V,9,0),"") -> 350 | M14: =IFERROR(VLOOKUP(Tabela4[[#This Row],[Cabo]],BD!A:AD,30,0),"") -> 350 | N14: =IF(SUMIF('Lançamento de Cabos'!B:B,Tabela4[[#This Row],[Cabo]],'Lançamento de Cabos'!C:C)=0,"",SUMIF('Lançamento de Cabos'!B:B,Tabela4[[#This Row],[Cabo]],'Lançamento de Cabos'!C:C)) -> 350 | O14: =IFERROR(IF(Tabela4[[#This Row],[Compr. Lançado]]/Tabela4[[#This Row],[Compr. Prev.]]>1,1,Tabela4[[#This Row],[Compr. Lançado]]/Tabela4[[#This Row],[Compr. Prev.]]),"") -> 1 | P14: =IFERROR(VLOOKUP(Tabela4[[#This Row],[Cabo]],BD!A:V,11,0),"") -> RACK 7HV - RCK-120-102 | Q14: =IFERROR(VLOOKUP(Tabela4[[#This Row],[Cabo]],BD!A:V,12,0),"") -> RACK CCP - RCK-90-105 | R14: =IF(Tabela4[[#This Row],[Cabo]]<>"",IFERROR(VLOOKUP(Tabela4[[#This Row],[Cabo]]&"-1",'Lançamento de Cabos'!$S:$T,2,0),IF(VLOOKUP(Tabela4[[#This Row],[Cabo]],BD!A:V,13,0)="---","---","")),"") -> --- | S14: =IF(Tabela4[[#This Row],[Cabo]]<>"",IFERROR(VLOOKUP(Tabela4[[#This Row],[Cabo]]&"-2",'Lançamento de Cabos'!$S:$T,2,0),IF(VLOOKUP(Tabela4[[#This Row],[Cabo]],BD!A:V,14,0)="---","---","")),"") -> --- | T14: =IF(Tabela4[[#This Row],[Cabo]]<>"",IFERROR(VLOOKUP(Tabela4[[#This Row],[Cabo]]&"-3",'Lançamento de Cabos'!$S:$T,2,0),IF(VLOOKUP(Tabela4[[#This Row],[Cabo]],BD!A:V,15,0)="---","---","")),"") -> --- | U14: =IF(Tabela4[[#This Row],[Cabo]]<>"",IFERROR(VLOOKUP(Tabela4[[#This Row],[Cabo]]&"-4",'Lançamento de Cabos'!$S:$T,2,0),IF(VLOOKUP(Tabela4[[#This Row],[Cabo]],BD!A:V,16,0)="---","---","")),"") -> --- | V14: =IF(Tabela4[[#This Row],[Cabo]]<>"",4-COUNTIF(Tabela4[[#This Row],[Teste de Continuidade]:[Hipot]],"---"),"") -> 0 | W14: =IF(Tabela4[[#This Row],[Cabo]]<>"",(COUNTIF(Tabela4[[#This Row],[Teste de Continuidade]:[Hipot]],"OK"))/(4-COUNTIF(Tabela4[[#This Row],[Teste de Continuidade]:[Hipot]],"---")),"") -> #DIV/0! | X14: =IF(Tabela4[[#This Row],[Cabo]]<>"",SUMIFS('Lançamento de Cabos'!$AF:$AF,'Lançamento de Cabos'!AE:AE,Tabela4[[#This Row],[Cabo]],'Lançamento de Cabos'!AJ:AJ,Área!$B$1),"") -> 0 | Y14: =IF(Tabela4[[#This Row],[Cabo]]<>"",SUMIFS('Lançamento de Cabos'!$AG:$AG,'Lançamento de Cabos'!AE:AE,Tabela4[[#This Row],[Cabo]],'Lançamento de Cabos'!AJ:AJ,Área!$B$1),"") -> 0 | Z14: =VLOOKUP(Tabela4[[#This Row],[Cabo]],BD!A:AB,28,0) -> Disponível
... C575: =IF($B$1="Geral",Tabela1[[#This Row],[Tag do Cabo]],IFERROR(INDEX(INDIRECT("BD!$A"&D575&":$A100000"),E575,1),"")) | D575: =IFERROR(D574+E574,"") | E575: =IFERROR(MATCH($B$1,INDIRECT("BD!$J"&D575&":$J100000"),0),"") | F575: =IFERROR(VLOOKUP(Tabela4[[#This Row],[Cabo]],BD!A:V,2,0),"") | G575: =IFERROR(VLOOKUP(Tabela4[[#This Row],[Cabo]],BD!A:V,5,0),"") | H575: =IFERROR(VLOOKUP(Tabela4[[#This Row],[Cabo]],BD!A:V,3,0),"") | I575: =IFERROR(VLOOKUP(Tabela4[[#This Row],[Cabo]],BD!A:V,4,0),"") | J575: =IFERROR(VLOOKUP(Tabela4[[#This Row],[Cabo]],BD!A:V,7,0),"") | K575: =IFERROR(IF(ROUNDDOWN(Tabela4[[#This Row],[%Lanç]]*Tabela4[[#This Row],[Lances Totais]],0)>Tabela4[[#This Row],[Lances Totais]],Tabela4[[#This Row],[Lances Totais]],ROUNDDOWN(Tabela4[[#This Row],[%Lanç]]*Tabela4[[#This Row],[Lances Totais]],0)),"") | L575: =IFERROR(VLOOKUP(Tabela4[[#This Row],[Cabo]],BD!A:V,9,0),"") | M575: =IFERROR(VLOOKUP(Tabela4[[#This Row],[Cabo]],BD!A:AD,30,0),"") | N575: =IF(SUMIF('Lançamento de Cabos'!B:B,Tabela4[[#This Row],[Cabo]],'Lançamento de Cabos'!C:C)=0,"",SUMIF('Lançamento de Cabos'!B:B,Tabela4[[#This Row],[Cabo]],'Lançamento de Cabos'!C:C)) | O575: =IFERROR(IF(Tabela4[[#This Row],[Compr. Lançado]]/Tabela4[[#This Row],[Compr. Prev.]]>1,1,Tabela4[[#This Row],[Compr. Lançado]]/Tabela4[[#This Row],[Compr. Prev.]]),"") | P575: =IFERROR(VLOOKUP(Tabela4[[#This Row],[Cabo]],BD!A:V,11,0),"") | Q575: =IFERROR(VLOOKUP(Tabela4[[#This Row],[Cabo]],BD!A:V,12,0),"") | R575: =IF(Tabela4[[#This Row],[Cabo]]<>"",IFERROR(VLOOKUP(Tabela4[[#This Row],[Cabo]]&"-1",'Lançamento de Cabos'!$S:$T,2,0),IF(VLOOKUP(Tabela4[[#This Row],[Cabo]],BD!A:V,13,0)="---","---","")),"") | S575: =IF(Tabela4[[#This Row],[Cabo]]<>"",IFERROR(VLOOKUP(Tabela4[[#This Row],[Cabo]]&"-2",'Lançamento de Cabos'!$S:$T,2,0),IF(VLOOKUP(Tabela4[[#This Row],[Cabo]],BD!A:V,14,0)="---","---","")),"") | T575: =IF(Tabela4[[#This Row],[Cabo]]<>"",IFERROR(VLOOKUP(Tabela4[[#This Row],[Cabo]]&"-3",'Lançamento de Cabos'!$S:$T,2,0),IF(VLOOKUP(Tabela4[[#This Row],[Cabo]],BD!A:V,15,0)="---","---","")),"") | U575: =IF(Tabela4[[#This Row],[Cabo]]<>"",IFERROR(VLOOKUP(Tabela4[[#This Row],[Cabo]]&"-4",'Lançamento de Cabos'!$S:$T,2,0),IF(VLOOKUP(Tabela4[[#This Row],[Cabo]],BD!A:V,16,0)="---","---","")),"") | V575: =IF(Tabela4[[#This Row],[Cabo]]<>"",4-COUNTIF(Tabela4[[#This Row],[Teste de Continuidade]:[Hipot]],"---"),"") | W575: =IF(Tabela4[[#This Row],[Cabo]]<>"",(COUNTIF(Tabela4[[#This Row],[Teste de Continuidade]:[Hipot]],"OK"))/(4-COUNTIF(Tabela4[[#This Row],[Teste de Continuidade]:[Hipot]],"---")),"") | X575: =IF(Tabela4[[#This Row],[Cabo]]<>"",SUMIFS('Lançamento de Cabos'!$AF:$AF,'Lançamento de Cabos'!AE:AE,Tabela4[[#This Row],[Cabo]],'Lançamento de Cabos'!AJ:AJ,Área!$B$1),"") | Y575: =IF(Tabela4[[#This Row],[Cabo]]<>"",SUMIFS('Lançamento de Cabos'!$AG:$AG,'Lançamento de Cabos'!AE:AE,Tabela4[[#This Row],[Cabo]],'Lançamento de Cabos'!AJ:AJ,Área!$B$1),"") | Z575: =VLOOKUP(Tabela4[[#This Row],[Cabo]],BD!A:AB,28,0) -> #N/A

Sheet Dashboard
H1: Lançamento de Cabos - Projeto Vesta
B6: Lançamento de Cabos - Geral | R6: Selecionar Área: | V6: FIBRA | AH6: ESCOPO - Listas de Cabos
R7: ="Lançamento de Cabos - Área - "&V6 -> Lançamento de Cabos - Área - FIBRA | AH7: Lista de Cabos | AO7: Total (m) | AQ7: Lançado (m) | AS7: %
B8: =Indicadores!M7 -> 0.90391169 | F8: Tipo | H8: Qtde Total | J8: Qtde Lançada | L8: % | N8: Saldo | R8: =Indicadores!M15 -> 0.75380898 | V8: Tipo | X8: Qtde Total | Z8: Qtde Lançada | AB8: % | AD8: Saldo | AH8: =CONCATENATE(Indicadores!A10,"-Rev.",Indicadores!B10) -> BK-SP54-00200-LC-80-00699_00000-Rev.2 | AO8: =Indicadores!C10 -> 230 | AQ8: =Indicadores!D10 -> 230 | AS8: =Indicadores!E10 -> 1
F9: Força | H9: =Indicadores!K3 -> 52918 | J9: =Indicadores!L3 -> 49068 | L9: =Indicadores!M3 -> 0.92724593 | N9: =Indicadores!N3 -> 3850 | V9: Força | X9: =IF($V$6="Geral",Indicadores!K3,Indicadores!K11) -> 0 | Z9: =IF($V$6="Geral",Indicadores!L3,Indicadores!L11) -> 0 | AB9: =IF($V$6="Geral",Indicadores!M3,Indicadores!M11) -> 0 | AD9: =IF($V$6="Geral",Indicadores!N3,Indicadores!N11) -> 0 | AH9: =CONCATENATE(Indicadores!A11,"-Rev.",Indicadores!B11) -> BK-SP54-00200-LC-81-00001_00000-Rev.6 | AO9: =Indicadores!C11 -> 5510 | AQ9: =Indicadores!D11 -> 5510 | AS9: =Indicadores!E11 -> 1
AH10: =CONCATENATE(Indicadores!A12,"-Rev.",Indicadores!B12) -> BK-SP54-00350-LC-80-00006_00000-Rev.6 | AO10: =Indicadores!C12 -> 6698 | AQ10: =Indicadores!D12 -> 6698 | AS10: =Indicadores!E12 -> 1
F11: Controle | H11: =Indicadores!K4 -> 37825 | J11: =Indicadores!L4 -> 34991 | L11: =Indicadores!M4 -> 0.92507601 | N11: =Indicadores!N4 -> 2834 | V11: Controle | X11: =IF($V$6="Geral",Indicadores!K4,Indicadores!K12) -> 0 | Z11: =IF($V$6="Geral",Indicadores!L4,Indicadores!L12) -> 0 | AB11: =IF($V$6="Geral",Indicadores!M4,Indicadores!M12) -> 0 | AD11: =IF($V$6="Geral",Indicadores!N4,Indicadores!N12) -> 0 | AH11: =CONCATENATE(Indicadores!A13,"-Rev.",Indicadores!B13) -> BK-SP54-00350-LC-80-00059_00000-Rev.2 | AO11: =Indicadores!C13 -> 100 | AQ11: =Indicadores!D13 -> 0 | AS11: =Indicadores!E13 -> 0
AH12: =CONCATENATE(Indicadores!A14,"-Rev.",Indicadores!B14) -> BK-SP54-01200-LC-80-00004_00000-Rev.10 | AO12: =Indicadores!C14 -> 5996 | AQ12: =Indicadores!D14 -> 5996 | AS12: =Indicadores!E14 -> 1
F13: Fibra Ótica | H13: =Indicadores!K5 -> 12208 | J13: =Indicadores!L5 -> 9202.5 | L13: =Indicadores!M5 -> 0.75380898 | N13: =Indicadores!N5 -> 3005.5 | V13: Fibra Ótica | X13: =IF($V$6="Geral",Indicadores!K5,Indicadores!K13) -> 12208 | Z13: =IF($V$6="Geral",Indicadores!L5,Indicadores!L13) -> 9202.5 | AB13: =IF($V$6="Geral",Indicadores!M5,Indicadores!M13) -> 0.75380898 | AD13: =IF($V$6="Geral",Indicadores!N5,Indicadores!N13) -> 3005.5 | AH13: =CONCATENATE(Indicadores!A15,"-Rev.",Indicadores!B15) -> BK-SP54-0900A-LC-74-00001_00000-Rev.5 | AO13: =Indicadores!C15 -> 58185 | AQ13: =Indicadores!D15 -> 50577 | AS13: =Indicadores!E15 -> 0.86924465
AH14: =CONCATENATE(Indicadores!A16,"-Rev.",Indicadores!B16) -> BK-SP54-0900A-LC-80-00168_00000-Rev.7 | AO14: =Indicadores!C16 -> 20 | AQ14: =Indicadores!D16 -> 0 | AS14: =Indicadores!E16 -> 0
F15: Rede | H15: =Indicadores!K6 -> 776.5 | J15: =Indicadores!L6 -> 499 | L15: =Indicadores!M6 -> 0.64262717 | N15: =Indicadores!N6 -> 277.5 | V15: Rede | X15: =IF($V$6="Geral",Indicadores!K6,Indicadores!K14) -> 0 | Z15: =IF($V$6="Geral",Indicadores!L6,Indicadores!L14) -> 0 | AB15: =IF($V$6="Geral",Indicadores!M6,Indicadores!M14) -> 0 | AD15: =IF($V$6="Geral",Indicadores!N6,Indicadores!N14) -> 0 | AH15: =CONCATENATE(Indicadores!A17,"-Rev.",Indicadores!B17) -> BK-SP54-0900A-LC-80-00177_00000-Rev.4 | AO15: =Indicadores!C17 -> 20 | AQ15: =Indicadores!D17 -> 0 | AS15: =Indicadores!E17 -> 0
AH16: =CONCATENATE(Indicadores!A18,"-Rev.",Indicadores!B18) -> BK-SP54-0900A-LC-80-00178_00000-Rev.3 | AO16: =Indicadores!C18 -> 25 | AQ16: =Indicadores!D18 -> 0 | AS16: =Indicadores!E18 -> 0
F17: Geral | H17: =Indicadores!K7 -> 103727.5 | J17: =Indicadores!L7 -> 93760.5 | L17: =Indicadores!M7 -> 0.90391169 | N17: =Indicadores!N7 -> 9967 | V17: Geral | X17: =IF(V6="Geral",Indicadores!K7,Indicadores!K15) -> 12208 | Z17: =IF($V$6="Geral",Indicadores!L7,Indicadores!L15) -> 9202.5 | AB17: =IF($V$6="Geral",Indicadores!M7,Indicadores!M15) -> 0.75380898 | AD17: =IF($V$6="Geral",Indicadores!N7,Indicadores!N15) -> 3005.5 | AH17: =CONCATENATE(Indicadores!A19,"-Rev.",Indicadores!B19) -> BK-SP54-0900A-LC-80-00179_00000-Rev.4 | AO17: =Indicadores!C19 -> 22 | AQ17: =Indicadores!D19 -> 0 | AS17: =Indicadores!E19 -> 0
AH18: =CONCATENATE(Indicadores!A20,"-Rev.",Indicadores!B20) -> BK-SP54-0900A-LC-80-00180_00000-Rev.4 | AO18: =Indicadores!C20 -> 22 | AQ18: =Indicadores!D20 -> 0 | AS18: =Indicadores!E20 -> 0
AH19: =CONCATENATE(Indicadores!A21,"-Rev.",Indicadores!B21) -> BK-SP54-0900A-LC-80-00185_00000-Rev.2 | AO19: =Indicadores!C21 -> 470 | AQ19: =Indicadores!D21 -> 470 | AS19: =Indicadores!E21 -> 1
B20: Lançamento de Cabos - Aterramento | R20: ="Testes e Ligações - "&V6 -> Testes e Ligações - FIBRA | AH20: =CONCATENATE(Indicadores!A22,"-Rev.",Indicadores!B22) -> BK-SP54-0900A-LC-80-00186_00000-Rev.3 | AO20: =Indicadores!C22 -> 1607 | AQ20: =Indicadores!D22 -> 1502 | AS20: =Indicadores!E22 -> 0.93466086
AH21: =CONCATENATE(Indicadores!A23,"-Rev.",Indicadores!B23) -> BK-SP54-0900A-LC-80-00187_00000-Rev.2 | AO21: =Indicadores!C23 -> 1320 | AQ21: =Indicadores!D23 -> 1120 | AS21: =Indicadores!E23 -> 0.84848485
B22: =L27 -> 0.88364865 | F22: Tipo | H22: Qtde Total | J22: Qtde Lançada | L22: % | N22: Saldo | R22: Avanço | V22: Tipo | X22: Total | Z22: Realizado | AB22: % | AD22: Saldo | AH22: =CONCATENATE(Indicadores!A24,"-Rev.",Indicadores!B24) -> BK-SP54-0900A-LC-80-00188_00000-Rev.2 | AO22: =Indicadores!C24 -> 3248 | AQ22: =Indicadores!D24 -> 2958 | AS22: =Indicadores!E24 -> 0.91071429
F23: 70 mm² 19 Fios | H23: =Indicadores!K18 -> 5700 | J23: =Indicadores!L18 -> 5239 | L23: =Indicadores!M18 -> 0.50755668 | N23: =Indicadores!N18 -> 461 | V23: Teste Cont. | X23: =Indicadores!K23 -> 7 | Z23: =Indicadores!L23 -> 0 | AB23: =Indicadores!M23 -> 0 | AD23: =Indicadores!N23 -> 7 | AH23: =CONCATENATE(Indicadores!A25,"-Rev.",Indicadores!B25) -> BK-SP54-0900A-LC-90-00004_00000-Rev.2 | AO23: =Indicadores!C25 -> 2959.5 | AQ23: =Indicadores!D25 -> 1669.5 | AS23: =Indicadores!E25 -> 0.56411556
V24: Born a Born | X24: =Indicadores!K24 -> 7 | Z24: =Indicadores!L24 -> 0 | AB24: =Indicadores!M24 -> 0 | AD24: =Indicadores!N24 -> 7 | AH24: =CONCATENATE(Indicadores!A26,"-Rev.",Indicadores!B26) -> BK-SP54-0900B-LC-74-00004_00000-Rev.2 | AO24: =Indicadores!C26 -> 12895 | AQ24: =Indicadores!D26 -> 12895 | AS24: =Indicadores!E26 -> 1
F25: 25 mm² 7 Fios | H25: =Indicadores!K19 -> 1700 | J25: =Indicadores!L19 -> 1300 | L25: =Indicadores!M19 -> 0.76470588 | N25: =Indicadores!N19 -> 400 | V25: Megger | X25: =Indicadores!K25 -> 0 | Z25: =Indicadores!L25 -> 0 | AB25: =Indicadores!M25 -> 0 | AD25: =Indicadores!N25 -> 0 | AH25: =CONCATENATE(Indicadores!A27,"-Rev.",Indicadores!B27) -> BK-SP54-0900B-LC-80-00155_00000-Rev.2 | AO25: =Indicadores!C27 -> 1250 | AQ25: =Indicadores!D27 -> 1000 | AS25: =Indicadores!E27 -> 0.8
V26: Hipot | X26: =Indicadores!K26 -> 0 | Z26: =Indicadores!L26 -> 0 | AB26: =Indicadores!M26 -> 0 | AD26: =Indicadores!N26 -> 0 | AH26: =CONCATENATE(Indicadores!A28,"-Rev.",Indicadores!B28) -> BK-SP54-0900B-LC-90-00010_00000-Rev.1 | AO26: =Indicadores!C28 -> 879 | AQ26: =Indicadores!D28 -> 864 | AS26: =Indicadores!E28 -> 0.98293515
F27: Geral | H27: =Indicadores!K20 -> 7400 | J27: =Indicadores!L20 -> 6539 | L27: =Indicadores!M20 -> 0.88364865 | N27: =Indicadores!N20 -> 861 | V27: Ligações | X27: =Indicadores!K27 -> 218 | Z27: =Indicadores!L27 -> 36 | AB27: =Indicadores!M27 -> 0.16513761 | AD27: =Indicadores!N27 -> 182 | AH27: =CONCATENATE(Indicadores!A29,"-Rev.",Indicadores!B29) -> E5WP000490-C-001-LC003-Rev.2 | AO27: =Indicadores!C29 -> 1949 | AQ27: =Indicadores!D29 -> 1949 | AS27: =Indicadores!E29 -> 1
AH28: =CONCATENATE(Indicadores!A30,"-Rev.",Indicadores!B30) -> E5WP000490-C-001-LC004-Rev.2 | AO28: =Indicadores!C30 -> 322 | AQ28: =Indicadores!D30 -> 322 | AS28: =Indicadores!E30 -> 1
AH29: Total | AO29: =SUM(AO7:AP28) -> 103727.5 | AQ29: =SUM(AQ7:AR28) -> 93760.5 | AS29: =AQ29/AO29 -> 0.90391169
B31: ="Acompanhamento - Lançamento de Cabos - "&V6 -> Acompanhamento - Lançamento de Cabos - FIBRA
C54: =IF($V$6="Geral","Status Geral de Cabos","Status Geral de Cabos - Área - "&$V$6) -> Status Geral de Cabos - Área - FIBRA
C55: Circuito | G55: Tipo | I55: Formação | K55: Tensão | M55: Isolamento | O55: Lances Totais | Q55: Lances Realizados | S55: Compr. Total | U55: Compr. Lançado | W55: Compr. Real | Y55: % Lanç | Z55: DE | AD55: PARA | AH55: Teste Cont. | AJ55: Born a Born | AL55: Megger | AN55: Hipot | AP55: Status Liberação | AR55: Ligações Realizadas
C56: =Área!C2 -> 1HVBUS3-ER1HV-001C | G56: =Área!F2 -> FO | I56: =Área!G2 -> CORDÃO ÓPTICO | K56: =Área!H2 -> - | M56: =Área!I2 -> - | O56: =Área!J2 -> 1 | Q56: =Área!K2 -> 1 | S56: =Área!L2 -> 40 | U56: =Área!N2 -> 40 | W56: =Área!M2 -> 40 | Y56: =Área!O2 -> 1 | Z56: =Área!P2 -> 1HV-BUS3 | AD56: =Área!Q2 -> ER-3 | AH56: =Área!R2 -> --- | AJ56: =Área!S2 -> --- | AL56: =Área!T2 -> --- | AN56: =Área!U2 -> --- | AP56: =IFERROR(Área!Z2,"") -> Disponível | AR56: =Área!Y2 -> 0
C57: =Área!C3 -> 1HVBUS3-ER1HV-002C | G57: =Área!F3 -> FO | I57: =Área!G3 -> CORDÃO ÓPTICO | K57: =Área!H3 -> - | M57: =Área!I3 -> - | O57: =Área!J3 -> 1 | Q57: =Área!K3 -> 1 | S57: =Área!L3 -> 40 | U57: =Área!N3 -> 40 | W57: =Área!M3 -> 40 | Y57: =Área!O3 -> 1 | Z57: =Área!P3 -> 1HV-BUS3 | AD57: =Área!Q3 -> ER-3 | AH57: =Área!R3 -> --- | AJ57: =Área!S3 -> --- | AL57: =Área!T3 -> --- | AN57: =Área!U3 -> --- | AP57: =IFERROR(Área!Z3,"") -> Disponível | AR57: =Área!Y3 -> 0
C58: =Área!C4 -> 1HVBUS3-ER1HV-003C | G58: =Área!F4 -> FO | I58: =Área!G4 -> CORDÃO ÓPTICO | K58: =Área!H4 -> - | M58: =Área!I4 -> - | O58: =Área!J4 -> 1 | Q58: =Área!K4 -> 1 | S58: =Área!L4 -> 40 | U58: =Área!N4 -> 40 | W58: =Área!M4 -> 40 | Y58: =Área!O4 -> 1 | Z58: =Área!P4 -> 1HV-BUS3 | AD58: =Área!Q4 -> ER-3 | AH58: =Área!R4 -> --- | AJ58: =Área!S4 -> --- | AL58: =Área!T4 -> --- | AN58: =Área!U4 -> --- | AP58: =IFERROR(Área!Z4,"") -> Disponível | AR58: =Área!Y4 -> 0
C59: =Área!C5 -> 1HVBUS3-ER1HV-004C | G59: =Área!F5 -> FO | I59: =Área!G5 -> CORDÃO ÓPTICO | K59: =Área!H5 -> - | M59: =Área!I5 -> - | O59: =Área!J5 -> 1 | Q59: =Área!K5 -> 1 | S59: =Área!L5 -> 40 | U59: =Área!N5 -> 40 | W59: =Área!M5 -> 40 | Y59: =Área!O5 -> 1 | Z59: =Área!P5 -> 1HV-BUS3 | AD59: =Área!Q5 -> ER-3 | AH59: =Área!R5 -> --- | AJ59: =Área!S5 -> --- | AL59: =Área!T5 -> --- | AN59: =Área!U5 -> --- | AP59: =IFERROR(Área!Z5,"") -> Disponível | AR59: =Área!Y5 -> 0
C60: =Área!C6 -> 1HVBUS3-ER1HV-005C | G60: =Área!F6 -> FO | I60: =Área!G6 -> CORDÃO ÓPTICO | K60: =Área!H6 -> - | M60: =Área!I6 -> - | O60: =Área!J6 -> 1 | Q60: =Área!K6 -> 1 | S60: =Área!L6 -> 40 | U60: =Área!N6 -> 40 | W60: =Área!M6 -> 40 | Y60: =Área!O6 -> 1 | Z60: =Área!P6 -> 1HV-BUS3 | AD60: =Área!Q6 -> ER-3 | AH60: =Área!R6 -> --- | AJ60: =Área!S6 -> --- | AL60: =Área!T6 -> --- | AN60: =Área!U6 -> --- | AP60: =IFERROR(Área!Z6,"") -> Disponível | AR60: =Área!Y6 -> 0
C61: =Área!C7 -> CBO001-SEL | G61: =Área!F7 -> FO | I61: =Área!G7 -> CORDÃO ÓPTICO | K61: =Área!H7 -> - | M61: =Área!I7 -> - | O61: =Área!J7 -> 1 | Q61: =Área!K7 | S61: =Área!L7 -> 20 | U61: =Área!N7 | W61: =Área!M7 -> 20 | Y61: =Área!O7 | Z61: =Área!P7 -> ER-3 | AD61: =Área!Q7 -> ER-4 | AH61: =Área!R7 -> --- | AJ61: =Área!S7 -> --- | AL61: =Área!T7 -> --- | AN61: =Área!U7 -> --- | AP61: =IFERROR(Área!Z7,"") -> Pend. Compra | AR61: =Área!Y7 -> 0
C62: =Área!C8 -> CDC-02290 | G62: =Área!F8 -> FO | I62: =Área!G8 -> CORDÃO ÓPTICO | K62: =Área!H8 -> - | M62: =Área!I8 -> - | O62: =Área!J8 -> 1 | Q62: =Área!K8 -> 1 | S62: =Área!L8 -> 2.5 | U62: =Área!N8 -> 2.5 | W62: =Área!M8 -> 2.5 | Y62: =Área!O8 -> 1 | Z62: =Área!P8 -> DIO-120-104 (30LV) | AD62: =Área!Q8 -> SWT-120-105 (30LV) | AH62: =Área!R8 -> --- | AJ62: =Área!S8 -> --- | AL62: =Área!T8 -> --- | AN62: =Área!U8 -> --- | AP62: =IFERROR(Área!Z8,"") -> Disponível | AR62: =Área!Y8 -> 0
C63: =Área!C9 -> CDC-02331 | G63: =Área!F9 -> FO | I63: =Área!G9 -> CORDÃO ÓPTICO | K63: =Área!H9 -> - | M63: =Área!I9 -> - | O63: =Área!J9 -> 1 | Q63: =Área!K9 -> 1 | S63: =Área!L9 -> 5 | U63: =Área!N9 -> 5 | W63: =Área!M9 -> 5 | Y63: =Área!O9 -> 1 | Z63: =Área!P9 -> PI-1205 (ACESSO REMOTO) | AD63: =Área!Q9 -> SWT-120-105 (30LV) | AH63: =Área!R9 -> --- | AJ63: =Área!S9 -> --- | AL63: =Área!T9 -> --- | AN63: =Área!U9 -> --- | AP63: =IFERROR(Área!Z9,"") -> Disponível | AR63: =Área!Y9 -> 0
C64: =Área!C10 -> 7HV-1HV-001C | G64: =Área!F10 -> FO | I64: =Área!G10 -> CABO ÓPTICO 4 VIAS | K64: =Área!H10 -> - | M64: =Área!I10 -> - | O64: =Área!J10 -> 1 | Q64: =Área!K10 -> 1 | S64: =Área!L10 -> 450 | U64: =Área!N10 -> 450 | W64: =Área!M10 -> 450 | Y64: =Área!O10 -> 1 | Z64: =Área!P10 -> 7HV | AD64: =Área!Q10 -> REMOTA 1HV | AH64: =Área!R10 -> --- | AJ64: =Área!S10 -> --- | AL64: =Área!T10 -> --- | AN64: =Área!U10 -> --- | AP64: =IFERROR(Área!Z10,"") -> Disponível | AR64: =Área!Y10 -> 0
C65: =Área!C11 -> CBO005-RS | G65: =Área!F11 -> FO | I65: =Área!G11 -> CABO ÓPTICO 4 VIAS | K65: =Área!H11 -> - | M65: =Área!I11 -> - | O65: =Área!J11 -> 1 | Q65: =Área!K11 -> 1 | S65: =Área!L11 -> 450 | U65: =Área!N11 -> 450 | W65: =Área!M11 -> 450 | Y65: =Área!O11 -> 1 | Z65: =Área!P11 -> PSDC2-DIO | AD65: =Área!Q11 -> PSDC4-DIO1 | AH65: =Área!R11 -> --- | AJ65: =Área!S11 -> --- | AL65: =Área!T11 -> --- | AN65: =Área!U11 -> --- | AP65: =IFERROR(Área!Z11,"") -> Disponível | AR65: =Área!Y11 -> 8
C66: =Área!C12 -> CDC-12009 | G66: =Área!F12 -> FO | I66: =Área!G12 -> FIBRA OPTICA SM 6 PARES | K66: =Área!H12 -> - | M66: =Área!I12 -> - | O66: =Área!J12 -> 1 | Q66: =Área!K12 -> 1 | S66: =Área!L12 -> 125 | U66: =Área!N12 -> 148 | W66: =Área!M12 -> 148 | Y66: =Área!O12 -> 1 | Z66: =Área!P12 -> RACK 7HV - RCK-120-102 | AD66: =Área!Q12 -> RCK-120-103 - RACK 30LV | AH66: =Área!R12 -> --- | AJ66: =Área!S12 -> --- | AL66: =Área!T12 -> --- | AN66: =Área!U12 -> --- | AP66: =IFERROR(Área!Z12,"") -> Disponível | AR66: =Área!Y12 -> 0
C67: =Área!C13 -> CDC-12007 | G67: =Área!F13 -> FO | I67: =Área!G13 -> FIBRA OPTICA SM 6 PARES | K67: =Área!H13 -> - | M67: =Área!I13 -> - | O67: =Área!J13 -> 1 | Q67: =Área!K13 -> 1 | S67: =Área!L13 -> 220 | U67: =Área!N13 -> 350 | W67: =Área!M13 -> 350 | Y67: =Área!O13 -> 1 | Z67: =Área!P13 -> DIO-120-104 (RCK-120-102) / ELETROCENTRO MOTORIZAÇÃO | AD67: =Área!Q13 -> DIO-CCP-104 (RCK-CCP-101) / CCP | AH67: =Área!R13 -> --- | AJ67: =Área!S13 -> --- | AL67: =Área!T13 -> --- | AN67: =Área!U13 -> --- | AP67: =IFERROR(Área!Z13,"") -> Disponível | AR67: =Área!Y13 -> 0
... C515: =Área!C461 | G515: =Área!F461 | I515: =Área!G461 | K515: =Área!H461 | M515: =Área!I461 | O515: =Área!J461 | Q515: =Área!K461 | S515: =Área!L461 | U515: =Área!N461 | W515: =Área!M461 | Y515: =Área!O461 | Z515: =Área!P461 | AD515: =Área!Q461 | AH515: =Área!R461 | AJ515: =Área!S461 | AL515: =Área!T461 | AN515: =Área!U461 | AP515: =IFERROR(Área!Z461,"") | AR515: =Área!Y461

Sheet BD
A1: Tag do Cabo | B1: Tipo | C1: Tensão do Circuito | D1: Classe Isolamento | E1: Formação | F1: Bitola (mm²) | G1: Qtd de Lances | H1: Comprimento Lance | I1: Comprimento Total | J1: Local para Curva de Acomp. | K1: DE | L1: PARA | M1: Teste de Continuidade | N1: Born a Born | O1: Megger | P1: Hipot | Q1: Item Medição | R1: Qtde. Lançada | S1: Qtde Ligações | T1: Lista de Cabos | U1: Revisão | V1: Luvas/Anilhas | W1: ID_Atividade | X1: Data de Solcitação do Cabo | Y1: Data de Liberação dos Cabos | Z1: Histórico | AA1: Bobina | AB1: Disponibilidade | AC1: Programação | AD1: Comprimento Real | AE1: Sinal | AF1: Circuito | AG1: Ligações Realizadas | AH1: %Ligações | AI1: Diagrama de Ligação | AJ1: Folha DI | AK1: NE | AL1: OBS
A2: 125VCC-1HVBUS3-001F | B2: Força | C2: 125 | D2: 0,6/1 | E2: 1x2/C#4 | F2: 4 | G2: 1 | H2: 20 | I2: 20 | J2: 1HV | K2: PAINEL DE 125Vcc (nota 2) | L2: 1HV-BUS3 - PAINEL 13,8kV - ALIM 1 | M2: Sim | N2: --- | O2: ="Sim" -> Sim | P2: --- | Q2: 5.10.2 | R2: =SUMIF('Lançamento de Cabos'!$B:$B,Tabela1[[#This Row],[Tag do Cabo]],'Lançamento de Cabos'!$C:$C) -> 40 | S2: =VLOOKUP(Tabela1[[#This Row],[Tag do Cabo]],'Diagramas Ligações'!A:V,14,0) -> 4 | T2: BK-SP54-0900A-LC-74-00001_00000 | U2: 5 | W2: ELE-0480 | X2: 44177 | Y2: 44218 | Z2: 22/01/2021: Liberação da Bobina, Nota1: Estas bobinas (n.72 e n.207), foram liberadas para Montcalm em 20-11-20, para retirada parcial. | AA2: 72 | AB2: =IF(AND(Tabela1[[#This Row],[Data de Solcitação do Cabo]]<>0,Tabela1[[#This Row],[Bobina]]<>0),"Disponível",IF(AND(Tabela1[[#This Row],[Data de Solcitação do Cabo]]<>0,Tabela1[[#This Row],[Data de Liberação dos Cabos]]=""),"Pend. Resp.",IF(AND(Tabela1[[#This Row],[Data de Solcitação do Cabo]]<>0,Tabela1[[#This Row],[Bobina]]=""),"Pend. Compra","Não Solic."))) -> Disponível | AC2: PR-LC-0004 | AD2: =IF(Tabela1[[#This Row],[Qtde. Lançada]]>Tabela1[[#This Row],[Comprimento Total]],Tabela1[[#This Row],[Qtde. Lançada]],Tabela1[[#This Row],[Comprimento Total]]) -> 40 | AE2: - | AF2: 1HVx1MV | AG2: =SUMIF('Lançamento de Cabos'!AE:AK,Tabela1[[#This Row],[Tag do Cabo]],'Lançamento de Cabos'!AG:AG) -> 0 | AH2: =IFERROR(VLOOKUP(Tabela1[[#This Row],[Tag do Cabo]],'Lançamento de Cabos'!AE:AK,7,0),0) -> 0 | AI2: BK-SP54-0900B-DI-74-00452 | AJ2: 7 | AK2: 330260
A3: 125VCC-PSDC2-001F | B3: Força | C3: 125 | D3: 0,6/1 | E3: 1x2/C#4 | F3: 4 | G3: 1 | H3: 40 | I3: 40 | J3: 1HV | K3: PAINEL DE 125Vcc (nota 2) | L3: PSDC2 - PAINEL DE REJEICAO DE CARGAS 1 | M3: Sim | N3: --- | O3: ="Sim" -> Sim | P3: --- | Q3: 5.10.2 | R3: =SUMIF('Lançamento de Cabos'!$B:$B,Tabela1[[#This Row],[Tag do Cabo]],'Lançamento de Cabos'!$C:$C) -> 40 | S3: =VLOOKUP(Tabela1[[#This Row],[Tag do Cabo]],'Diagramas Ligações'!A:V,14,0) -> 4 | T3: BK-SP54-0900A-LC-74-00001_00000 | U3: 5 | W3: ELE-0480 | X3: 44177 | Y3: 44218 | Z3: 22/01/2021: Liberação da Bobina, Nota1: Estas bobinas (n.72 e n.207), foram liberadas para Montcalm em 20-11-20, para retirada parcial. | AA3: 72 | AB3: =IF(AND(Tabela1[[#This Row],[Data de Solcitação do Cabo]]<>0,Tabela1[[#This Row],[Bobina]]<>0),"Disponível",IF(AND(Tabela1[[#This Row],[Data de Solcitação do Cabo]]<>0,Tabela1[[#This Row],[Data de Liberação dos Cabos]]=""),"Pend. Resp.",IF(AND(Tabela1[[#This Row],[Data de Solcitação do Cabo]]<>0,Tabela1[[#This Row],[Bobina]]=""),"Pend. Compra","Não Solic."))) -> Disponível | AC3: PR-LC-0004 | AD3: =IF(Tabela1[[#This Row],[Qtde. Lançada]]>Tabela1[[#This Row],[Comprimento Total]],Tabela1[[#This Row],[Qtde. Lançada]],Tabela1[[#This Row],[Comprimento Total]]) -> 40 | AE3: - | AF3: 1HVx1MV | AG3: =SUMIF('Lançamento de Cabos'!AE:AK,Tabela1[[#This Row],[Tag do Cabo]],'Lançamento de Cabos'!AG:AG) -> 0 | AH3: =IFERROR(VLOOKUP(Tabela1[[#This Row],[Tag do Cabo]],'Lançamento de Cabos'!AE:AK,7,0),0) -> 0 | AI3: BK-SP54-0900B-DI-74-00450 | AJ3: 25 | AK3: 330260
A4: 1HVBUS3-ER1HV-001C | B4: FO | C4: - | D4: - | E4: CORDÃO ÓPTICO | F4: - | G4: 1 | H4: 40 | I4: 40 | J4: FIBRA | K4: 1HV-BUS3 | L4: ER-3 | M4: --- | N4: --- | O4: --- | P4: --- | Q4: 5.6.1 | R4: =SUMIF('Lançamento de Cabos'!$B:$B,Tabela1[[#This Row],[Tag do Cabo]],'Lançamento de Cabos'!$C:$C) -> 40 | S4: =VLOOKUP(Tabela1[[#This Row],[Tag do Cabo]],'Diagramas Ligações'!A:V,14,0) -> 2 | T4: BK-SP54-0900A-LC-74-00001_00000 | U4: 5 | V4: N/A | W4: ELE-0480 | X4: 44177 | Y4: 44218 | Z4: 22/01/2021: Liberação da Bobina | AA4: NE 3147548 | AB4: =IF(AND(Tabela1[[#This Row],[Data de Solcitação do Cabo]]<>0,Tabela1[[#This Row],[Bobina]]<>0),"Disponível",IF(AND(Tabela1[[#This Row],[Data de Solcitação do Cabo]]<>0,Tabela1[[#This Row],[Data de Liberação dos Cabos]]=""),"Pend. Resp.",IF(AND(Tabela1[[#This Row],[Data de Solcitação do Cabo]]<>0,Tabela1[[#This Row],[Bobina]]=""),"Pend. Compra","Não Solic."))) -> Disponível | AC4: PR-LC-0004 | AD4: =IF(Tabela1[[#This Row],[Qtde. Lançada]]>Tabela1[[#This Row],[Comprimento Total]],Tabela1[[#This Row],[Qtde. Lançada]],Tabela1[[#This Row],[Comprimento Total]]) -> 40 | AE4: - | AF4: 1HV | AG4: =SUMIF('Lançamento de Cabos'!AE:AK,Tabela1[[#This Row],[Tag do Cabo]],'Lançamento de Cabos'!AG:AG) -> 0 | AH4: =IFERROR(VLOOKUP(Tabela1[[#This Row],[Tag do Cabo]],'Lançamento de Cabos'!AE:AK,7,0),0) -> 0 | AI4: BK-SP54-0900B-DI-74-00450 | AJ4: 30 | AK4: 3147548
A5: 1HVBUS3-ER1HV-002C | B5: FO | C5: - | D5: - | E5: CORDÃO ÓPTICO | F5: - | G5: 1 | H5: 40 | I5: 40 | J5: FIBRA | K5: 1HV-BUS3 | L5: ER-3 | M5: --- | N5: --- | O5: --- | P5: --- | Q5: 5.6.1 | R5: =SUMIF('Lançamento de Cabos'!$B:$B,Tabela1[[#This Row],[Tag do Cabo]],'Lançamento de Cabos'!$C:$C) -> 40 | S5: =VLOOKUP(Tabela1[[#This Row],[Tag do Cabo]],'Diagramas Ligações'!A:V,14,0) -> 2 | T5: BK-SP54-0900A-LC-74-00001_00000 | U5: 5 | V5: N/A | W5: ELE-0480 | X5: 44177 | Y5: 44218 | Z5: 22/01/2021: Liberação da Bobina | AA5: NE 3147548 | AB5: =IF(AND(Tabela1[[#This Row],[Data de Solcitação do Cabo]]<>0,Tabela1[[#This Row],[Bobina]]<>0),"Disponível",IF(AND(Tabela1[[#This Row],[Data de Solcitação do Cabo]]<>0,Tabela1[[#This Row],[Data de Liberação dos Cabos]]=""),"Pend. Resp.",IF(AND(Tabela1[[#This Row],[Data de Solcitação do Cabo]]<>0,Tabela1[[#This Row],[Bobina]]=""),"Pend. Compra","Não Solic."))) -> Disponível | AC5: PR-LC-0004 | AD5: =IF(Tabela1[[#This Row],[Qtde. Lançada]]>Tabela1[[#This Row],[Comprimento Total]],Tabela1[[#This Row],[Qtde. Lançada]],Tabela1[[#This Row],[Comprimento Total]]) -> 40 | AE5: - | AF5: 1HV | AG5: =SUMIF('Lançamento de Cabos'!AE:AK,Tabela1[[#This Row],[Tag do Cabo]],'Lançamento de Cabos'!AG:AG) -> 0 | AH5: =IFERROR(VLOOKUP(Tabela1[[#This Row],[Tag do Cabo]],'Lançamento de Cabos'!AE:AK,7,0),0) -> 0 | AI5: BK-SP54-0900B-DI-74-00450 | AJ5: 30 | AK5: 3147548
A6: 1HVBUS3-ER1HV-003C | B6: FO | C6: - | D6: - | E6: CORDÃO ÓPTICO | F6: - | G6: 1 | H6: 40 | I6: 40 | J6: FIBRA | K6: 1HV-BUS3 | L6: ER-3 | M6: --- | N6: --- | O6: --- | P6: --- | Q6: 5.6.1 | R6: =SUMIF('Lançamento de Cabos'!$B:$B,Tabela1[[#This Row],[Tag do Cabo]],'Lançamento de Cabos'!$C:$C) -> 40 | S6: =VLOOKUP(Tabela1[[#This Row],[Tag do Cabo]],'Diagramas Ligações'!A:V,14,0) -> 2 | T6: BK-SP54-0900A-LC-74-00001_00000 | U6: 5 | V6: N/A | W6: ELE-0480 | X6: 44177 | Y6: 44218 | Z6: 22/01/2021: Liberação da Bobina | AA6: NE 3147548 | AB6: =IF(AND(Tabela1[[#This Row],[Data de Solcitação do Cabo]]<>0,Tabela1[[#This Row],[Bobina]]<>0),"Disponível",IF(AND(Tabela1[[#This Row],[Data de Solcitação do Cabo]]<>0,Tabela1[[#This Row],[Data de Liberação dos Cabos]]=""),"Pend. Resp.",IF(AND(Tabela1[[#This Row],[Data de Solcitação do Cabo]]<>0,Tabela1[[#This Row],[Bobina]]=""),"Pend. Compra","Não Solic."))) -> Disponível | AC6: PR-LC-0004 | AD6: =IF(Tabela1[[#This Row],[Qtde. Lançada]]>Tabela1[[#This Row],[Comprimento Total]],Tabela1[[#This Row],[Qtde. Lançada]],Tabela1[[#This Row],[Comprimento Total]]) -> 40 | AE6: - | AF6: 1HV | AG6: =SUMIF('Lançamento de Cabos'!AE:AK,Tabela1[[#This Row],[Tag do Cabo]],'Lançamento de Cabos'!AG:AG) -> 0 | AH6: =IFERROR(VLOOKUP(Tabela1[[#This Row],[Tag do Cabo]],'Lançamento de Cabos'!AE:AK,7,0),0) -> 0 | AI6: BK-SP54-0900B-DI-74-00450 | AJ6: 30 | AK6: 3147548
A7: 1HVBUS3-ER1HV-004C | B7: FO | C7: - | D7: - | E7: CORDÃO ÓPTICO | F7: - | G7: 1 | H7: 40 | I7: 40 | J7: FIBRA | K7: 1HV-BUS3 | L7: ER-3 | M7: --- | N7: --- | O7: --- | P7: --- | Q7: 5.6.1 | R7: =SUMIF('Lançamento de Cabos'!$B:$B,Tabela1[[#This Row],[Tag do Cabo]],'Lançamento de Cabos'!$C:$C) -> 40 | S7: =VLOOKUP(Tabela1[[#This Row],[Tag do Cabo]],'Diagramas Ligações'!A:V,14,0) -> 2 | T7: BK-SP54-0900A-LC-74-00001_00000 | U7: 5 | V7: N/A | W7: ELE-0480 | X7: 44177 | Y7: 44218 | Z7: 22/01/2021: Liberação da Bobina | AA7: NE 3147548 | AB7: =IF(AND(Tabela1[[#This Row],[Data de Solcitação do Cabo]]<>0,Tabela1[[#This Row],[Bobina]]<>0),"Disponível",IF(AND(Tabela1[[#This Row],[Data de Solcitação do Cabo]]<>0,Tabela1[[#This Row],[Data de Liberação dos Cabos]]=""),"Pend. Resp.",IF(AND(Tabela1[[#This Row],[Data de Solcitação do Cabo]]<>0,Tabela1[[#This Row],[Bobina]]=""),"Pend. Compra","Não Solic."))) -> Disponível | AC7: PR-LC-0004 | AD7: =IF(Tabela1[[#This Row],[Qtde. Lançada]]>Tabela1[[#This Row],[Comprimento Total]],Tabela1[[#This Row],[Qtde. Lançada]],Tabela1[[#This Row],[Comprimento Total]]) -> 40 | AE7: - | AF7: 1HV | AG7: =SUMIF('Lançamento de Cabos'!AE:AK,Tabela1[[#This Row],[Tag do Cabo]],'Lançamento de Cabos'!AG:AG) -> 0 | AH7: =IFERROR(VLOOKUP(Tabela1[[#This Row],[Tag do Cabo]],'Lançamento de Cabos'!AE:AK,7,0),0) -> 0 | AI7: BK-SP54-0900B-DI-74-00450 | AJ7: 30 | AK7: 3147548
A8: 1HVBUS3-ER1HV-005C | B8: FO | C8: - | D8: - | E8: CORDÃO ÓPTICO | F8: - | G8: 1 | H8: 40 | I8: 40 | J8: FIBRA | K8: 1HV-BUS3 | L8: ER-3 | M8: --- | N8: --- | O8: --- | P8: --- | Q8: 5.6.1 | R8: =SUMIF('Lançamento de Cabos'!$B:$B,Tabela1[[#This Row],[Tag do Cabo]],'Lançamento de Cabos'!$C:$C) -> 40 | S8: =VLOOKUP(Tabela1[[#This Row],[Tag do Cabo]],'Diagramas Ligações'!A:V,14,0) -> 2 | T8: BK-SP54-0900A-LC-74-00001_00000 | U8: 5 | V8: N/A | W8: ELE-0480 | X8: 44177 | Y8: 44218 | Z8: 22/01/2021: Liberação da Bobina | AA8: NE 3147548 | AB8: =IF(AND(Tabela1[[#This Row],[Data de Solcitação do Cabo]]<>0,Tabela1[[#This Row],[Bobina]]<>0),"Disponível",IF(AND(Tabela1[[#This Row],[Data de Solcitação do Cabo]]<>0,Tabela1[[#This Row],[Data de Liberação dos Cabos]]=""),"Pend. Resp.",IF(AND(Tabela1[[#This Row],[Data de Solcitação do Cabo]]<>0,Tabela1[[#This Row],[Bobina]]=""),"Pend. Compra","Não Solic."))) -> Disponível | AC8: PR-LC-0004 | AD8: =IF(Tabela1[[#This Row],[Qtde. Lançada]]>Tabela1[[#This Row],[Comprimento Total]],Tabela1[[#This Row],[Qtde. Lançada]],Tabela1[[#This Row],[Comprimento Total]]) -> 40 | AE8: - | AF8: 1HV | AG8: =SUMIF('Lançamento de Cabos'!AE:AK,Tabela1[[#This Row],[Tag do Cabo]],'Lançamento de Cabos'!AG:AG) -> 0 | AH8: =IFERROR(VLOOKUP(Tabela1[[#This Row],[Tag do Cabo]],'Lançamento de Cabos'!AE:AK,7,0),0) -> 0 | AI8: BK-SP54-0900B-DI-74-00450 | AJ8: 30 | AK8: 3147548
A9: 220V-1HVBUS3-001F | B9: Força | C9: 127 | D9: 0,6/1 | E9: 1x2/C#4 | F9: 4 | G9: 1 | H9: 40 | I9: 40 | J9: 1HV | K9: PAINEL DE 220/127V (nota 2) | L9: 1HV-BUS3 - PAINEL 13,8kV | M9: Sim | N9: --- | O9: ="Sim" -> Sim | P9: --- | Q9: 5.10.2 | R9: =SUMIF('Lançamento de Cabos'!$B:$B,Tabela1[[#This Row],[Tag do Cabo]],'Lançamento de Cabos'!$C:$C) -> 40 | S9: =VLOOKUP(Tabela1[[#This Row],[Tag do Cabo]],'Diagramas Ligações'!A:V,14,0) -> 4 | T9: BK-SP54-0900A-LC-74-00001_00000 | U9: 5 | W9: ELE-0480 | X9: 44177 | Y9: 44218 | Z9: 22/01/2021: Liberação da Bobina, Nota1: Estas bobinas (n.72 e n.207), foram liberadas para Montcalm em 20-11-20, para retirada parcial. | AA9: 72 | AB9: =IF(AND(Tabela1[[#This Row],[Data de Solcitação do Cabo]]<>0,Tabela1[[#This Row],[Bobina]]<>0),"Disponível",IF(AND(Tabela1[[#This Row],[Data de Solcitação do Cabo]]<>0,Tabela1[[#This Row],[Data de Liberação dos Cabos]]=""),"Pend. Resp.",IF(AND(Tabela1[[#This Row],[Data de Solcitação do Cabo]]<>0,Tabela1[[#This Row],[Bobina]]=""),"Pend. Compra","Não Solic."))) -> Disponível | AC9: PR-LC-0004 | AD9: =IF(Tabela1[[#This Row],[Qtde. Lançada]]>Tabela1[[#This Row],[Comprimento Total]],Tabela1[[#This Row],[Qtde. Lançada]],Tabela1[[#This Row],[Comprimento Total]]) -> 40 | AE9: - | AF9: 1HV | AG9: =SUMIF('Lançamento de Cabos'!AE:AK,Tabela1[[#This Row],[Tag do Cabo]],'Lançamento de Cabos'!AG:AG) -> 0 | AH9: =IFERROR(VLOOKUP(Tabela1[[#This Row],[Tag do Cabo]],'Lançamento de Cabos'!AE:AK,7,0),0) -> 0 | AI9: BK-SP54-0900B-DI-74-00452 | AJ9: 7 | AK9: 330260
A10: 220V-PSDC2-001F | B10: Força | C10: 127 | D10: 0,6/1 | E10: 1x2/C#4 | F10: 4 | G10: 1 | H10: 40 | I10: 40 | J10: 1HV | K10: PAINEL DE 220/127V (nota 2) | L10: PSDC2 - PAINEL DE REJEICAO DE CARGAS 1 | M10: Sim | N10: --- | O10: ="Sim" -> Sim | P10: --- | Q10: 5.10.2 | R10: =SUMIF('Lançamento de Cabos'!$B:$B,Tabela1[[#This Row],[Tag do Cabo]],'Lançamento de Cabos'!$C:$C) -> 40 | S10: =VLOOKUP(Tabela1[[#This Row],[Tag do Cabo]],'Diagramas Ligações'!A:V,14,0) -> 4 | T10: BK-SP54-0900A-LC-74-00001_00000 | U10: 5 | W10: ELE-0480 | X10: 44177 | Y10: 44218 | Z10: 22/01/2021: Liberação da Bobina, Nota1: Estas bobinas (n.72 e n.207), foram liberadas para Montcalm em 20-11-20, para retirada parcial. | AA10: 72 | AB10: =IF(AND(Tabela1[[#This Row],[Data de Solcitação do Cabo]]<>0,Tabela1[[#This Row],[Bobina]]<>0),"Disponível",IF(AND(Tabela1[[#This Row],[Data de Solcitação do Cabo]]<>0,Tabela1[[#This Row],[Data de Liberação dos Cabos]]=""),"Pend. Resp.",IF(AND(Tabela1[[#This Row],[Data de Solcitação do Cabo]]<>0,Tabela1[[#This Row],[Bobina]]=""),"Pend. Compra","Não Solic."))) -> Disponível | AC10: PR-LC-0004 | AD10: =IF(Tabela1[[#This Row],[Qtde. Lançada]]>Tabela1[[#This Row],[Comprimento Total]],Tabela1[[#This Row],[Qtde. Lançada]],Tabela1[[#This Row],[Comprimento Total]]) -> 40 | AE10: - | AF10: 1HV | AG10: =SUMIF('Lançamento de Cabos'!AE:AK,Tabela1[[#This Row],[Tag do Cabo]],'Lançamento de Cabos'!AG:AG) -> 0 | AH10: =IFERROR(VLOOKUP(Tabela1[[#This Row],[Tag do Cabo]],'Lançamento de Cabos'!AE:AK,7,0),0) -> 0 | AI10: BK-SP54-0900B-DI-74-00450 | AJ10: 25 | AK10: 330260
A11: TR2-1HV-002F | B11: Força | C11: 13800 | D11: 8,7/15 | E11: 6x3x1/C#150 | F11: 150 | G11: 18 | H11: 30 | I11: 540 | J11: 1HV | K11: EMENDA NA 1HV - PORAO DE CABOS | L11: PAINEL 1HV-BUS3 | M11: Sim | N11: --- | O11: Sim | P11: Sim | Q11: 5.2.3 | R11: =SUMIF('Lançamento de Cabos'!$B:$B,Tabela1[[#This Row],[Tag do Cabo]],'Lançamento de Cabos'!$C:$C) -> 0 | S11: =VLOOKUP(Tabela1[[#This Row],[Tag do Cabo]],'Diagramas Ligações'!A:V,14,0) -> 36 | T11: BK-SP54-0900A-LC-74-00001_00000 | U11: 5 | W11: ELE-0480 | X11: 44177 | Y11: 44218 | Z11: 01/03/2021: Cabos em compra, previsão para 07-03 a 15-03 | AB11: =IF(AND(Tabela1[[#This Row],[Data de Solcitação do Cabo]]<>0,Tabela1[[#This Row],[Bobina]]<>0),"Disponível",IF(AND(Tabela1[[#This Row],[Data de Solcitação do Cabo]]<>0,Tabela1[[#This Row],[Data de Liberação dos Cabos]]=""),"Pend. Resp.",IF(AND(Tabela1[[#This Row],[Data de Solcitação do Cabo]]<>0,Tabela1[[#This Row],[Bobina]]=""),"Pend. Compra","Não Solic."))) -> Pend. Compra | AC11: PR-LC-0004 | AD11: =IF(Tabela1[[#This Row],[Qtde. Lançada]]>Tabela1[[#This Row],[Comprimento Total]],Tabela1[[#This Row],[Qtde. Lançada]],Tabela1[[#This Row],[Comprimento Total]]) -> 540 | AE11: - | AF11: 1HV | AG11: =SUMIF('Lançamento de Cabos'!AE:AK,Tabela1[[#This Row],[Tag do Cabo]],'Lançamento de Cabos'!AG:AG) -> 0 | AH11: =IFERROR(VLOOKUP(Tabela1[[#This Row],[Tag do Cabo]],'Lançamento de Cabos'!AE:AK,7,0),0) -> 0 | AI11: BK-SP54-0900B-DI-74-00452 | AJ11: 6 | AK11: 919525
A12: TR6A-1HVBUS3-001F | B12: Força | C12: 13800 | D12: 8,7/15 | E12: 3x3x1/C#120 | F12: 120 | G12: 9 | H12: 40 | I12: 360 | J12: 1HV | K12: TR-6A | L12: CUBICULO TR-6A (1HV-BUS3) | M12: Sim | N12: --- | O12: Sim | P12: Sim | Q12: 5.2.3 | R12: =SUMIF('Lançamento de Cabos'!$B:$B,Tabela1[[#This Row],[Tag do Cabo]],'Lançamento de Cabos'!$C:$C) -> 0 | S12: =VLOOKUP(Tabela1[[#This Row],[Tag do Cabo]],'Diagramas Ligações'!A:V,14,0) -> 18 | T12: BK-SP54-0900A-LC-74-00001_00000 | U12: 5 | W12: - | X12: 44231 | Y12: 44256 | Z12: 01/03/2021: Cabos em compra, previsão para 07-03 a 15-03 | AB12: =IF(AND(Tabela1[[#This Row],[Data de Solcitação do Cabo]]<>0,Tabela1[[#This Row],[Bobina]]<>0),"Disponível",IF(AND(Tabela1[[#This Row],[Data de Solcitação do Cabo]]<>0,Tabela1[[#This Row],[Data de Liberação dos Cabos]]=""),"Pend. Resp.",IF(AND(Tabela1[[#This Row],[Data de Solcitação do Cabo]]<>0,Tabela1[[#This Row],[Bobina]]=""),"Pend. Compra","Não Solic."))) -> Pend. Compra | AC12: PR-LC-0004 | AD12: =IF(Tabela1[[#This Row],[Qtde. Lançada]]>Tabela1[[#This Row],[Comprimento Total]],Tabela1[[#This Row],[Qtde. Lançada]],Tabela1[[#This Row],[Comprimento Total]]) -> 360 | AE12: - | AF12: 1HV | AG12: =SUMIF('Lançamento de Cabos'!AE:AK,Tabela1[[#This Row],[Tag do Cabo]],'Lançamento de Cabos'!AG:AG) -> 0 | AH12: =IFERROR(VLOOKUP(Tabela1[[#This Row],[Tag do Cabo]],'Lançamento de Cabos'!AE:AK,7,0),0) -> 0 | AI12: BK-SP54-0900B-DI-74-00452 | AJ12: 6 | AK12: 334119
A13: TR8-1HVBUS1-001F | B13: Força | C13: 13800 | D13: 8,7/15 | E13: 1x3x1/C#120 | F13: 120 | G13: 3 | H13: 20 | I13: 60 | J13: 1HV | K13: EMENDA NA 1HV - PORÃO DE CABOS | L13: CUBICULO TR-8 (1HV-BUS1) | M13: Sim | N13: --- | O13: Sim | P13: Sim | Q13: 5.2.3 | R13: =SUMIF('Lançamento de Cabos'!$B:$B,Tabela1[[#This Row],[Tag do Cabo]],'Lançamento de Cabos'!$C:$C) -> 0 | S13: =VLOOKUP(Tabela1[[#This Row],[Tag do Cabo]],'Diagramas Ligações'!A:V,14,0) -> 3 | T13: BK-SP54-0900A-LC-74-00001_00000 | U13: 5 | W13: - | X13: 44231 | Y13: 44256 | Z13: 01/03/2021: Cabos em compra, previsão para 07-03 a 15-03 | AB13: =IF(AND(Tabela1[[#This Row],[Data de Solcitação do Cabo]]<>0,Tabela1[[#This Row],[Bobina]]<>0),"Disponível",IF(AND(Tabela1[[#This Row],[Data de Solcitação do Cabo]]<>0,Tabela1[[#This Row],[Data de Liberação dos Cabos]]=""),"Pend. Resp.",IF(AND(Tabela1[[#This Row],[Data de Solcitação do Cabo]]<>0,Tabela1[[#This Row],[Bobina]]=""),"Pend. Compra","Não Solic."))) -> Pend. Compra | AC13: PR-LC-0004 | AD13: =IF(Tabela1[[#This Row],[Qtde. Lançada]]>Tabela1[[#This Row],[Comprimento Total]],Tabela1[[#This Row],[Qtde. Lançada]],Tabela1[[#This Row],[Comprimento Total]]) -> 60 | AE13: - | AF13: 1HV | AG13: =SUMIF('Lançamento de Cabos'!AE:AK,Tabela1[[#This Row],[Tag do Cabo]],'Lançamento de Cabos'!AG:AG) -> 0 | AH13: =IFERROR(VLOOKUP(Tabela1[[#This Row],[Tag do Cabo]],'Lançamento de Cabos'!AE:AK,7,0),0) -> 0 | AI13: BK-SP54-0900B-DI-74-00452 | AJ13: 6 | AK13: 919986
A14: GAINE-1HVBUS3-001C | B14: Controle | C14: 127 | D14: 0,6/1 | E14: 1x1x12/C#2,5 | F14: 2.5 | G14: 1 | H14: 40 | I14: 40 | J14: 1HV | K14: GAINE 2 | L14: 1HV-BUS3 - PAINEL 13,8kV - 52D1 | M14: Sim | N14: ="Sim" -> Sim | O14: --- | P14: --- | Q14: 5.8.1 | R14: =SUMIF('Lançamento de Cabos'!$B:$B,Tabela1[[#This Row],[Tag do Cabo]],'Lançamento de Cabos'!$C:$C) -> 53 | S14: =VLOOKUP(Tabela1[[#This Row],[Tag do Cabo]],'Diagramas Ligações'!A:V,14,0) -> 24 | T14: BK-SP54-0900A-LC-74-00001_00000 | U14: 5 | V14: Controle 2/18 | W14: ELE-0480 | X14: 44177 | Y14: 44218 | Z14: 22/01/2021: Liberação da Bobina | AA14: 215 | AB14: =IF(AND(Tabela1[[#This Row],[Data de Solcitação do Cabo]]<>0,Tabela1[[#This Row],[Bobina]]<>0),"Disponível",IF(AND(Tabela1[[#This Row],[Data de Solcitação do Cabo]]<>0,Tabela1[[#This Row],[Data de Liberação dos Cabos]]=""),"Pend. Resp.",IF(AND(Tabela1[[#This Row],[Data de Solcitação do Cabo]]<>0,Tabela1[[#This Row],[Bobina]]=""),"Pend. Compra","Não Solic."))) -> Disponível | AC14: PR-LC-0004 | AD14: =IF(Tabela1[[#This Row],[Qtde. Lançada]]>Tabela1[[#This Row],[Comprimento Total]],Tabela1[[#This Row],[Qtde. Lançada]],Tabela1[[#This Row],[Comprimento Total]]) -> 53 | AE14: - | AF14: 1HV | AG14: =SUMIF('Lançamento de Cabos'!AE:AK,Tabela1[[#This Row],[Tag do Cabo]],'Lançamento de Cabos'!AG:AG) -> 0 | AH14: =IFERROR(VLOOKUP(Tabela1[[#This Row],[Tag do Cabo]],'Lançamento de Cabos'!AE:AK,7,0),0) -> 0 | AI14: BK-SP54-0900B-DI-74-00452 | AJ14: 8 | AK14: 9044579
A15: GAINE-1HVBUS3-002C | B15: Controle | C15: 127 | D15: 0,6/1 | E15: 1x1x12/C#2,5 | F15: 2.5 | G15: 1 | H15: 40 | I15: 40 | J15: 1HV | K15: GAINE 2 | L15: 1HV-BUS3 - PAINEL 13,8kV - 52D1 | M15: Sim | N15: ="Sim" -> Sim | O15: --- | P15: --- | Q15: 5.8.1 | R15: =SUMIF('Lançamento de Cabos'!$B:$B,Tabela1[[#This Row],[Tag do Cabo]],'Lançamento de Cabos'!$C:$C) -> 53 | S15: =VLOOKUP(Tabela1[[#This Row],[Tag do Cabo]],'Diagramas Ligações'!A:V,14,0) -> 24 | T15: BK-SP54-0900A-LC-74-00001_00000 | U15: 5 | V15: Controle 2/18 | W15: ELE-0480 | X15: 44177 | Y15: 44218 | Z15: 22/01/2021: Liberação da Bobina | AA15: 215 | AB15: =IF(AND(Tabela1[[#This Row],[Data de Solcitação do Cabo]]<>0,Tabela1[[#This Row],[Bobina]]<>0),"Disponível",IF(AND(Tabela1[[#This Row],[Data de Solcitação do Cabo]]<>0,Tabela1[[#This Row],[Data de Liberação dos Cabos]]=""),"Pend. Resp.",IF(AND(Tabela1[[#This Row],[Data de Solcitação do Cabo]]<>0,Tabela1[[#This Row],[Bobina]]=""),"Pend. Compra","Não Solic."))) -> Disponível | AC15: PR-LC-0004 | AD15: =IF(Tabela1[[#This Row],[Qtde. Lançada]]>Tabela1[[#This Row],[Comprimento Total]],Tabela1[[#This Row],[Qtde. Lançada]],Tabela1[[#This Row],[Comprimento Total]]) -> 53 | AE15: - | AF15: 1HV | AG15: =SUMIF('Lançamento de Cabos'!AE:AK,Tabela1[[#This Row],[Tag do Cabo]],'Lançamento de Cabos'!AG:AG) -> 0 | AH15: =IFERROR(VLOOKUP(Tabela1[[#This Row],[Tag do Cabo]],'Lançamento de Cabos'!AE:AK,7,0),0) -> 0 | AI15: BK-SP54-0900B-DI-74-00452 | AJ15: 8 | AK15: 9044579
A16: GAINE-1HVBUS3-003C | B16: Controle | C16: 127 | D16: 0,6/1 | E16: 1x1x12/C#2,5 | F16: 2.5 | G16: 1 | H16: 40 | I16: 40 | J16: 1HV | K16: GAINE 2 | L16: 1HV-BUS3 - PAINEL 13,8kV - 52D1 | M16: Sim | N16: ="Sim" -> Sim | O16: --- | P16: --- | Q16: 5.8.1 | R16: =SUMIF('Lançamento de Cabos'!$B:$B,Tabela1[[#This Row],[Tag do Cabo]],'Lançamento de Cabos'!$C:$C) -> 53 | S16: =VLOOKUP(Tabela1[[#This Row],[Tag do Cabo]],'Diagramas Ligações'!A:V,14,0) -> 24 | T16: BK-SP54-0900A-LC-74-00001_00000 | U16: 5 | V16: Controle 2/18 | W16: ELE-0480 | X16: 44177 | Y16: 44218 | Z16: 22/01/2021: Liberação da Bobina | AA16: 215 | AB16: =IF(AND(Tabela1[[#This Row],[Data de Solcitação do Cabo]]<>0,Tabela1[[#This Row],[Bobina]]<>0),"Disponível",IF(AND(Tabela1[[#This Row],[Data de Solcitação do Cabo]]<>0,Tabela1[[#This Row],[Data de Liberação dos Cabos]]=""),"Pend. Resp.",IF(AND(Tabela1[[#This Row],[Data de Solcitação do Cabo]]<>0,Tabela1[[#This Row],[Bobina]]=""),"Pend. Compra","Não Solic."))) -> Disponível | AC16: PR-LC-0004 | AD16: =IF(Tabela1[[#This Row],[Qtde. Lançada]]>Tabela1[[#This Row],[Comprimento Total]],Tabela1[[#This Row],[Qtde. Lançada]],Tabela1[[#This Row],[Comprimento Total]]) -> 53 | AE16: - | AF16: 1HV | AG16: =SUMIF('Lançamento de Cabos'!AE:AK,Tabela1[[#This Row],[Tag do Cabo]],'Lançamento de Cabos'!AG:AG) -> 0 | AH16: =IFERROR(VLOOKUP(Tabela1[[#This Row],[Tag do Cabo]],'Lançamento de Cabos'!AE:AK,7,0),0) -> 0 | AI16: BK-SP54-0900B-DI-74-00452 | AJ16: 8 | AK16: 9044579
A17: PSDC2-1HV-001C | B17: Controle | C17: 125 | D17: 0,6/1 | E17: 1x1x7/C#2,5 | F17: 2.5 | G17: 1 | H17: 30 | I17: 30 | J17: 1HV | K17: PSDC2 - PAINEL DE REJEICAO DE CARGAS 2 - regua BNC | L17: DJ. 1HV-24HV1 | M17: Sim | N17: ="Sim" -> Sim | O17: --- | P17: --- | Q17: 5.8.1 | R17: =SUMIF('Lançamento de Cabos'!$B:$B,Tabela1[[#This Row],[Tag do Cabo]],'Lançamento de Cabos'!$C:$C) -> 42 | S17: =VLOOKUP(Tabela1[[#This Row],[Tag do Cabo]],'Diagramas Ligações'!A:V,14,0) -> 14 | T17: BK-SP54-0900A-LC-74-00001_00000 | U17: 5 | V17: Controle 2/18 | W17: ELE-0480 | X17: 44177 | Y17: 44218 | Z17: 22/01/2021: Liberação da Bobina 02/03/2021: Alterada a Bobina de 70 para 225, verifciar se atenderá os lançamentos | AA17: 225 | AB17: =IF(AND(Tabela1[[#This Row],[Data de Solcitação do Cabo]]<>0,Tabela1[[#This Row],[Bobina]]<>0),"Disponível",IF(AND(Tabela1[[#This Row],[Data de Solcitação do Cabo]]<>0,Tabela1[[#This Row],[Data de Liberação dos Cabos]]=""),"Pend. Resp.",IF(AND(Tabela1[[#This Row],[Data de Solcitação do Cabo]]<>0,Tabela1[[#This Row],[Bobina]]=""),"Pend. Compra","Não Solic."))) -> Disponível | AC17: PR-LC-0004 | AD17: =IF(Tabela1[[#This Row],[Qtde. Lançada]]>Tabela1[[#This Row],[Comprimento Total]],Tabela1[[#This Row],[Qtde. Lançada]],Tabela1[[#This Row],[Comprimento Total]]) -> 42 | AE17: - | AF17: 1HV | AG17: =SUMIF('Lançamento de Cabos'!AE:AK,Tabela1[[#This Row],[Tag do Cabo]],'Lançamento de Cabos'!AG:AG) -> 0 | AH17: =IFERROR(VLOOKUP(Tabela1[[#This Row],[Tag do Cabo]],'Lançamento de Cabos'!AE:AK,7,0),0) -> 0 | AI17: BK-SP54-0900B-DI-74-00450 | AJ17: 26 | AK17: 49726
A18: PSDC2-1HV-002C | B18: Controle | C18: 125 | D18: 0,6/1 | E18: 1x1x7/C#2,5 | F18: 2.5 | G18: 1 | H18: 30 | I18: 30 | J18: 1HV | K18: PSDC2 - PAINEL DE REJEICAO DE CARGAS 2 - regua BNC | L18: DJ. 1HV-24HV2 | M18: Sim | N18: ="Sim" -> Sim | O18: --- | P18: --- | Q18: 5.8.1 | R18: =SUMIF('Lançamento de Cabos'!$B:$B,Tabela1[[#This Row],[Tag do Cabo]],'Lançamento de Cabos'!$C:$C) -> 42 | S18: =VLOOKUP(Tabela1[[#This Row],[Tag do Cabo]],'Diagramas Ligações'!A:V,14,0) -> 14 | T18: BK-SP54-0900A-LC-74-00001_00000 | U18: 5 | V18: Controle 2/18 | W18: ELE-0480 | X18: 44177 | Y18: 44218 | Z18: 22/01/2021: Liberação da Bobina 02/03/2021: Alterada a Bobina de 70 para 225, verifciar se atenderá os lançamentos | AA18: 225 | AB18: =IF(AND(Tabela1[[#This Row],[Data de Solcitação do Cabo]]<>0,Tabela1[[#This Row],[Bobina]]<>0),"Disponível",IF(AND(Tabela1[[#This Row],[Data de Solcitação do Cabo]]<>0,Tabela1[[#This Row],[Data de Liberação dos Cabos]]=""),"Pend. Resp.",IF(AND(Tabela1[[#This Row],[Data de Solcitação do Cabo]]<>0,Tabela1[[#This Row],[Bobina]]=""),"Pend. Compra","Não Solic."))) -> Disponível | AC18: PR-LC-0004 | AD18: =IF(Tabela1[[#This Row],[Qtde. Lançada]]>Tabela1[[#This Row],[Comprimento Total]],Tabela1[[#This Row],[Qtde. Lançada]],Tabela1[[#This Row],[Comprimento Total]]) -> 42 | AE18: - | AF18: 1HV | AG18: =SUMIF('Lançamento de Cabos'!AE:AK,Tabela1[[#This Row],[Tag do Cabo]],'Lançamento de Cabos'!AG:AG) -> 0 | AH18: =IFERROR(VLOOKUP(Tabela1[[#This Row],[Tag do Cabo]],'Lançamento de Cabos'!AE:AK,7,0),0) -> 0 | AI18: BK-SP54-0900B-DI-74-00450 | AJ18: 26 | AK18: 49726
A19: PSDC2-1HV-003C | B19: Controle | C19: 125 | D19: 0,6/1 | E19: 1x1x7/C#2,5 | F19: 2.5 | G19: 1 | H19: 30 | I19: 30 | J19: 1HV | K19: PSDC2 - PAINEL DE REJEICAO DE CARGAS 2 - regua BNC | L19: DJ. GE902 | M19: Sim | N19: ="Sim" -> Sim | O19: --- | P19: --- | Q19: 5.8.1 | R19: =SUMIF('Lançamento de Cabos'!$B:$B,Tabela1[[#This Row],[Tag do Cabo]],'Lançamento de Cabos'!$C:$C) -> 42 | S19: =VLOOKUP(Tabela1[[#This Row],[Tag do Cabo]],'Diagramas Ligações'!A:V,14,0) -> 14 | T19: BK-SP54-0900A-LC-74-00001_00000 | U19: 5 | V19: Controle 2/18 | W19: ELE-0480 | X19: 44177 | Y19: 44218 | Z19: 22/01/2021: Liberação da Bobina 02/03/2021: Alterada a Bobina de 70 para 225, verifciar se atenderá os lançamentos | AA19: 225 | AB19: =IF(AND(Tabela1[[#This Row],[Data de Solcitação do Cabo]]<>0,Tabela1[[#This Row],[Bobina]]<>0),"Disponível",IF(AND(Tabela1[[#This Row],[Data de Solcitação do Cabo]]<>0,Tabela1[[#This Row],[Data de Liberação dos Cabos]]=""),"Pend. Resp.",IF(AND(Tabela1[[#This Row],[Data de Solcitação do Cabo]]<>0,Tabela1[[#This Row],[Bobina]]=""),"Pend. Compra","Não Solic."))) -> Disponível | AC19: PR-LC-0004 | AD19: =IF(Tabela1[[#This Row],[Qtde. Lançada]]>Tabela1[[#This Row],[Comprimento Total]],Tabela1[[#This Row],[Qtde. Lançada]],Tabela1[[#This Row],[Comprimento Total]]) -> 42 | AE19: - | AF19: 1HV | AG19: =SUMIF('Lançamento de Cabos'!AE:AK,Tabela1[[#This Row],[Tag do Cabo]],'Lançamento de Cabos'!AG:AG) -> 0 | AH19: =IFERROR(VLOOKUP(Tabela1[[#This Row],[Tag do Cabo]],'Lançamento de Cabos'!AE:AK,7,0),0) -> 0 | AI19: BK-SP54-0900B-DI-74-00450 | AJ19: 26 | AK19: 49726
A20: CBO001-SEL | B20: FO | C20: - | D20: - | E20: CORDÃO ÓPTICO | F20: - | G20: 1 | H20: 20 | I20: 20 | J20: FIBRA | K20: ER-3 | L20: ER-4 | M20: --- | N20: --- | O20: --- | P20: --- | Q20: 5.6.1 | R20: =SUMIF('Lançamento de Cabos'!$B:$B,Tabela1[[#This Row],[Tag do Cabo]],'Lançamento de Cabos'!$C:$C) -> 0 | S20: =VLOOKUP(Tabela1[[#This Row],[Tag do Cabo]],'Diagramas Ligações'!A:V,14,0) -> 2 | T20: BK-SP54-0900A-LC-74-00001_00000 | U20: 5 | V20: N/A | W20: - | X20: 44256 | Y20: 44256 | Z20: 01/03/2021: Cabos em compra, previsão para 07-03 a 15-03 | AB20: =IF(AND(Tabela1[[#This Row],[Data de Solcitação do Cabo]]<>0,Tabela1[[#This Row],[Bobina]]<>0),"Disponível",IF(AND(Tabela1[[#This Row],[Data de Solcitação do Cabo]]<>0,Tabela1[[#This Row],[Data de Liberação dos Cabos]]=""),"Pend. Resp.",IF(AND(Tabela1[[#This Row],[Data de Solcitação do Cabo]]<>0,Tabela1[[#This Row],[Bobina]]=""),"Pend. Compra","Não Solic."))) -> Pend. Compra | AD20: =IF(Tabela1[[#This Row],[Qtde. Lançada]]>Tabela1[[#This Row],[Comprimento Total]],Tabela1[[#This Row],[Qtde. Lançada]],Tabela1[[#This Row],[Comprimento Total]]) -> 20 | AE20: Rede Fibra | AF20: 1HVx1MV | AG20: =SUMIF('Lançamento de Cabos'!AE:AK,Tabela1[[#This Row],[Tag do Cabo]],'Lançamento de Cabos'!AG:AG) -> 0 | AH20: =IFERROR(VLOOKUP(Tabela1[[#This Row],[Tag do Cabo]],'Lançamento de Cabos'!AE:AK,7,0),0) -> 0 | AI20: BK-SP54-0900B-DI-74-00450 | AJ20: 30 | AK20: 3054429
A21: PSDC2-1MV-001C | B21: Controle | C21: 125 | D21: 0,6/1 | E21: 1x1x7/C#2,5 | F21: 2.5 | G21: 1 | H21: 30 | I21: 30 | J21: 1HV | K21: PSDC2 - PAINEL DE REJEICAO DE CARGAS 2 - regua BNC | L21: DJ. 1MV-B1-GA-905C | M21: Sim | N21: ="Sim" -> Sim | O21: --- | P21: --- | Q21: 5.8.1 | R21: =SUMIF('Lançamento de Cabos'!$B:$B,Tabela1[[#This Row],[Tag do Cabo]],'Lançamento de Cabos'!$C:$C) -> 48 | S21: =VLOOKUP(Tabela1[[#This Row],[Tag do Cabo]],'Diagramas Ligações'!A:V,14,0) -> 14 | T21: BK-SP54-0900A-LC-74-00001_00000 | U21: 5 | V21: Controle 2/18 | W21: ELE-0480 | X21: 44177 | Y21: 44218 | Z21: 22/01/2021: Liberação da Bobina | AA21: 70 | AB21: =IF(AND(Tabela1[[#This Row],[Data de Solcitação do Cabo]]<>0,Tabela1[[#This Row],[Bobina]]<>0),"Disponível",IF(AND(Tabela1[[#This Row],[Data de Solcitação do Cabo]]<>0,Tabela1[[#This Row],[Data de Liberação dos Cabos]]=""),"Pend. Resp.",IF(AND(Tabela1[[#This Row],[Data de Solcitação do Cabo]]<>0,Tabela1[[#This Row],[Bobina]]=""),"Pend. Compra","Não Solic."))) -> Disponível | AC21: PR-LC-0005 | AD21: =IF(Tabela1[[#This Row],[Qtde. Lançada]]>Tabela1[[#This Row],[Comprimento Total]],Tabela1[[#This Row],[Qtde. Lançada]],Tabela1[[#This Row],[Comprimento Total]]) -> 48 | AE21: - | AF21: 1HVx1MV | AG21: =SUMIF('Lançamento de Cabos'!AE:AK,Tabela1[[#This Row],[Tag do Cabo]],'Lançamento de Cabos'!AG:AG) -> 0 | AH21: =IFERROR(VLOOKUP(Tabela1[[#This Row],[Tag do Cabo]],'Lançamento de Cabos'!AE:AK,7,0),0) -> 0 | AI21: BK-SP54-0900B-DI-74-00450 | AJ21: 27 | AK21: 49726
A22: PSDC2-1MV-002C | B22: Controle | C22: 125 | D22: 0,6/1 | E22: 1x1x7/C#2,5 | F22: 2.5 | G22: 1 | H22: 30 | I22: 30 | J22: 1HV | K22: PSDC2 - PAINEL DE REJEICAO DE CARGAS 2 - regua BNC | L22: DJ. 1MV-B1-GA-902D | M22: Sim | N22: ="Sim" -> Sim | O22: --- | P22: --- | Q22: 5.8.1 | R22: =SUMIF('Lançamento de Cabos'!$B:$B,Tabela1[[#This Row],[Tag do Cabo]],'Lançamento de Cabos'!$C:$C) -> 47 | S22: =VLOOKUP(Tabela1[[#This Row],[Tag do Cabo]],'Diagramas Ligações'!A:V,14,0) -> 14 | T22: BK-SP54-0900A-LC-74-00001_00000 | U22: 5 | V22: Controle 2/18 | W22: ELE-0480 | X22: 44177 | Y22: 44218 | Z22: 22/01/2021: Liberação da Bobina | AA22: 70 | AB22: =IF(AND(Tabela1[[#This Row],[Data de Solcitação do Cabo]]<>0,Tabela1[[#This Row],[Bobina]]<>0),"Disponível",IF(AND(Tabela1[[#This Row],[Data de Solcitação do Cabo]]<>0,Tabela1[[#This Row],[Data de Liberação dos Cabos]]=""),"Pend. Resp.",IF(AND(Tabela1[[#This Row],[Data de Solcitação do Cabo]]<>0,Tabela1[[#This Row],[Bobina]]=""),"Pend. Compra","Não Solic."))) -> Disponível | AC22: PR-LC-0005 | AD22: =IF(Tabela1[[#This Row],[Qtde. Lançada]]>Tabela1[[#This Row],[Comprimento Total]],Tabela1[[#This Row],[Qtde. Lançada]],Tabela1[[#This Row],[Comprimento Total]]) -> 47 | AE22: - | AF22: 1HVx1MV | AG22: =SUMIF('Lançamento de Cabos'!AE:AK,Tabela1[[#This Row],[Tag do Cabo]],'Lançamento de Cabos'!AG:AG) -> 0 | AH22: =IFERROR(VLOOKUP(Tabela1[[#This Row],[Tag do Cabo]],'Lançamento de Cabos'!AE:AK,7,0),0) -> 0 | AI22: BK-SP54-0900B-DI-74-00450 | AJ22: 27 | AK22: 49726
A23: PSDC2-1MV-003C | B23: Controle | C23: 125 | D23: 0,6/1 | E23: 1x1x7/C#2,5 | F23: 2.5 | G23: 1 | H23: 30 | I23: 30 | J23: 1HV | K23: PSDC2 - PAINEL DE REJEICAO DE CARGAS 2 - regua BNC | L23: DJ. 1MV-B1-GB-302 | M23: Sim | N23: ="Sim" -> Sim | O23: --- | P23: --- | Q23: 5.8.1 | R23: =SUMIF('Lançamento de Cabos'!$B:$B,Tabela1[[#This Row],[Tag do Cabo]],'Lançamento de Cabos'!$C:$C) -> 40 | S23: =VLOOKUP(Tabela1[[#This Row],[Tag do Cabo]],'Diagramas Ligações'!A:V,14,0) -> 14 | T23: BK-SP54-0900A-LC-74-00001_00000 | U23: 5 | V23: Controle 2/18 | W23: ELE-0480 | X23: 44177 | Y23: 44218 | Z23: 22/01/2021: Liberação da Bobina | AA23: 70 | AB23: =IF(AND(Tabela1[[#This Row],[Data de Solcitação do Cabo]]<>0,Tabela1[[#This Row],[Bobina]]<>0),"Disponível",IF(AND(Tabela1[[#This Row],[Data de Solcitação do Cabo]]<>0,Tabela1[[#This Row],[Data de Liberação dos Cabos]]=""),"Pend. Resp.",IF(AND(Tabela1[[#This Row],[Data de Solcitação do Cabo]]<>0,Tabela1[[#This Row],[Bobina]]=""),"Pend. Compra","Não Solic."))) -> Disponível | AC23: PR-LC-0005 | AD23: =IF(Tabela1[[#This Row],[Qtde. Lançada]]>Tabela1[[#This Row],[Comprimento Total]],Tabela1[[#This Row],[Qtde. Lançada]],Tabela1[[#This Row],[Comprimento Total]]) -> 40 | AE23: - | AF23: 1HVx1MV | AG23: =SUMIF('Lançamento de Cabos'!AE:AK,Tabela1[[#This Row],[Tag do Cabo]],'Lançamento de Cabos'!AG:AG) -> 0 | AH23: =IFERROR(VLOOKUP(Tabela1[[#This Row],[Tag do Cabo]],'Lançamento de Cabos'!AE:AK,7,0),0) -> 0 | AI23: BK-SP54-0900B-DI-74-00450 | AJ23: 27 | AK23: 49726
A24: PSDC2-1MV-004C | B24: Controle | C24: 125 | D24: 0,6/1 | E24: 1x1x7/C#2,5 | F24: 2.5 | G24: 1 | H24: 30 | I24: 30 | J24: 1HV | K24: PSDC2 - PAINEL DE REJEICAO DE CARGAS 2 - regua BNC | L24: DJ. 1MV-B1-GA-208D | M24: Sim | N24: ="Sim" -> Sim | O24: --- | P24: --- | Q24: 5.8.1 | R24: =SUMIF('Lançamento de Cabos'!$B:$B,Tabela1[[#This Row],[Tag do Cabo]],'Lançamento de Cabos'!$C:$C) -> 39 | S24: =VLOOKUP(Tabela1[[#This Row],[Tag do Cabo]],'Diagramas Ligações'!A:V,14,0) -> 14 | T24: BK-SP54-0900A-LC-74-00001_00000 | U24: 5 | V24: Controle 2/18 | W24: ELE-0480 | X24: 44177 | Y24: 44218 | Z24: 22/01/2021: Liberação da Bobina | AA24: 70 | AB24: =IF(AND(Tabela1[[#This Row],[Data de Solcitação do Cabo]]<>0,Tabela1[[#This Row],[Bobina]]<>0),"Disponível",IF(AND(Tabela1[[#This Row],[Data de Solcitação do Cabo]]<>0,Tabela1[[#This Row],[Data de Liberação dos Cabos]]=""),"Pend. Resp.",IF(AND(Tabela1[[#This Row],[Data de Solcitação do Cabo]]<>0,Tabela1[[#This Row],[Bobina]]=""),"Pend. Compra","Não Solic."))) -> Disponível | AC24: PR-LC-0005 | AD24: =IF(Tabela1[[#This Row],[Qtde. Lançada]]>Tabela1[[#This Row],[Comprimento Total]],Tabela1[[#This Row],[Qtde. Lançada]],Tabela1[[#This Row],[Comprimento Total]]) -> 39 | AE24: - | AF24: 1HVx1MV | AG24: =SUMIF('Lançamento de Cabos'!AE:AK,Tabela1[[#This Row],[Tag do Cabo]],'Lançamento de Cabos'!AG:AG) -> 0 | AH24: =IFERROR(VLOOKUP(Tabela1[[#This Row],[Tag do Cabo]],'Lançamento de Cabos'!AE:AK,7,0),0) -> 0 | AI24: BK-SP54-0900B-DI-74-00450 | AJ24: 27 | AK24: 49726
A25: PSDC2-1MV-005C | B25: Controle | C25: 125 | D25: 0,6/1 | E25: 1x1x7/C#2,5 | F25: 2.5 | G25: 1 | H25: 30 | I25: 30 | J25: 1HV | K25: PSDC2 - PAINEL DE REJEICAO DE CARGAS 2 - regua BNC | L25: DJ. 1MV-B1-GB-601/602 | M25: Sim | N25: ="Sim" -> Sim | O25: --- | P25: --- | Q25: 5.8.1 | R25: =SUMIF('Lançamento de Cabos'!$B:$B,Tabela1[[#This Row],[Tag do Cabo]],'Lançamento de Cabos'!$C:$C) -> 40 | S25: =VLOOKUP(Tabela1[[#This Row],[Tag do Cabo]],'Diagramas Ligações'!A:V,14,0) -> 14 | T25: BK-SP54-0900A-LC-74-00001_00000 | U25: 5 | V25: Controle 2/18 | W25: ELE-0480 | X25: 44177 | Y25: 44218 | Z25: 22/01/2021: Liberação da Bobina | AA25: 70 | AB25: =IF(AND(Tabela1[[#This Row],[Data de Solcitação do Cabo]]<>0,Tabela1[[#This Row],[Bobina]]<>0),"Disponível",IF(AND(Tabela1[[#This Row],[Data de Solcitação do Cabo]]<>0,Tabela1[[#This Row],[Data de Liberação dos Cabos]]=""),"Pend. Resp.",IF(AND(Tabela1[[#This Row],[Data de Solcitação do Cabo]]<>0,Tabela1[[#This Row],[Bobina]]=""),"Pend. Compra","Não Solic."))) -> Disponível | AC25: PR-LC-0005 | AD25: =IF(Tabela1[[#This Row],[Qtde. Lançada]]>Tabela1[[#This Row],[Comprimento Total]],Tabela1[[#This Row],[Qtde. Lançada]],Tabela1[[#This Row],[Comprimento Total]]) -> 40 | AE25: - | AF25: 1HVx1MV | AG25: =SUMIF('Lançamento de Cabos'!AE:AK,Tabela1[[#This Row],[Tag do Cabo]],'Lançamento de Cabos'!AG:AG) -> 0 | AH25: =IFERROR(VLOOKUP(Tabela1[[#This Row],[Tag do Cabo]],'Lançamento de Cabos'!AE:AK,7,0),0) -> 0 | AI25: BK-SP54-0900B-DI-74-00450 | AJ25: 27 | AK25: 49726
A26: PSDC2-1MV-006C | B26: Controle | C26: 125 | D26: 0,6/1 | E26: 1x1x7/C#2,5 | F26: 2.5 | G26: 1 | H26: 30 | I26: 30 | J26: 1HV | K26: PSDC2 - PAINEL DE REJEICAO DE CARGAS 2 - regua BNC | L26: DJ. 1MV-B1-GB-966 | M26: Sim | N26: ="Sim" -> Sim | O26: --- | P26: --- | Q26: 5.8.1 | R26: =SUMIF('Lançamento de Cabos'!$B:$B,Tabela1[[#This Row],[Tag do Cabo]],'Lançamento de Cabos'!$C:$C) -> 39 | S26: =VLOOKUP(Tabela1[[#This Row],[Tag do Cabo]],'Diagramas Ligações'!A:V,14,0) -> 14 | T26: BK-SP54-0900A-LC-74-00001_00000 | U26: 5 | V26: Controle 2/18 | W26: ELE-0480 | X26: 44177 | Y26: 44218 | Z26: 22/01/2021: Liberação da Bobina | AA26: 70 | AB26: =IF(AND(Tabela1[[#This Row],[Data de Solcitação do Cabo]]<>0,Tabela1[[#This Row],[Bobina]]<>0),"Disponível",IF(AND(Tabela1[[#This Row],[Data de Solcitação do Cabo]]<>0,Tabela1[[#This Row],[Data de Liberação dos Cabos]]=""),"Pend. Resp.",IF(AND(Tabela1[[#This Row],[Data de Solcitação do Cabo]]<>0,Tabela1[[#This Row],[Bobina]]=""),"Pend. Compra","Não Solic."))) -> Disponível | AC26: PR-LC-0005 | AD26: =IF(Tabela1[[#This Row],[Qtde. Lançada]]>Tabela1[[#This Row],[Comprimento Total]],Tabela1[[#This Row],[Qtde. Lançada]],Tabela1[[#This Row],[Comprimento Total]]) -> 39 | AE26: - | AF26: 1HVx1MV | AG26: =SUMIF('Lançamento de Cabos'!AE:AK,Tabela1[[#This Row],[Tag do Cabo]],'Lançamento de Cabos'!AG:AG) -> 0 | AH26: =IFERROR(VLOOKUP(Tabela1[[#This Row],[Tag do Cabo]],'Lançamento de Cabos'!AE:AK,7,0),0) -> 0 | AI26: BK-SP54-0900B-DI-74-00450 | AJ26: 28 | AK26: 49726
A27: PSDC2-1MV-007C | B27: Controle | C27: 125 | D27: 0,6/1 | E27: 1x1x7/C#2,5 | F27: 2.5 | G27: 1 | H27: 30 | I27: 30 | J27: 1HV | K27: PSDC2 - PAINEL DE REJEICAO DE CARGAS 2 - regua BNC | L27: DJ. 1MV-B1-GB-967A | M27: Sim | N27: ="Sim" -> Sim | O27: --- | P27: --- | Q27: 5.8.1 | R27: =SUMIF('Lançamento de Cabos'!$B:$B,Tabela1[[#This Row],[Tag do Cabo]],'Lançamento de Cabos'!$C:$C) -> 42 | S27: =VLOOKUP(Tabela1[[#This Row],[Tag do Cabo]],'Diagramas Ligações'!A:V,14,0) -> 14 | T27: BK-SP54-0900A-LC-74-00001_00000 | U27: 5 | V27: Controle 2/18 | W27: ELE-0480 | X27: 44177 | Y27: 44218 | Z27: 22/01/2021: Liberação da Bobina | AA27: 207 | AB27: =IF(AND(Tabela1[[#This Row],[Data de Solcitação do Cabo]]<>0,Tabela1[[#This Row],[Bobina]]<>0),"Disponível",IF(AND(Tabela1[[#This Row],[Data de Solcitação do Cabo]]<>0,Tabela1[[#This Row],[Data de Liberação dos Cabos]]=""),"Pend. Resp.",IF(AND(Tabela1[[#This Row],[Data de Solcitação do Cabo]]<>0,Tabela1[[#This Row],[Bobina]]=""),"Pend. Compra","Não Solic."))) -> Disponível | AC27: PR-LC-0005 | AD27: =IF(Tabela1[[#This Row],[Qtde. Lançada]]>Tabela1[[#This Row],[Comprimento Total]],Tabela1[[#This Row],[Qtde. Lançada]],Tabela1[[#This Row],[Comprimento Total]]) -> 42 | AE27: - | AF27: 1HVx1MV | AG27: =SUMIF('Lançamento de Cabos'!AE:AK,Tabela1[[#This Row],[Tag do Cabo]],'Lançamento de Cabos'!AG:AG) -> 0 | AH27: =IFERROR(VLOOKUP(Tabela1[[#This Row],[Tag do Cabo]],'Lançamento de Cabos'!AE:AK,7,0),0) -> 0 | AI27: BK-SP54-0900B-DI-74-00450 | AJ27: 28 | AK27: 49726
A28: PSDC2-1MV-008C | B28: Controle | C28: 125 | D28: 0,6/1 | E28: 1x1x7/C#2,5 | F28: 2.5 | G28: 1 | H28: 30 | I28: 30 | J28: 1HV | K28: PSDC2 - PAINEL DE REJEICAO DE CARGAS 2 - regua BNC | L28: DJ. 1MV-B1-GB-967B | M28: Sim | N28: ="Sim" -> Sim | O28: --- | P28: --- | Q28: 5.8.1 | R28: =SUMIF('Lançamento de Cabos'!$B:$B,Tabela1[[#This Row],[Tag do Cabo]],'Lançamento de Cabos'!$C:$C) -> 42 | S28: =VLOOKUP(Tabela1[[#This Row],[Tag do Cabo]],'Diagramas Ligações'!A:V,14,0) -> 14 | T28: BK-SP54-0900A-LC-74-00001_00000 | U28: 5 | V28: Controle 2/18 | W28: ELE-0480 | X28: 44177 | Y28: 44218 | Z28: 22/01/2021: Liberação da Bobina | AA28: 207 | AB28: =IF(AND(Tabela1[[#This Row],[Data de Solcitação do Cabo]]<>0,Tabela1[[#This Row],[Bobina]]<>0),"Disponível",IF(AND(Tabela1[[#This Row],[Data de Solcitação do Cabo]]<>0,Tabela1[[#This Row],[Data de Liberação dos Cabos]]=""),"Pend. Resp.",IF(AND(Tabela1[[#This Row],[Data de Solcitação do Cabo]]<>0,Tabela1[[#This Row],[Bobina]]=""),"Pend. Compra","Não Solic."))) -> Disponível | AC28: PR-LC-0005 | AD28: =IF(Tabela1[[#This Row],[Qtde. Lançada]]>Tabela1[[#This Row],[Comprimento Total]],Tabela1[[#This Row],[Qtde. Lançada]],Tabela1[[#This Row],[Comprimento Total]]) -> 42 | AE28: - | AF28: 1HVx1MV | AG28: =SUMIF('Lançamento de Cabos'!AE:AK,Tabela1[[#This Row],[Tag do Cabo]],'Lançamento de Cabos'!AG:AG) -> 0 | AH28: =IFERROR(VLOOKUP(Tabela1[[#This Row],[Tag do Cabo]],'Lançamento de Cabos'!AE:AK,7,0),0) -> 0 | AI28: BK-SP54-0900B-DI-74-00450 | AJ28: 28 | AK28: 49726
A29: PSDC2-1MV-009C | B29: Controle | C29: 125 | D29: 0,6/1 | E29: 1x1x7/C#2,5 | F29: 2.5 | G29: 1 | H29: 30 | I29: 30 | J29: 1HV | K29: PSDC2 - PAINEL DE REJEICAO DE CARGAS 2 - regua BNC | L29: DJ. 1MV-B1-GA-906E | M29: Sim | N29: ="Sim" -> Sim | O29: --- | P29: --- | Q29: 5.8.1 | R29: =SUMIF('Lançamento de Cabos'!$B:$B,Tabela1[[#This Row],[Tag do Cabo]],'Lançamento de Cabos'!$C:$C) -> 38 | S29: =VLOOKUP(Tabela1[[#This Row],[Tag do Cabo]],'Diagramas Ligações'!A:V,14,0) -> 14 | T29: BK-SP54-0900A-LC-74-00001_00000 | U29: 5 | V29: Controle 2/18 | W29: ELE-0480 | X29: 44177 | Y29: 44218 | Z29: 22/01/2021: Liberação da Bobina, Nota1: Estas bobinas (n.72 e n.207), foram liberadas para Montcalm em 20-11-20, para retirada parcial. | AA29: 225 | AB29: =IF(AND(Tabela1[[#This Row],[Data de Solcitação do Cabo]]<>0,Tabela1[[#This Row],[Bobina]]<>0),"Disponível",IF(AND(Tabela1[[#This Row],[Data de Solcitação do Cabo]]<>0,Tabela1[[#This Row],[Data de Liberação dos Cabos]]=""),"Pend. Resp.",IF(AND(Tabela1[[#This Row],[Data de Solcitação do Cabo]]<>0,Tabela1[[#This Row],[Bobina]]=""),"Pend. Compra","Não Solic."))) -> Disponível | AC29: PR-LC-0005 | AD29: =IF(Tabela1[[#This Row],[Qtde. Lançada]]>Tabela1[[#This Row],[Comprimento Total]],Tabela1[[#This Row],[Qtde. Lançada]],Tabela1[[#This Row],[Comprimento Total]]) -> 38 | AE29: - | AF29: 1HVx1MV | AG29: =SUMIF('Lançamento de Cabos'!AE:AK,Tabela1[[#This Row],[Tag do Cabo]],'Lançamento de Cabos'!AG:AG) -> 0 | AH29: =IFERROR(VLOOKUP(Tabela1[[#This Row],[Tag do Cabo]],'Lançamento de Cabos'!AE:AK,7,0),0) -> 0 | AI29: BK-SP54-0900B-DI-74-00450 | AJ29: 28 | AK29: 49726
A30: PSDC2-1MV-010C | B30: Controle | C30: 125 | D30: 0,6/1 | E30: 1x1x7/C#2,5 | F30: 2.5 | G30: 1 | H30: 30 | I30: 30 | J30: 1HV | K30: PSDC2 - PAINEL DE REJEICAO DE CARGAS 2 - regua BNC | L30: DJ. 1MV-B1-GA-203F | M30: Sim | N30: ="Sim" -> Sim | O30: --- | P30: --- | Q30: 5.8.1 | R30: =SUMIF('Lançamento de Cabos'!$B:$B,Tabela1[[#This Row],[Tag do Cabo]],'Lançamento de Cabos'!$C:$C) -> 41 | S30: =VLOOKUP(Tabela1[[#This Row],[Tag do Cabo]],'Diagramas Ligações'!A:V,14,0) -> 14 | T30: BK-SP54-0900A-LC-74-00001_00000 | U30: 5 | V30: Controle 2/18 | W30: ELE-0480 | X30: 44177 | Y30: 44218 | Z30: 22/01/2021: Liberação da Bobina, Nota1: Estas bobinas (n.72 e n.207), foram liberadas para Montcalm em 20-11-20, para retirada parcial. | AA30: 207 | AB30: =IF(AND(Tabela1[[#This Row],[Data de Solcitação do Cabo]]<>0,Tabela1[[#This Row],[Bobina]]<>0),"Disponível",IF(AND(Tabela1[[#This Row],[Data de Solcitação do Cabo]]<>0,Tabela1[[#This Row],[Data de Liberação dos Cabos]]=""),"Pend. Resp.",IF(AND(Tabela1[[#This Row],[Data de Solcitação do Cabo]]<>0,Tabela1[[#This Row],[Bobina]]=""),"Pend. Compra","Não Solic."))) -> Disponível | AC30: PR-LC-0005 | AD30: =IF(Tabela1[[#This Row],[Qtde. Lançada]]>Tabela1[[#This Row],[Comprimento Total]],Tabela1[[#This Row],[Qtde. Lançada]],Tabela1[[#This Row],[Comprimento Total]]) -> 41 | AE30: - | AF30: 1HVx1MV | AG30: =SUMIF('Lançamento de Cabos'!AE:AK,Tabela1[[#This Row],[Tag do Cabo]],'Lançamento de Cabos'!AG:AG) -> 0 | AH30: =IFERROR(VLOOKUP(Tabela1[[#This Row],[Tag do Cabo]],'Lançamento de Cabos'!AE:AK,7,0),0) -> 0 | AI30: BK-SP54-0900B-DI-74-00450 | AJ30: 28 | AK30: 49726
A31: U-2278 | B31: Controle | C31: - | D31: - | E31: 2P#1,0mm²+SHI+SHC | F31: 1 | G31: 1 | H31: 230 | I31: 230 | J31: 1HV | K31: SUBESTAÇÃO 1HV/PAINEL 1MV | L31: CCP/SDCD AQUENTE2 | M31: Sim | N31: ="Sim" -> Sim | O31: --- | P31: --- | Q31: 4.6.1 | R31: =SUMIF('Lançamento de Cabos'!$B:$B,Tabela1[[#This Row],[Tag do Cabo]],'Lançamento de Cabos'!$C:$C) -> 230 | S31: =VLOOKUP(Tabela1[[#This Row],[Tag do Cabo]],'Diagramas Ligações'!A:V,14,0) -> 8 | T31: BK-SP54-00200-LC-80-00699_00000 | U31: 2 | V31: Controle 1/18 | W31: INST-1250 | X31: 44177 | Y31: 44210 | Z31: 08/01/2021: Em compra 14/01/2021: Liberação da Bobina 217 15/01/2021: Notificado pelo Rogério que a disponibilidade da bobina 217 deve ser desconsiderada para esse circuito. 19/01/2021: Notificado em email que a bobina deve ser a bobina 73. | AA31: 73 | AB31: =IF(AND(Tabela1[[#This Row],[Data de Solcitação do Cabo]]<>0,Tabela1[[#This Row],[Bobina]]<>0),"Disponível",IF(AND(Tabela1[[#This Row],[Data de Solcitação do Cabo]]<>0,Tabela1[[#This Row],[Data de Liberação dos Cabos]]=""),"Pend. Resp.",IF(AND(Tabela1[[#This Row],[Data de Solcitação do Cabo]]<>0,Tabela1[[#This Row],[Bobina]]=""),"Pend. Compra","Não Solic."))) -> Disponível | AC31: PR-LC-0006 | AD31: =IF(Tabela1[[#This Row],[Qtde. Lançada]]>Tabela1[[#This Row],[Comprimento Total]],Tabela1[[#This Row],[Qtde. Lançada]],Tabela1[[#This Row],[Comprimento Total]]) -> 230 | AE31: Digital (N.I.S.) | AF31: 1HVxCCP | AG31: =SUMIF('Lançamento de Cabos'!AE:AK,Tabela1[[#This Row],[Tag do Cabo]],'Lançamento de Cabos'!AG:AG) -> 0 | AH31: =IFERROR(VLOOKUP(Tabela1[[#This Row],[Tag do Cabo]],'Lançamento de Cabos'!AE:AK,7,0),0) -> 0 | AI31: BK-SP54-00200-DI-80-05653/BK-SP54-00200-DI-80-05659 | AJ31: 112/104 | AK31: 2009470
A32: 1MV-GAM-906E-001C | B32: Controle | C32: 125 | D32: 0,6/1 | E32: 1x9/C#2,5 | F32: 2.5 | G32: 1 | H32: 40 | I32: 40 | J32: 1HV | K32: PAINEL 1MV | L32: 1MV-GAINE IV (COMANDO) | M32: Sim | N32: ="Sim" -> Sim | O32: --- | P32: --- | Q32: 5.8.1 | R32: =SUMIF('Lançamento de Cabos'!$B:$B,Tabela1[[#This Row],[Tag do Cabo]],'Lançamento de Cabos'!$C:$C) -> 42 | S32: =VLOOKUP(Tabela1[[#This Row],[Tag do Cabo]],'Diagramas Ligações'!A:V,14,0) -> 8 | T32: BK-SP54-0900A-LC-74-00001_00000 | U32: 5 | V32: Controle 2/18 | W32: ELE-0800 | X32: 44177 | Y32: 44218 | Z32: 22/01/2021: Liberação da Bobina, Nota 3: Esta bobina foi paga para a Montcalm em 23-11-20, já para atender estes circuitos. Verificar - bobina deve estar em posse da Montcam ou a mesma não retirou do almoxarifado. | AA32: 71 | AB32: =IF(AND(Tabela1[[#This Row],[Data de Solcitação do Cabo]]<>0,Tabela1[[#This Row],[Bobina]]<>0),"Disponível",IF(AND(Tabela1[[#This Row],[Data de Solcitação do Cabo]]<>0,Tabela1[[#This Row],[Data de Liberação dos Cabos]]=""),"Pend. Resp.",IF(AND(Tabela1[[#This Row],[Data de Solcitação do Cabo]]<>0,Tabela1[[#This Row],[Bobina]]=""),"Pend. Compra","Não Solic."))) -> Disponível | AC32: PR-LC-0007 | AD32: =IF(Tabela1[[#This Row],[Qtde. Lançada]]>Tabela1[[#This Row],[Comprimento Total]],Tabela1[[#This Row],[Qtde. Lançada]],Tabela1[[#This Row],[Comprimento Total]]) -> 42 | AE32: - | AF32: 1MV | AG32: =SUMIF('Lançamento de Cabos'!AE:AK,Tabela1[[#This Row],[Tag do Cabo]],'Lançamento de Cabos'!AG:AG) -> 0 | AH32: =IFERROR(VLOOKUP(Tabela1[[#This Row],[Tag do Cabo]],'Lançamento de Cabos'!AE:AK,7,0),0) -> 0 | AI32: BK-SP54-0900B-DI-74-00452 | AJ32: 2 | AK32: 932951
A33: 1MV-GBM-967B-001C | B33: Controle | C33: 125 | D33: 0,6/1 | E33: 1x9/C#2,5 | F33: 2.5 | G33: 1 | H33: 40 | I33: 40 | J33: 1HV | K33: PAINEL 1MV | L33: 1MV-GAINE IV (COMANDO) | M33: Sim | N33: ="Sim" -> Sim | O33: --- | P33: --- | Q33: 5.8.1 | R33: =SUMIF('Lançamento de Cabos'!$B:$B,Tabela1[[#This Row],[Tag do Cabo]],'Lançamento de Cabos'!$C:$C) -> 47 | S33: =VLOOKUP(Tabela1[[#This Row],[Tag do Cabo]],'Diagramas Ligações'!A:V,14,0) -> 8 | T33: BK-SP54-0900A-LC-74-00001_00000 | U33: 5 | V33: Controle 2/18 | W33: ELE-1250 | X33: 44177 | Y33: 44218 | Z33: 22/01/2021: Liberação da Bobina, Nota 3: Esta bobina foi paga para a Montcalm em 23-11-20, já para atender estes circuitos. Verificar - bobina deve estar em posse da Montcam ou a mesma não retirou do almoxarifado. | AA33: 71 | AB33: =IF(AND(Tabela1[[#This Row],[Data de Solcitação do Cabo]]<>0,Tabela1[[#This Row],[Bobina]]<>0),"Disponível",IF(AND(Tabela1[[#This Row],[Data de Solcitação do Cabo]]<>0,Tabela1[[#This Row],[Data de Liberação dos Cabos]]=""),"Pend. Resp.",IF(AND(Tabela1[[#This Row],[Data de Solcitação do Cabo]]<>0,Tabela1[[#This Row],[Bobina]]=""),"Pend. Compra","Não Solic."))) -> Disponível | AC33: PR-LC-0007 | AD33: =IF(Tabela1[[#This Row],[Qtde. Lançada]]>Tabela1[[#This Row],[Comprimento Total]],Tabela1[[#This Row],[Qtde. Lançada]],Tabela1[[#This Row],[Comprimento Total]]) -> 47 | AE33: - | AF33: 1MV | AG33: =SUMIF('Lançamento de Cabos'!AE:AK,Tabela1[[#This Row],[Tag do Cabo]],'Lançamento de Cabos'!AG:AG) -> 0 | AH33: =IFERROR(VLOOKUP(Tabela1[[#This Row],[Tag do Cabo]],'Lançamento de Cabos'!AE:AK,7,0),0) -> 0 | AI33: BK-SP54-0900B-DI-74-00452 | AJ33: 1 | AK33: 932951
A34: 1MV-GBM-208A-001C | B34: Controle | C34: 125 | D34: 0,6/1 | E34: 1x9/C#2,5 | F34: 2.5 | G34: 1 | H34: 40 | I34: 40 | J34: 1HV | K34: PAINEL 1MV | L34: 1MV-GAINE IV (COMANDO) | M34: Sim | N34: ="Sim" -> Sim | O34: --- | P34: --- | Q34: 5.8.1 | R34: =SUMIF('Lançamento de Cabos'!$B:$B,Tabela1[[#This Row],[Tag do Cabo]],'Lançamento de Cabos'!$C:$C) -> 45 | S34: =VLOOKUP(Tabela1[[#This Row],[Tag do Cabo]],'Diagramas Ligações'!A:V,14,0) -> 12 | T34: BK-SP54-0900A-LC-74-00001_00000 | U34: 5 | V34: Controle 2/18 | W34: ELE-1090 | X34: 44177 | Y34: 44218 | Z34: 22/01/2021: Liberação da Bobina, Nota 3: Esta bobina foi paga para a Montcalm em 23-11-20, já para atender estes circuitos. Verificar - bobina deve estar em posse da Montcam ou a mesma não retirou do almoxarifado. 02/03/2021: Alterada a bobina de 71 para 225, avaliar se atenderá o lançamento dos cabos. | AA34: 225 | AB34: =IF(AND(Tabela1[[#This Row],[Data de Solcitação do Cabo]]<>0,Tabela1[[#This Row],[Bobina]]<>0),"Disponível",IF(AND(Tabela1[[#This Row],[Data de Solcitação do Cabo]]<>0,Tabela1[[#This Row],[Data de Liberação dos Cabos]]=""),"Pend. Resp.",IF(AND(Tabela1[[#This Row],[Data de Solcitação do Cabo]]<>0,Tabela1[[#This Row],[Bobina]]=""),"Pend. Compra","Não Solic."))) -> Disponível | AC34: PR-LC-0007 | AD34: =IF(Tabela1[[#This Row],[Qtde. Lançada]]>Tabela1[[#This Row],[Comprimento Total]],Tabela1[[#This Row],[Qtde. Lançada]],Tabela1[[#This Row],[Comprimento Total]]) -> 45 | AE34: - | AF34: 1MV | AG34: =SUMIF('Lançamento de Cabos'!AE:AK,Tabela1[[#This Row],[Tag do Cabo]],'Lançamento de Cabos'!AG:AG) -> 0 | AH34: =IFERROR(VLOOKUP(Tabela1[[#This Row],[Tag do Cabo]],'Lançamento de Cabos'!AE:AK,7,0),0) -> 0 | AI34: BK-SP54-0900B-DI-74-00452 | AJ34: 5 | AK34: 932951
A35: 1MV-GBM-967A-001C | B35: Controle | C35: 125 | D35: 0,6/1 | E35: 1x9/C#2,5 | F35: 2.5 | G35: 1 | H35: 40 | I35: 40 | J35: 1HV | K35: PAINEL 1MV | L35: 1MV-GAINE IV (COMANDO) | M35: Sim | N35: ="Sim" -> Sim | O35: --- | P35: --- | Q35: 5.8.1 | R35: =SUMIF('Lançamento de Cabos'!$B:$B,Tabela1[[#This Row],[Tag do Cabo]],'Lançamento de Cabos'!$C:$C) -> 40 | S35: =VLOOKUP(Tabela1[[#This Row],[Tag do Cabo]],'Diagramas Ligações'!A:V,14,0) -> 8 | T35: BK-SP54-0900A-LC-74-00001_00000 | U35: 5 | V35: Controle 2/18 | W35: ELE-1150 | X35: 44177 | Y35: 44218 | Z35: 22/01/2021: Liberação da Bobina, Nota 3: Esta bobina foi paga para a Montcalm em 23-11-20, já para atender estes circuitos. Verificar - bobina deve estar em posse da Montcam ou a mesma não retirou do almoxarifado. 02/03/2021: Alterada a bobina de 71 para 225, avaliar se atenderá o lançamento dos cabos. | AA35: 225 | AB35: =IF(AND(Tabela1[[#This Row],[Data de Solcitação do Cabo]]<>0,Tabela1[[#This Row],[Bobina]]<>0),"Disponível",IF(AND(Tabela1[[#This Row],[Data de Solcitação do Cabo]]<>0,Tabela1[[#This Row],[Data de Liberação dos Cabos]]=""),"Pend. Resp.",IF(AND(Tabela1[[#This Row],[Data de Solcitação do Cabo]]<>0,Tabela1[[#This Row],[Bobina]]=""),"Pend. Compra","Não Solic."))) -> Disponível | AC35: PR-LC-0007 | AD35: =IF(Tabela1[[#This Row],[Qtde. Lançada]]>Tabela1[[#This Row],[Comprimento Total]],Tabela1[[#This Row],[Qtde. Lançada]],Tabela1[[#This Row],[Comprimento Total]]) -> 40 | AE35: - | AF35: 1MV | AG35: =SUMIF('Lançamento de Cabos'!AE:AK,Tabela1[[#This Row],[Tag do Cabo]],'Lançamento de Cabos'!AG:AG) -> 0 | AH35: =IFERROR(VLOOKUP(Tabela1[[#This Row],[Tag do Cabo]],'Lançamento de Cabos'!AE:AK,7,0),0) -> 0 | AI35: BK-SP54-0900B-DI-74-00452 | AJ35: 4 | AK35: 932951
A36: U-91156 | B36: Controle | C36: - | D36: - | E36: 1P#1,5mm²+SHI | F36: 1.5 | G36: 1 | H36: 150 | I36: 150 | J36: 1HV | K36: SALA EL. 1MV (CCM - GBM-967A) | L36: SIS - TMR-XVIII | M36: Sim | N36: ="Sim" -> Sim | O36: --- | P36: --- | Q36: 4.6.1 | R36: =SUMIF('Lançamento de Cabos'!$B:$B,Tabela1[[#This Row],[Tag do Cabo]],'Lançamento de Cabos'!$C:$C) -> 150 | S36: =VLOOKUP(Tabela1[[#This Row],[Tag do Cabo]],'Diagramas Ligações'!A:V,14,0) -> 4 | T36: BK-SP54-0900A-LC-80-00187_00000 | U36: 2 | V36: Controle 1/18 | W36: INST-1610 | X36: 44177 | Y36: 44204 | Z36: 08/01/2021: Liberação da bobina | AA36: NE 901166 | AB36: =IF(AND(Tabela1[[#This Row],[Data de Solcitação do Cabo]]<>0,Tabela1[[#This Row],[Bobina]]<>0),"Disponível",IF(AND(Tabela1[[#This Row],[Data de Solcitação do Cabo]]<>0,Tabela1[[#This Row],[Data de Liberação dos Cabos]]=""),"Pend. Resp.",IF(AND(Tabela1[[#This Row],[Data de Solcitação do Cabo]]<>0,Tabela1[[#This Row],[Bobina]]=""),"Pend. Compra","Não Solic."))) -> Disponível | AC36: PR-LC-0008 | AD36: =IF(Tabela1[[#This Row],[Qtde. Lançada]]>Tabela1[[#This Row],[Comprimento Total]],Tabela1[[#This Row],[Qtde. Lançada]],Tabela1[[#This Row],[Comprimento Total]]) -> 150 | AE36: Digital (N.I.S.) | AF36: 1MVxCCU | AG36: =SUMIF('Lançamento de Cabos'!AE:AK,Tabela1[[#This Row],[Tag do Cabo]],'Lançamento de Cabos'!AG:AG) -> 0 | AH36: =IFERROR(VLOOKUP(Tabela1[[#This Row],[Tag do Cabo]],'Lançamento de Cabos'!AE:AK,7,0),0) -> 0 | AI36: BK-SP54-0900A-DI-80-01645/BK-SP54-0900A-DI-80-01646 | AJ36: 1/37 | AK36: 901166
A37: U-91157 | B37: Controle | C37: - | D37: - | E37: 2P#1,0mm²+SHI+SHC | F37: 1 | G37: 1 | H37: 150 | I37: 150 | J37: 1HV | K37: SALA EL. 1MV (CCM - GBM-967A) | L37: SIS - TMR-XVIII | M37: Sim | N37: ="Sim" -> Sim | O37: --- | P37: --- | Q37: 4.6.1 | R37: =SUMIF('Lançamento de Cabos'!$B:$B,Tabela1[[#This Row],[Tag do Cabo]],'Lançamento de Cabos'!$C:$C) -> 150 | S37: =VLOOKUP(Tabela1[[#This Row],[Tag do Cabo]],'Diagramas Ligações'!A:V,14,0) -> 8 | T37: BK-SP54-0900A-LC-80-00187_00000 | U37: 2 | V37: Controle 1/18 | W37: INST-1610 | X37: 44177 | Y37: 44204 | Z37: 08/01/2021: Liberação da bobina | AA37: 73 | AB37: =IF(AND(Tabela1[[#This Row],[Data de Solcitação do Cabo]]<>0,Tabela1[[#This Row],[Bobina]]<>0),"Disponível",IF(AND(Tabela1[[#This Row],[Data de Solcitação do Cabo]]<>0,Tabela1[[#This Row],[Data de Liberação dos Cabos]]=""),"Pend. Resp.",IF(AND(Tabela1[[#This Row],[Data de Solcitação do Cabo]]<>0,Tabela1[[#This Row],[Bobina]]=""),"Pend. Compra","Não Solic."))) -> Disponível | AC37: PR-LC-0008 | AD37: =IF(Tabela1[[#This Row],[Qtde. Lançada]]>Tabela1[[#This Row],[Comprimento Total]],Tabela1[[#This Row],[Qtde. Lançada]],Tabela1[[#This Row],[Comprimento Total]]) -> 150 | AE37: Digital (N.I.S.) | AF37: 1MVxCCU | AG37: =SUMIF('Lançamento de Cabos'!AE:AK,Tabela1[[#This Row],[Tag do Cabo]],'Lançamento de Cabos'!AG:AG) -> 0 | AH37: =IFERROR(VLOOKUP(Tabela1[[#This Row],[Tag do Cabo]],'Lançamento de Cabos'!AE:AK,7,0),0) -> 0 | AI37: BK-SP54-0900A-DI-80-01645/BK-SP54-0900A-DI-80-01646 | AJ37: 1/1, 47 | AK37: 2009470
A38: U-91158 | B38: Controle | C38: - | D38: - | E38: 1P#1,0mm²+SHI | F38: 1 | G38: 1 | H38: 150 | I38: 150 | J38: 1HV | K38: SALA EL. 1MV (CCM - GBM-967B) | L38: SIS - TMR-XVIII | M38: Sim | N38: ="Sim" -> Sim | O38: --- | P38: --- | Q38: 4.6.1 | R38: =SUMIF('Lançamento de Cabos'!$B:$B,Tabela1[[#This Row],[Tag do Cabo]],'Lançamento de Cabos'!$C:$C) -> 150 | S38: =VLOOKUP(Tabela1[[#This Row],[Tag do Cabo]],'Diagramas Ligações'!A:V,14,0) -> 4 | T38: BK-SP54-0900A-LC-80-00187_00000 | U38: 2 | V38: Controle 1/18 | W38: INST-1610 | X38: 44177 | Y38: 44204 | Z38: 08/01/2021: Liberação da bobina | AA38: 170 | AB38: =IF(AND(Tabela1[[#This Row],[Data de Solcitação do Cabo]]<>0,Tabela1[[#This Row],[Bobina]]<>0),"Disponível",IF(AND(Tabela1[[#This Row],[Data de Solcitação do Cabo]]<>0,Tabela1[[#This Row],[Data de Liberação dos Cabos]]=""),"Pend. Resp.",IF(AND(Tabela1[[#This Row],[Data de Solcitação do Cabo]]<>0,Tabela1[[#This Row],[Bobina]]=""),"Pend. Compra","Não Solic."))) -> Disponível | AC38: PR-LC-0008 | AD38: =IF(Tabela1[[#This Row],[Qtde. Lançada]]>Tabela1[[#This Row],[Comprimento Total]],Tabela1[[#This Row],[Qtde. Lançada]],Tabela1[[#This Row],[Comprimento Total]]) -> 150 | AE38: Digital (N.I.S.) | AF38: 1MVxCCU | AG38: =SUMIF('Lançamento de Cabos'!AE:AK,Tabela1[[#This Row],[Tag do Cabo]],'Lançamento de Cabos'!AG:AG) -> 0 | AH38: =IFERROR(VLOOKUP(Tabela1[[#This Row],[Tag do Cabo]],'Lançamento de Cabos'!AE:AK,7,0),0) -> 0 | AI38: BK-SP54-0900A-DI-80-01645/BK-SP54-0900A-DI-80-01646 | AJ38: 3/44 | AK38: 306860
A39: U-91159 | B39: Controle | C39: - | D39: - | E39: 2P#1,0mm²+SHI+SHC | F39: 1 | G39: 1 | H39: 150 | I39: 150 | J39: 1HV | K39: SALA EL. 1MV (CCM - GBM-967B) | L39: SIS - TMR-XVIII | M39: Sim | N39: ="Sim" -> Sim | O39: --- | P39: --- | Q39: 4.6.1 | R39: =SUMIF('Lançamento de Cabos'!$B:$B,Tabela1[[#This Row],[Tag do Cabo]],'Lançamento de Cabos'!$C:$C) -> 150 | S39: =VLOOKUP(Tabela1[[#This Row],[Tag do Cabo]],'Diagramas Ligações'!A:V,14,0) -> 8 | T39: BK-SP54-0900A-LC-80-00187_00000 | U39: 2 | V39: Controle 1/18 | W39: INST-1610 | X39: 44177 | Y39: 44210 | Z39: 14/01/2021: Liberação da bobina | AA39: 217 | AB39: =IF(AND(Tabela1[[#This Row],[Data de Solcitação do Cabo]]<>0,Tabela1[[#This Row],[Bobina]]<>0),"Disponível",IF(AND(Tabela1[[#This Row],[Data de Solcitação do Cabo]]<>0,Tabela1[[#This Row],[Data de Liberação dos Cabos]]=""),"Pend. Resp.",IF(AND(Tabela1[[#This Row],[Data de Solcitação do Cabo]]<>0,Tabela1[[#This Row],[Bobina]]=""),"Pend. Compra","Não Solic."))) -> Disponível | AC39: PR-LC-0008 | AD39: =IF(Tabela1[[#This Row],[Qtde. Lançada]]>Tabela1[[#This Row],[Comprimento Total]],Tabela1[[#This Row],[Qtde. Lançada]],Tabela1[[#This Row],[Comprimento Total]]) -> 150 | AE39: Digital (N.I.S.) | AF39: 1MVxCCU | AG39: =SUMIF('Lançamento de Cabos'!AE:AK,Tabela1[[#This Row],[Tag do Cabo]],'Lançamento de Cabos'!AG:AG) -> 0 | AH39: =IFERROR(VLOOKUP(Tabela1[[#This Row],[Tag do Cabo]],'Lançamento de Cabos'!AE:AK,7,0),0) -> 0 | AI39: BK-SP54-0900A-DI-80-01645/BK-SP54-0900A-DI-80-01646 | AJ39: 3/16, 48 | AK39: 2009470
A40: 1MV-GAM-906E-001AQ-ANT | B40: Força | C40: 120 | D40: 0,6/1 | E40: 1x2/C#4 | F40: 4 | G40: 1 | H40: 170 | I40: 170 | J40: GA-906E | K40: PAINEL DE RESISTENCIA DE AQUECIMENTO | L40: MOTOR GAM-906E (AQUECIMENTO) | M40: Sim | N40: --- | O40: ="Sim" -> Sim | P40: --- | Q40: 5.10.2 | R40: =SUMIF('Lançamento de Cabos'!$B:$B,Tabela1[[#This Row],[Tag do Cabo]],'Lançamento de Cabos'!$C:$C) -> 170 | S40: =VLOOKUP(Tabela1[[#This Row],[Tag do Cabo]],'Diagramas Ligações'!A:V,14,0) -> 4 | T40: BK-SP54-0900A-LC-74-00001_00000 | U40: 5 | W40: ELE-0800 | X40: 44177 | Y40: 44218 | Z40: 22/01/2021: Liberação da Bobina | AA40: 178 | AB40: =IF(AND(Tabela1[[#This Row],[Data de Solcitação do Cabo]]<>0,Tabela1[[#This Row],[Bobina]]<>0),"Disponível",IF(AND(Tabela1[[#This Row],[Data de Solcitação do Cabo]]<>0,Tabela1[[#This Row],[Data de Liberação dos Cabos]]=""),"Pend. Resp.",IF(AND(Tabela1[[#This Row],[Data de Solcitação do Cabo]]<>0,Tabela1[[#This Row],[Bobina]]=""),"Pend. Compra","Não Solic."))) -> Disponível | AC40: PR-LC-0007 | AD40: =IF(Tabela1[[#This Row],[Qtde. Lançada]]>Tabela1[[#This Row],[Comprimento Total]],Tabela1[[#This Row],[Qtde. Lançada]],Tabela1[[#This Row],[Comprimento Total]]) -> 170 | AE40: - | AF40: 1MVxGA-906E | AG40: =SUMIF('Lançamento de Cabos'!AE:AK,Tabela1[[#This Row],[Tag do Cabo]],'Lançamento de Cabos'!AG:AG) -> 0 | AH40: =IFERROR(VLOOKUP(Tabela1[[#This Row],[Tag do Cabo]],'Lançamento de Cabos'!AE:AK,7,0),0) -> 0 | AI40: BK-SP54-0900B-DI-74-00452 | AJ40: 2 | AK40: 3160463
A41: 1MV-GAM-906E-001F | B41: Força | C41: 2400 | D41: 3,6/6 | E41: 3x1x1/C#185 | F41: 185 | G41: 3 | H41: 170 | I41: 510 | J41: GA-906E | K41: PAINEL 1MV | L41: MOTOR GAM-906E | M41: Sim | N41: --- | O41: Sim | P41: Sim | Q41: 5.2.13 | R41: =SUMIF('Lançamento de Cabos'!$B:$B,Tabela1[[#This Row],[Tag do Cabo]],'Lançamento de Cabos'!$C:$C) -> 510 | S41: =VLOOKUP(Tabela1[[#This Row],[Tag do Cabo]],'Diagramas Ligações'!A:V,14,0) -> 6 | T41: BK-SP54-0900A-LC-74-00001_00000 | U41: 5 | W41: ELE-0800 | X41: 44177 | Y41: 44218 | Z41: 22/01/2021: Liberação da Bobina, Nota 4: Estas bobinas foram pago para a Montcalm em 15-12-20. Verificar - bobina devem estar em posse da Montcam ou a mesma não retirou do almoxarifado. | AA41: 117 | AB41: =IF(AND(Tabela1[[#This Row],[Data de Solcitação do Cabo]]<>0,Tabela1[[#This Row],[Bobina]]<>0),"Disponível",IF(AND(Tabela1[[#This Row],[Data de Solcitação do Cabo]]<>0,Tabela1[[#This Row],[Data de Liberação dos Cabos]]=""),"Pend. Resp.",IF(AND(Tabela1[[#This Row],[Data de Solcitação do Cabo]]<>0,Tabela1[[#This Row],[Bobina]]=""),"Pend. Compra","Não Solic."))) -> Disponível | AC41: PR-LC-0007 | AD41: =IF(Tabela1[[#This Row],[Qtde. Lançada]]>Tabela1[[#This Row],[Comprimento Total]],Tabela1[[#This Row],[Qtde. Lançada]],Tabela1[[#This Row],[Comprimento Total]]) -> 510 | AE41: - | AF41: 1MVxGA-906E | AG41: =SUMIF('Lançamento de Cabos'!AE:AK,Tabela1[[#This Row],[Tag do Cabo]],'Lançamento de Cabos'!AG:AG) -> 6 | AH41: =IFERROR(VLOOKUP(Tabela1[[#This Row],[Tag do Cabo]],'Lançamento de Cabos'!AE:AK,7,0),0) -> 1 | AI41: BK-SP54-0900B-DI-74-00452 | AJ41: 2 | AK41: 933028
A42: 1MV-GAM-906E-001SA | B42: Controle | C42: 4-20mA | D42: 0.3 | E42: 1x8T#1,0 | F42: 1 | G42: 1 | H42: 170 | I42: 170 | J42: GA-906E | K42: PAINEL 1MV | L42: MOTOR GAM-906E (RTD) | M42: Sim | N42: Sim | O42: --- | P42: --- | Q42: 5.7.1 | R42: =SUMIF('Lançamento de Cabos'!$B:$B,Tabela1[[#This Row],[Tag do Cabo]],'Lançamento de Cabos'!$C:$C) -> 170 | S42: =VLOOKUP(Tabela1[[#This Row],[Tag do Cabo]],'Diagramas Ligações'!A:V,14,0) -> 48 | T42: BK-SP54-0900A-LC-74-00001_00000 | U42: 5 | V42: Controle 1/18 | W42: ELE-0800 | X42: 44177 | Y42: 44218 | Z42: 22/01/2021: Liberação da Bobina, Nota 2: A bobina está com 700m de cabos, para uma necessidade de 780 metros. A Montcalm deve verificar no campo se os 700metros é suficiente (medir rota). | AA42: 130 | AB42: =IF(AND(Tabela1[[#This Row],[Data de Solcitação do Cabo]]<>0,Tabela1[[#This Row],[Bobina]]<>0),"Disponível",IF(AND(Tabela1[[#This Row],[Data de Solcitação do Cabo]]<>0,Tabela1[[#This Row],[Data de Liberação dos Cabos]]=""),"Pend. Resp.",IF(AND(Tabela1[[#This Row],[Data de Solcitação do Cabo]]<>0,Tabela1[[#This Row],[Bobina]]=""),"Pend. Compra","Não Solic."))) -> Disponível | AC42: PR-LC-0007 | AD42: =IF(Tabela1[[#This Row],[Qtde. Lançada]]>Tabela1[[#This Row],[Comprimento Total]],Tabela1[[#This Row],[Qtde. Lançada]],Tabela1[[#This Row],[Comprimento Total]]) -> 170 | AE42: - | AF42: 1MVxGA-906E | AG42: =SUMIF('Lançamento de Cabos'!AE:AK,Tabela1[[#This Row],[Tag do Cabo]],'Lançamento de Cabos'!AG:AG) -> 0 | AH42: =IFERROR(VLOOKUP(Tabela1[[#This Row],[Tag do Cabo]],'Lançamento de Cabos'!AE:AK,7,0),0) -> 0 | AI42: BK-SP54-0900B-DI-74-00452 | AJ42: 2 | AK42: 1414059
A43: 1MV-GAM-906E-002C | B43: Controle | C43: 125 | D43: 0,6/1 | E43: 1x9/C#2,5 | F43: 2.5 | G43: 1 | H43: 170 | I43: 170 | J43: GA-906E | K43: 1MV-GAINE IV | L43: MOTOR GAM-906E (BOTOEIRA) | M43: Sim | N43: ="Sim" -> Sim | O43: --- | P43: --- | Q43: 5.8.1 | R43: =SUMIF('Lançamento de Cabos'!$B:$B,Tabela1[[#This Row],[Tag do Cabo]],'Lançamento de Cabos'!$C:$C) -> 170 | S43: =VLOOKUP(Tabela1[[#This Row],[Tag do Cabo]],'Diagramas Ligações'!A:V,14,0) -> 8 | T43: BK-SP54-0900A-LC-74-00001_00000 | U43: 5 | V43: Controle 2/18 | W43: ELE-0800 | X43: 44177 | Y43: 44218 | Z43: 22/01/2021: Liberação da Bobina, Nota 3: Esta bobina foi paga para a Montcalm em 23-11-20, já para atender estes circuitos. Verificar - bobina deve estar em posse da Montcam ou a mesma não retirou do almoxarifado. | AA43: 71 | AB43: =IF(AND(Tabela1[[#This Row],[Data de Solcitação do Cabo]]<>0,Tabela1[[#This Row],[Bobina]]<>0),"Disponível",IF(AND(Tabela1[[#This Row],[Data de Solcitação do Cabo]]<>0,Tabela1[[#This Row],[Data de Liberação dos Cabos]]=""),"Pend. Resp.",IF(AND(Tabela1[[#This Row],[Data de Solcitação do Cabo]]<>0,Tabela1[[#This Row],[Bobina]]=""),"Pend. Compra","Não Solic."))) -> Disponível | AC43: PR-LC-0007 | AD43: =IF(Tabela1[[#This Row],[Qtde. Lançada]]>Tabela1[[#This Row],[Comprimento Total]],Tabela1[[#This Row],[Qtde. Lançada]],Tabela1[[#This Row],[Comprimento Total]]) -> 170 | AE43: - | AF43: 1MVxGA-906E | AG43: =SUMIF('Lançamento de Cabos'!AE:AK,Tabela1[[#This Row],[Tag do Cabo]],'Lançamento de Cabos'!AG:AG) -> 0 | AH43: =IFERROR(VLOOKUP(Tabela1[[#This Row],[Tag do Cabo]],'Lançamento de Cabos'!AE:AK,7,0),0) -> 0 | AI43: BK-SP54-0900B-DI-74-00452 | AJ43: 2 | AK43: 932951
A44: U-91134 | B44: Controle | C44: - | D44: - | E44: 4P#1,0mm²+SHI+SHC | F44: 1 | G44: 1 | H44: 130 | I44: 130 | J44: GA-906E | K44: SUBESTAÇÃO 1HV/PAINEL 1MV | L44: PL-90-127X - GA-906E | M44: Sim | N44: ="Sim" -> Sim | O44: --- | P44: --- | Q44: 4.6.1 | R44: =SUMIF('Lançamento de Cabos'!$B:$B,Tabela1[[#This Row],[Tag do Cabo]],'Lançamento de Cabos'!$C:$C) -> 130 | S44: =VLOOKUP(Tabela1[[#This Row],[Tag do Cabo]],'Diagramas Ligações'!A:V,14,0) -> 8 | T44: BK-SP54-0900A-LC-80-00185_00000 | U44: 2 | V44: Controle 1/18 | W44: INST-1160 | X44: 44177 | Y44: 44210 | Z44: 14/01/2021: Liberação da bobina | AA44: 125 | AB44: =IF(AND(Tabela1[[#This Row],[Data de Solcitação do Cabo]]<>0,Tabela1[[#This Row],[Bobina]]<>0),"Disponível",IF(AND(Tabela1[[#This Row],[Data de Solcitação do Cabo]]<>0,Tabela1[[#This Row],[Data de Liberação dos Cabos]]=""),"Pend. Resp.",IF(AND(Tabela1[[#This Row],[Data de Solcitação do Cabo]]<>0,Tabela1[[#This Row],[Bobina]]=""),"Pend. Compra","Não Solic."))) -> Disponível | AC44: PR-LC-0007 | AD44: =IF(Tabela1[[#This Row],[Qtde. Lançada]]>Tabela1[[#This Row],[Comprimento Total]],Tabela1[[#This Row],[Qtde. Lançada]],Tabela1[[#This Row],[Comprimento Total]]) -> 130 | AE44: Digital (N.I.S.) | AF44: 1MVxGA-906E | AG44: =SUMIF('Lançamento de Cabos'!AE:AK,Tabela1[[#This Row],[Tag do Cabo]],'Lançamento de Cabos'!AG:AG) -> 0 | AH44: =IFERROR(VLOOKUP(Tabela1[[#This Row],[Tag do Cabo]],'Lançamento de Cabos'!AE:AK,7,0),0) -> 0 | AI44: BK-SP54-0900A-DI-80-01647 | AJ44: 2 | AK44: 1423312
A45: U-91135 | B45: Controle | C45: - | D45: - | E45: 4P#1,0mm²+SHI+SHC | F45: 1 | G45: 1 | H45: 130 | I45: 130 | J45: GA-906E | K45: SUBESTAÇÃO 1HV/PAINEL 1MV | L45: PL-90-127X - GA-906E | M45: Sim | N45: ="Sim" -> Sim | O45: --- | P45: --- | Q45: 4.6.1 | R45: =SUMIF('Lançamento de Cabos'!$B:$B,Tabela1[[#This Row],[Tag do Cabo]],'Lançamento de Cabos'!$C:$C) -> 130 | S45: =VLOOKUP(Tabela1[[#This Row],[Tag do Cabo]],'Diagramas Ligações'!A:V,14,0) -> 8 | T45: BK-SP54-0900A-LC-80-00185_00000 | U45: 2 | V45: Controle 1/18 | W45: INST-1160 | X45: 44177 | Y45: 44210 | Z45: 14/01/2021: Liberação da bobina | AA45: 125 | AB45: =IF(AND(Tabela1[[#This Row],[Data de Solcitação do Cabo]]<>0,Tabela1[[#This Row],[Bobina]]<>0),"Disponível",IF(AND(Tabela1[[#This Row],[Data de Solcitação do Cabo]]<>0,Tabela1[[#This Row],[Data de Liberação dos Cabos]]=""),"Pend. Resp.",IF(AND(Tabela1[[#This Row],[Data de Solcitação do Cabo]]<>0,Tabela1[[#This Row],[Bobina]]=""),"Pend. Compra","Não Solic."))) -> Disponível | AC45: PR-LC-0007 | AD45: =IF(Tabela1[[#This Row],[Qtde. Lançada]]>Tabela1[[#This Row],[Comprimento Total]],Tabela1[[#This Row],[Qtde. Lançada]],Tabela1[[#This Row],[Comprimento Total]]) -> 130 | AE45: Digital (N.I.S.) | AF45: 1MVxGA-906E | AG45: =SUMIF('Lançamento de Cabos'!AE:AK,Tabela1[[#This Row],[Tag do Cabo]],'Lançamento de Cabos'!AG:AG) -> 0 | AH45: =IFERROR(VLOOKUP(Tabela1[[#This Row],[Tag do Cabo]],'Lançamento de Cabos'!AE:AK,7,0),0) -> 0 | AI45: BK-SP54-0900A-DI-80-01647 | AJ45: 3 | AK45: 1423312
A46: 1MV-GAM-208A-001F | B46: Força | C46: 2400 | D46: 3,6/6 | E46: 3x1x1/C#120 | F46: 120 | G46: 3 | H46: 190 | I46: 570 | J46: GB-208A | K46: PAINEL 1MV | L46: MOTOR GAM-208A | M46: Sim | N46: --- | O46: Sim | P46: Sim | Q46: 5.2.13 | R46: =SUMIF('Lançamento de Cabos'!$B:$B,Tabela1[[#This Row],[Tag do Cabo]],'Lançamento de Cabos'!$C:$C) -> 720 | S46: =VLOOKUP(Tabela1[[#This Row],[Tag do Cabo]],'Diagramas Ligações'!A:V,14,0) -> 6 | T46: BK-SP54-0900A-LC-74-00001_00000 | U46: 5 | W46: ELE-1090 | X46: 44177 | Y46: 44218 | Z46: 22/01/2021: Liberação da Bobina, Nota 4: Estas bobinas foram pago para a Montcalm em 15-12-20. Verificar - bobina devem estar em posse da Montcam ou a mesma não retirou do almoxarifado. | AA46: 138 | AB46: =IF(AND(Tabela1[[#This Row],[Data de Solcitação do Cabo]]<>0,Tabela1[[#This Row],[Bobina]]<>0),"Disponível",IF(AND(Tabela1[[#This Row],[Data de Solcitação do Cabo]]<>0,Tabela1[[#This Row],[Data de Liberação dos Cabos]]=""),"Pend. Resp.",IF(AND(Tabela1[[#This Row],[Data de Solcitação do Cabo]]<>0,Tabela1[[#This Row],[Bobina]]=""),"Pend. Compra","Não Solic."))) -> Disponível | AC46: PR-LC-0007 | AD46: =IF(Tabela1[[#This Row],[Qtde. Lançada]]>Tabela1[[#This Row],[Comprimento Total]],Tabela1[[#This Row],[Qtde. Lançada]],Tabela1[[#This Row],[Comprimento Total]]) -> 720 | AE46: - | AF46: 1MVxGB-208A | AG46: =SUMIF('Lançamento de Cabos'!AE:AK,Tabela1[[#This Row],[Tag do Cabo]],'Lançamento de Cabos'!AG:AG) -> 0 | AH46: =IFERROR(VLOOKUP(Tabela1[[#This Row],[Tag do Cabo]],'Lançamento de Cabos'!AE:AK,7,0),0) -> 0 | AI46: BK-SP54-0900B-DI-74-00452 | AJ46: 5 | AK46: 933025
A47: 1MV-GBM-208A-001AQ-ANT | B47: Força | C47: 120 | D47: 0,6/1 | E47: 1x2/C#6 | F47: 6 | G47: 1 | H47: 190 | I47: 190 | J47: GB-208A | K47: PAINEL DE RESISTENCIA DE AQUECIMENTO | L47: MOTOR GAM-208A (AQUECIMENTO) | M47: Sim | N47: --- | O47: ="Sim" -> Sim | P47: --- | Q47: 5.3.3 | R47: =SUMIF('Lançamento de Cabos'!$B:$B,Tabela1[[#This Row],[Tag do Cabo]],'Lançamento de Cabos'!$C:$C) -> 190 | S47: =VLOOKUP(Tabela1[[#This Row],[Tag do Cabo]],'Diagramas Ligações'!A:V,14,0) -> 4 | T47: BK-SP54-0900A-LC-74-00001_00000 | U47: 5 | W47: ELE-1090 | X47: 44177 | Y47: 44218 | Z47: 22/01/2021: Liberação da Bobina 09/02/2021: Cabos em compra (bobina antiga: NE 330264) | AA47: NE 330264 | AB47: =IF(AND(Tabela1[[#This Row],[Data de Solcitação do Cabo]]<>0,Tabela1[[#This Row],[Bobina]]<>0),"Disponível",IF(AND(Tabela1[[#This Row],[Data de Solcitação do Cabo]]<>0,Tabela1[[#This Row],[Data de Liberação dos Cabos]]=""),"Pend. Resp.",IF(AND(Tabela1[[#This Row],[Data de Solcitação do Cabo]]<>0,Tabela1[[#This Row],[Bobina]]=""),"Pend. Compra","Não Solic."))) -> Disponível | AC47: PR-LC-0007 | AD47: =IF(Tabela1[[#This Row],[Qtde. Lançada]]>Tabela1[[#This Row],[Comprimento Total]],Tabela1[[#This Row],[Qtde. Lançada]],Tabela1[[#This Row],[Comprimento Total]]) -> 190 | AE47: - | AF47: 1MVxGB-208A | AG47: =SUMIF('Lançamento de Cabos'!AE:AK,Tabela1[[#This Row],[Tag do Cabo]],'Lançamento de Cabos'!AG:AG) -> 0 | AH47: =IFERROR(VLOOKUP(Tabela1[[#This Row],[Tag do Cabo]],'Lançamento de Cabos'!AE:AK,7,0),0) -> 0 | AI47: BK-SP54-0900B-DI-74-00452 | AJ47: 5 | AK47: 330264
A48: 1MV-GBM-208A-001SA | B48: Controle | C48: 4-20mA | D48: 0.3 | E48: 1x8T#1,0 | F48: 1 | G48: 1 | H48: 190 | I48: 190 | J48: GB-208A | K48: PAINEL 1MV | L48: MOTOR GBM-208A (RTD) | M48: Sim | N48: Sim | O48: --- | P48: --- | Q48: 5.7.1 | R48: =SUMIF('Lançamento de Cabos'!$B:$B,Tabela1[[#This Row],[Tag do Cabo]],'Lançamento de Cabos'!$C:$C) -> 190 | S48: =VLOOKUP(Tabela1[[#This Row],[Tag do Cabo]],'Diagramas Ligações'!A:V,14,0) -> 48 | T48: BK-SP54-0900A-LC-74-00001_00000 | U48: 5 | V48: Controle 1/18 | W48: ELE-1090 | X48: 44177 | Y48: 44218 | Z48: 22/01/2021: Liberação da Bobina, Nota 2: A bobina está com 700m de cabos, para uma necessidade de 780 metros. A Montcalm deve verificar no campo se os 700metros é suficiente (medir rota). 09/02/2021: Cabos em compra (bobina antiga: 130) | AA48: 130 | AB48: =IF(AND(Tabela1[[#This Row],[Data de Solcitação do Cabo]]<>0,Tabela1[[#This Row],[Bobina]]<>0),"Disponível",IF(AND(Tabela1[[#This Row],[Data de Solcitação do Cabo]]<>0,Tabela1[[#This Row],[Data de Liberação dos Cabos]]=""),"Pend. Resp.",IF(AND(Tabela1[[#This Row],[Data de Solcitação do Cabo]]<>0,Tabela1[[#This Row],[Bobina]]=""),"Pend. Compra","Não Solic."))) -> Disponível | AC48: PR-LC-0007 | AD48: =IF(Tabela1[[#This Row],[Qtde. Lançada]]>Tabela1[[#This Row],[Comprimento Total]],Tabela1[[#This Row],[Qtde. Lançada]],Tabela1[[#This Row],[Comprimento Total]]) -> 190 | AE48: - | AF48: 1MVxGB-208A | AG48: =SUMIF('Lançamento de Cabos'!AE:AK,Tabela1[[#This Row],[Tag do Cabo]],'Lançamento de Cabos'!AG:AG) -> 0 | AH48: =IFERROR(VLOOKUP(Tabela1[[#This Row],[Tag do Cabo]],'Lançamento de Cabos'!AE:AK,7,0),0) -> 0 | AI48: BK-SP54-0900B-DI-74-00452 | AJ48: 5 | AK48: 1414059
A49: 1MV-GBM-208A-002C | B49: Controle | C49: 125 | D49: 0,6/1 | E49: 1x9/C#2,5 | F49: 2.5 | G49: 1 | H49: 190 | I49: 190 | J49: GB-208A | K49: 1MV-GAINE IV | L49: MOTOR GBM-208A (BOTOEIRA) | M49: Sim | N49: ="Sim" -> Sim | O49: --- | P49: --- | Q49: 5.8.1 | R49: =SUMIF('Lançamento de Cabos'!$B:$B,Tabela1[[#This Row],[Tag do Cabo]],'Lançamento de Cabos'!$C:$C) -> 190 | S49: =VLOOKUP(Tabela1[[#This Row],[Tag do Cabo]],'Diagramas Ligações'!A:V,14,0) -> 12 | T49: BK-SP54-0900A-LC-74-00001_00000 | U49: 5 | V49: Controle 2/18 | W49: ELE-1090 | X49: 44177 | Y49: 44218 | Z49: 22/01/2021: Liberação da Bobina, Nota 3: Esta bobina foi paga para a Montcalm em 23-11-20, já para atender estes circuitos. Verificar - bobina deve estar em posse da Montcam ou a mesma não retirou do almoxarifado. 09/02/2021: Cabos em compra (bobina antiga: 71) | AA49: NE 932951 | AB49: =IF(AND(Tabela1[[#This Row],[Data de Solcitação do Cabo]]<>0,Tabela1[[#This Row],[Bobina]]<>0),"Disponível",IF(AND(Tabela1[[#This Row],[Data de Solcitação do Cabo]]<>0,Tabela1[[#This Row],[Data de Liberação dos Cabos]]=""),"Pend. Resp.",IF(AND(Tabela1[[#This Row],[Data de Solcitação do Cabo]]<>0,Tabela1[[#This Row],[Bobina]]=""),"Pend. Compra","Não Solic."))) -> Disponível | AC49: PR-LC-0007 | AD49: =IF(Tabela1[[#This Row],[Qtde. Lançada]]>Tabela1[[#This Row],[Comprimento Total]],Tabela1[[#This Row],[Qtde. Lançada]],Tabela1[[#This Row],[Comprimento Total]]) -> 190 | AE49: - | AF49: 1MVxGB-208A | AG49: =SUMIF('Lançamento de Cabos'!AE:AK,Tabela1[[#This Row],[Tag do Cabo]],'Lançamento de Cabos'!AG:AG) -> 0 | AH49: =IFERROR(VLOOKUP(Tabela1[[#This Row],[Tag do Cabo]],'Lançamento de Cabos'!AE:AK,7,0),0) -> 0 | AI49: BK-SP54-0900B-DI-74-00452 | AJ49: 5 | AK49: 932951
A50: 1MV-GBM-967A-001AQ-ANT | B50: Força | C50: 120 | D50: 0,6/1 | E50: 1x2/C#10 | F50: 10 | G50: 1 | H50: 210 | I50: 210 | J50: GB-967A/B | K50: PAINEL DE RESISTENCIA DE AQUECIMENTO | L50: MOTOR GBM-967A (AQUECIMENTO) | M50: Sim | N50: --- | O50: ="Sim" -> Sim | P50: --- | Q50: 5.5.2 | R50: =SUMIF('Lançamento de Cabos'!$B:$B,Tabela1[[#This Row],[Tag do Cabo]],'Lançamento de Cabos'!$C:$C) -> 210 | S50: =VLOOKUP(Tabela1[[#This Row],[Tag do Cabo]],'Diagramas Ligações'!A:V,14,0) -> 4 | T50: BK-SP54-0900A-LC-74-00001_00000 | U50: 5 | W50: ELE-1150 | X50: 44177 | Y50: 44218 | Z50: 22/01/2021: Liberação da Bobina | AA50: 171 | AB50: =IF(AND(Tabela1[[#This Row],[Data de Solcitação do Cabo]]<>0,Tabela1[[#This Row],[Bobina]]<>0),"Disponível",IF(AND(Tabela1[[#This Row],[Data de Solcitação do Cabo]]<>0,Tabela1[[#This Row],[Data de Liberação dos Cabos]]=""),"Pend. Resp.",IF(AND(Tabela1[[#This Row],[Data de Solcitação do Cabo]]<>0,Tabela1[[#This Row],[Bobina]]=""),"Pend. Compra","Não Solic."))) -> Disponível | AC50: PR-LC-0007 | AD50: =IF(Tabela1[[#This Row],[Qtde. Lançada]]>Tabela1[[#This Row],[Comprimento Total]],Tabela1[[#This Row],[Qtde. Lançada]],Tabela1[[#This Row],[Comprimento Total]]) -> 210 | AE50: - | AF50: 1MVxGB-967A | AG50: =SUMIF('Lançamento de Cabos'!AE:AK,Tabela1[[#This Row],[Tag do Cabo]],'Lançamento de Cabos'!AG:AG) -> 0 | AH50: =IFERROR(VLOOKUP(Tabela1[[#This Row],[Tag do Cabo]],'Lançamento de Cabos'!AE:AK,7,0),0) -> 0 | AI50: BK-SP54-0900B-DI-74-00452 | AJ50: 4 | AK50: 932805
A51: 1MV-GBM-967A-001F | B51: Força | C51: 2400 | D51: 3,6/6 | E51: 3x1x1/C#120 | F51: 120 | G51: 3 | H51: 210 | I51: 630 | J51: GB-967A/B | K51: PAINEL 1MV | L51: MOTOR GBM-967A | M51: Sim | N51: --- | O51: Sim | P51: Sim | Q51: 5.2.13 | R51: =SUMIF('Lançamento de Cabos'!$B:$B,Tabela1[[#This Row],[Tag do Cabo]],'Lançamento de Cabos'!$C:$C) -> 630 | S51: =VLOOKUP(Tabela1[[#This Row],[Tag do Cabo]],'Diagramas Ligações'!A:V,14,0) -> 6 | T51: BK-SP54-0900A-LC-74-00001_00000 | U51: 5 | W51: ELE-1150 | X51: 44177 | Y51: 44218 | Z51: 22/01/2021: Liberação da Bobina, Nota 4: Estas bobinas foram pago para a Montcalm em 15-12-20. Verificar - bobina devem estar em posse da Montcam ou a mesma não retirou do almoxarifado. | AA51: 27 | AB51: =IF(AND(Tabela1[[#This Row],[Data de Solcitação do Cabo]]<>0,Tabela1[[#This Row],[Bobina]]<>0),"Disponível",IF(AND(Tabela1[[#This Row],[Data de Solcitação do Cabo]]<>0,Tabela1[[#This Row],[Data de Liberação dos Cabos]]=""),"Pend. Resp.",IF(AND(Tabela1[[#This Row],[Data de Solcitação do Cabo]]<>0,Tabela1[[#This Row],[Bobina]]=""),"Pend. Compra","Não Solic."))) -> Disponível | AC51: PR-LC-0007 | AD51: =IF(Tabela1[[#This Row],[Qtde. Lançada]]>Tabela1[[#This Row],[Comprimento Total]],Tabela1[[#This Row],[Qtde. Lançada]],Tabela1[[#This Row],[Comprimento Total]]) -> 630 | AE51: - | AF51: 1MVxGB-967A | AG51: =SUMIF('Lançamento de Cabos'!AE:AK,Tabela1[[#This Row],[Tag do Cabo]],'Lançamento de Cabos'!AG:AG) -> 0 | AH51: =IFERROR(VLOOKUP(Tabela1[[#This Row],[Tag do Cabo]],'Lançamento de Cabos'!AE:AK,7,0),0) -> 0 | AI51: BK-SP54-0900B-DI-74-00452 | AJ51: 4 | AK51: 933025
A52: 1MV-GBM-967A-001SA | B52: Controle | C52: 4-20mA | D52: 0.3 | E52: 1x8T#1,0 | F52: 1 | G52: 1 | H52: 210 | I52: 210 | J52: GB-967A/B | K52: PAINEL 1MV | L52: MOTOR GBM-967A (RTD) | M52: Sim | N52: Sim | O52: --- | P52: --- | Q52: 5.7.1 | R52: =SUMIF('Lançamento de Cabos'!$B:$B,Tabela1[[#This Row],[Tag do Cabo]],'Lançamento de Cabos'!$C:$C) -> 210 | S52: =VLOOKUP(Tabela1[[#This Row],[Tag do Cabo]],'Diagramas Ligações'!A:V,14,0) -> 48 | T52: BK-SP54-0900A-LC-74-00001_00000 | U52: 5 | V52: Controle 1/18 | W52: ELE-1150 | X52: 44177 | Y52: 44218 | Z52: 22/01/2021: Liberação da Bobina, Nota 2: A bobina está com 700m de cabos, para uma necessidade de 780 metros. A Montcalm deve verificar no campo se os 700metros é suficiente (medir rota). | AA52: 130 | AB52: =IF(AND(Tabela1[[#This Row],[Data de Solcitação do Cabo]]<>0,Tabela1[[#This Row],[Bobina]]<>0),"Disponível",IF(AND(Tabela1[[#This Row],[Data de Solcitação do Cabo]]<>0,Tabela1[[#This Row],[Data de Liberação dos Cabos]]=""),"Pend. Resp.",IF(AND(Tabela1[[#This Row],[Data de Solcitação do Cabo]]<>0,Tabela1[[#This Row],[Bobina]]=""),"Pend. Compra","Não Solic."))) -> Disponível | AC52: PR-LC-0007 | AD52: =IF(Tabela1[[#This Row],[Qtde. Lançada]]>Tabela1[[#This Row],[Comprimento Total]],Tabela1[[#This Row],[Qtde. Lançada]],Tabela1[[#This Row],[Comprimento Total]]) -> 210 | AE52: - | AF52: 1MVxGB-967A | AG52: =SUMIF('Lançamento de Cabos'!AE:AK,Tabela1[[#This Row],[Tag do Cabo]],'Lançamento de Cabos'!AG:AG) -> 0 | AH52: =IFERROR(VLOOKUP(Tabela1[[#This Row],[Tag do Cabo]],'Lançamento de Cabos'!AE:AK,7,0),0) -> 0 | AI52: BK-SP54-0900B-DI-74-00452 | AJ52: 4 | AK52: 1414059
A53: 1MV-GBM-967A-002C | B53: Controle | C53: 125 | D53: 0,6/1 | E53: 1x9/C#2,5 | F53: 2.5 | G53: 1 | H53: 210 | I53: 210 | J53: GB-967A/B | K53: 1MV-GAINE IV | L53: MOTOR GBM-967A (BOTOEIRA) | M53: Sim | N53: ="Sim" -> Sim | O53: --- | P53: --- | Q53: 5.8.1 | R53: =SUMIF('Lançamento de Cabos'!$B:$B,Tabela1[[#This Row],[Tag do Cabo]],'Lançamento de Cabos'!$C:$C) -> 210 | S53: =VLOOKUP(Tabela1[[#This Row],[Tag do Cabo]],'Diagramas Ligações'!A:V,14,0) -> 8 | T53: BK-SP54-0900A-LC-74-00001_00000 | U53: 5 | V53: Controle 2/18 | W53: ELE-1150 | X53: 44177 | Y53: 44218 | Z53: 22/01/2021: Liberação da Bobina, Nota 3: Esta bobina foi paga para a Montcalm em 23-11-20, já para atender estes circuitos. Verificar - bobina deve estar em posse da Montcam ou a mesma não retirou do almoxarifado. | AA53: 71 | AB53: =IF(AND(Tabela1[[#This Row],[Data de Solcitação do Cabo]]<>0,Tabela1[[#This Row],[Bobina]]<>0),"Disponível",IF(AND(Tabela1[[#This Row],[Data de Solcitação do Cabo]]<>0,Tabela1[[#This Row],[Data de Liberação dos Cabos]]=""),"Pend. Resp.",IF(AND(Tabela1[[#This Row],[Data de Solcitação do Cabo]]<>0,Tabela1[[#This Row],[Bobina]]=""),"Pend. Compra","Não Solic."))) -> Disponível | AC53: PR-LC-0007 | AD53: =IF(Tabela1[[#This Row],[Qtde. Lançada]]>Tabela1[[#This Row],[Comprimento Total]],Tabela1[[#This Row],[Qtde. Lançada]],Tabela1[[#This Row],[Comprimento Total]]) -> 210 | AE53: - | AF53: 1MVxGB-967A | AG53: =SUMIF('Lançamento de Cabos'!AE:AK,Tabela1[[#This Row],[Tag do Cabo]],'Lançamento de Cabos'!AG:AG) -> 0 | AH53: =IFERROR(VLOOKUP(Tabela1[[#This Row],[Tag do Cabo]],'Lançamento de Cabos'!AE:AK,7,0),0) -> 0 | AI53: BK-SP54-0900B-DI-74-00452 | AJ53: 4 | AK53: 932951
A54: 1MV-GBM-967B-001AQ-ANT | B54: Força | C54: 120 | D54: 0,6/1 | E54: 1x2/C#10 | F54: 10 | G54: 1 | H54: 210 | I54: 210 | J54: GB-967A/B | K54: PAINEL DE RESISTENCIA DE AQUECIMENTO | L54: MOTOR GBM-967B (AQUECIMENTO) | M54: Sim | N54: --- | O54: ="Sim" -> Sim | P54: --- | Q54: 5.5.2 | R54: =SUMIF('Lançamento de Cabos'!$B:$B,Tabela1[[#This Row],[Tag do Cabo]],'Lançamento de Cabos'!$C:$C) -> 210 | S54: =VLOOKUP(Tabela1[[#This Row],[Tag do Cabo]],'Diagramas Ligações'!A:V,14,0) -> 4 | T54: BK-SP54-0900A-LC-74-00001_00000 | U54: 5 | W54: ELE-1250 | X54: 44177 | Y54: 44218 | Z54: 22/01/2021: Liberação da Bobina | AA54: 171 | AB54: =IF(AND(Tabela1[[#This Row],[Data de Solcitação do Cabo]]<>0,Tabela1[[#This Row],[Bobina]]<>0),"Disponível",IF(AND(Tabela1[[#This Row],[Data de Solcitação do Cabo]]<>0,Tabela1[[#This Row],[Data de Liberação dos Cabos]]=""),"Pend. Resp.",IF(AND(Tabela1[[#This Row],[Data de Solcitação do Cabo]]<>0,Tabela1[[#This Row],[Bobina]]=""),"Pend. Compra","Não Solic."))) -> Disponível | AC54: PR-LC-0007 | AD54: =IF(Tabela1[[#This Row],[Qtde. Lançada]]>Tabela1[[#This Row],[Comprimento Total]],Tabela1[[#This Row],[Qtde. Lançada]],Tabela1[[#This Row],[Comprimento Total]]) -> 210 | AE54: - | AF54: 1MVxGB-967B | AG54: =SUMIF('Lançamento de Cabos'!AE:AK,Tabela1[[#This Row],[Tag do Cabo]],'Lançamento de Cabos'!AG:AG) -> 0 | AH54: =IFERROR(VLOOKUP(Tabela1[[#This Row],[Tag do Cabo]],'Lançamento de Cabos'!AE:AK,7,0),0) -> 0 | AI54: BK-SP54-0900B-DI-74-00452 | AJ54: 1 | AK54: 932805
A55: 1MV-GBM-967B-001F | B55: Força | C55: 2400 | D55: 3,6/6 | E55: 3x1x1/C#120 | F55: 120 | G55: 3 | H55: 210 | I55: 630 | J55: GB-967A/B | K55: PAINEL 1MV | L55: MOTOR GBM-967B | M55: Sim | N55: --- | O55: Sim | P55: Sim | Q55: 5.2.13 | R55: =SUMIF('Lançamento de Cabos'!$B:$B,Tabela1[[#This Row],[Tag do Cabo]],'Lançamento de Cabos'!$C:$C) -> 630 | S55: =VLOOKUP(Tabela1[[#This Row],[Tag do Cabo]],'Diagramas Ligações'!A:V,14,0) -> 6 | T55: BK-SP54-0900A-LC-74-00001_00000 | U55: 5 | W55: ELE-1250 | X55: 44177 | Y55: 44218 | Z55: 22/01/2021: Liberação da Bobina, Nota 4: Estas bobinas foram pago para a Montcalm em 15-12-20. Verificar - bobina devem estar em posse da Montcam ou a mesma não retirou do almoxarifado. | AA55: 31 | AB55: =IF(AND(Tabela1[[#This Row],[Data de Solcitação do Cabo]]<>0,Tabela1[[#This Row],[Bobina]]<>0),"Disponível",IF(AND(Tabela1[[#This Row],[Data de Solcitação do Cabo]]<>0,Tabela1[[#This Row],[Data de Liberação dos Cabos]]=""),"Pend. Resp.",IF(AND(Tabela1[[#This Row],[Data de Solcitação do Cabo]]<>0,Tabela1[[#This Row],[Bobina]]=""),"Pend. Compra","Não Solic."))) -> Disponível | AC55: PR-LC-0007 | AD55: =IF(Tabela1[[#This Row],[Qtde. Lançada]]>Tabela1[[#This Row],[Comprimento Total]],Tabela1[[#This Row],[Qtde. Lançada]],Tabela1[[#This Row],[Comprimento Total]]) -> 630 | AE55: - | AF55: 1MVxGB-967B | AG55: =SUMIF('Lançamento de Cabos'!AE:AK,Tabela1[[#This Row],[Tag do Cabo]],'Lançamento de Cabos'!AG:AG) -> 0 | AH55: =IFERROR(VLOOKUP(Tabela1[[#This Row],[Tag do Cabo]],'Lançamento de Cabos'!AE:AK,7,0),0) -> 0 | AI55: BK-SP54-0900B-DI-74-00452 | AJ55: 1 | AK55: 933025
A56: 1MV-GBM-967B-001SA | B56: Controle | C56: 4-20mA | D56: 0.3 | E56: 1x8T#1,0 | F56: 1 | G56: 1 | H56: 210 | I56: 210 | J56: GB-967A/B | K56: PAINEL 1MV | L56: MOTOR GBM-967B (RTD) | M56: Sim | N56: Sim | O56: --- | P56: --- | Q56: 5.7.1 | R56: =SUMIF('Lançamento de Cabos'!$B:$B,Tabela1[[#This Row],[Tag do Cabo]],'Lançamento de Cabos'!$C:$C) -> 210 | S56: =VLOOKUP(Tabela1[[#This Row],[Tag do Cabo]],'Diagramas Ligações'!A:V,14,0) -> 48 | T56: BK-SP54-0900A-LC-74-00001_00000 | U56: 5 | V56: Controle 1/18 | W56: ELE-1250 | X56: 44177 | Y56: 44218 | Z56: 22/01/2021: Liberação da Bobina, Nota 2: A bobina está com 700m de cabos, para uma necessidade de 780 metros. A Montcalm deve verificar no campo se os 700metros é suficiente (medir rota). | AA56: 130 | AB56: =IF(AND(Tabela1[[#This Row],[Data de Solcitação do Cabo]]<>0,Tabela1[[#This Row],[Bobina]]<>0),"Disponível",IF(AND(Tabela1[[#This Row],[Data de Solcitação do Cabo]]<>0,Tabela1[[#This Row],[Data de Liberação dos Cabos]]=""),"Pend. Resp.",IF(AND(Tabela1[[#This Row],[Data de Solcitação do Cabo]]<>0,Tabela1[[#This Row],[Bobina]]=""),"Pend. Compra","Não Solic."))) -> Disponível | AC56: PR-LC-0007 | AD56: =IF(Tabela1[[#This Row],[Qtde. Lançada]]>Tabela1[[#This Row],[Comprimento Total]],Tabela1[[#This Row],[Qtde. Lançada]],Tabela1[[#This Row],[Comprimento Total]]) -> 210 | AE56: - | AF56: 1MVxGB-967B | AG56: =SUMIF('Lançamento de Cabos'!AE:AK,Tabela1[[#This Row],[Tag do Cabo]],'Lançamento de Cabos'!AG:AG) -> 0 | AH56: =IFERROR(VLOOKUP(Tabela1[[#This Row],[Tag do Cabo]],'Lançamento de Cabos'!AE:AK,7,0),0) -> 0 | AI56: BK-SP54-0900B-DI-74-00452 | AJ56: 1 | AK56: 1414059
A57: 1MV-GBM-967B-002C | B57: Controle | C57: 125 | D57: 0,6/1 | E57: 1x9/C#2,5 | F57: 2.5 | G57: 1 | H57: 210 | I57: 210 | J57: GB-967A/B | K57: 1MV-GAINE IV | L57: MOTOR GBM-967B (BOTOEIRA) | M57: Sim | N57: ="Sim" -> Sim | O57: --- | P57: --- | Q57: 5.8.1 | R57: =SUMIF('Lançamento de Cabos'!$B:$B,Tabela1[[#This Row],[Tag do Cabo]],'Lançamento de Cabos'!$C:$C) -> 210 | S57: =VLOOKUP(Tabela1[[#This Row],[Tag do Cabo]],'Diagramas Ligações'!A:V,14,0) -> 8 | T57: BK-SP54-0900A-LC-74-00001_00000 | U57: 5 | V57: Controle 2/18 | W57: ELE-1250 | X57: 44177 | Y57: 44218 | Z57: 22/01/2021: Liberação da Bobina, Nota 3: Esta bobina foi paga para a Montcalm em 23-11-20, já para atender estes circuitos. Verificar - bobina deve estar em posse da Montcam ou a mesma não retirou do almoxarifado. | AA57: 71 | AB57: =IF(AND(Tabela1[[#This Row],[Data de Solcitação do Cabo]]<>0,Tabela1[[#This Row],[Bobina]]<>0),"Disponível",IF(AND(Tabela1[[#This Row],[Data de Solcitação do Cabo]]<>0,Tabela1[[#This Row],[Data de Liberação dos Cabos]]=""),"Pend. Resp.",IF(AND(Tabela1[[#This Row],[Data de Solcitação do Cabo]]<>0,Tabela1[[#This Row],[Bobina]]=""),"Pend. Compra","Não Solic."))) -> Disponível | AC57: PR-LC-0007 | AD57: =IF(Tabela1[[#This Row],[Qtde. Lançada]]>Tabela1[[#This Row],[Comprimento Total]],Tabela1[[#This Row],[Qtde. Lançada]],Tabela1[[#This Row],[Comprimento Total]]) -> 210 | AE57: - | AF57: 1MVxGB-967B | AG57: =SUMIF('Lançamento de Cabos'!AE:AK,Tabela1[[#This Row],[Tag do Cabo]],'Lançamento de Cabos'!AG:AG) -> 0 | AH57: =IFERROR(VLOOKUP(Tabela1[[#This Row],[Tag do Cabo]],'Lançamento de Cabos'!AE:AK,7,0),0) -> 0 | AI57: BK-SP54-0900B-DI-74-00452 | AJ57: 1 | AK57: 932951
A58: CDC-02290 | B58: FO | C58: - | D58: - | E58: CORDÃO ÓPTICO | F58: - | G58: 1 | H58: 2.5 | I58: 2.5 | J58: FIBRA | K58: DIO-120-104 (30LV) | L58: SWT-120-105 (30LV) | M58: --- | N58: --- | O58: --- | P58: --- | Q58: 4.3.1 | R58: =SUMIF('Lançamento de Cabos'!$B:$B,Tabela1[[#This Row],[Tag do Cabo]],'Lançamento de Cabos'!$C:$C) -> 2.5 | S58: =VLOOKUP(Tabela1[[#This Row],[Tag do Cabo]],'Diagramas Ligações'!A:V,14,0) -> 2 | T58: BK-SP54-0900A-LC-90-00004_00000 | U58: 2 | V58: N/A | W58: INST-2170 | X58: 44177 | Y58: 44207 | Z58: 11/01/2021: Liberação da bobina | AA58: NE 3046024 | AB58: =IF(AND(Tabela1[[#This Row],[Data de Solcitação do Cabo]]<>0,Tabela1[[#This Row],[Bobina]]<>0),"Disponível",IF(AND(Tabela1[[#This Row],[Data de Solcitação do Cabo]]<>0,Tabela1[[#This Row],[Data de Liberação dos Cabos]]=""),"Pend. Resp.",IF(AND(Tabela1[[#This Row],[Data de Solcitação do Cabo]]<>0,Tabela1[[#This Row],[Bobina]]=""),"Pend. Compra","Não Solic."))) -> Disponível | AC58: PR-LC-0009 | AD58: =IF(Tabela1[[#This Row],[Qtde. Lançada]]>Tabela1[[#This Row],[Comprimento Total]],Tabela1[[#This Row],[Qtde. Lançada]],Tabela1[[#This Row],[Comprimento Total]]) -> 2.5 | AE58: - | AF58: 30LV | AG58: =SUMIF('Lançamento de Cabos'!AE:AK,Tabela1[[#This Row],[Tag do Cabo]],'Lançamento de Cabos'!AG:AG) -> 0 | AH58: =IFERROR(VLOOKUP(Tabela1[[#This Row],[Tag do Cabo]],'Lançamento de Cabos'!AE:AK,7,0),0) -> 0 | AI58: Não Localizado | AK58: 3046024
A59: CDC-02331 | B59: FO | C59: - | D59: - | E59: CORDÃO ÓPTICO | F59: - | G59: 1 | H59: 5 | I59: 5 | J59: FIBRA | K59: PI-1205 (ACESSO REMOTO) | L59: SWT-120-105 (30LV) | M59: --- | N59: --- | O59: --- | P59: --- | Q59: 4.3.1 | R59: =SUMIF('Lançamento de Cabos'!$B:$B,Tabela1[[#This Row],[Tag do Cabo]],'Lançamento de Cabos'!$C:$C) -> 5 | S59: =VLOOKUP(Tabela1[[#This Row],[Tag do Cabo]],'Diagramas Ligações'!A:V,14,0) -> 2 | T59: BK-SP54-0900A-LC-90-00004_00000 | U59: 2 | V59: N/A | W59: INST-2170 | X59: 44120 | Z59: 28/10/2020: Respondido que havia 1 cordão óptico de 5m disponível, verificar se são necessários dois cordões ópticos. | AA59: NE 3018894 | AB59: =IF(AND(Tabela1[[#This Row],[Data de Solcitação do Cabo]]<>0,Tabela1[[#This Row],[Bobina]]<>0),"Disponível",IF(AND(Tabela1[[#This Row],[Data de Solcitação do Cabo]]<>0,Tabela1[[#This Row],[Data de Liberação dos Cabos]]=""),"Pend. Resp.",IF(AND(Tabela1[[#This Row],[Data de Solcitação do Cabo]]<>0,Tabela1[[#This Row],[Bobina]]=""),"Pend. Compra","Não Solic."))) -> Disponível | AC59: PR-LC-0009 | AD59: =IF(Tabela1[[#This Row],[Qtde. Lançada]]>Tabela1[[#This Row],[Comprimento Total]],Tabela1[[#This Row],[Qtde. Lançada]],Tabela1[[#This Row],[Comprimento Total]]) -> 5 | AE59: - | AF59: 30LV | AG59: =SUMIF('Lançamento de Cabos'!AE:AK,Tabela1[[#This Row],[Tag do Cabo]],'Lançamento de Cabos'!AG:AG) -> 0 | AH59: =IFERROR(VLOOKUP(Tabela1[[#This Row],[Tag do Cabo]],'Lançamento de Cabos'!AE:AK,7,0),0) -> 0 | AI59: BK-SP54-00200-DP-90-00023 | AJ59: 1 | AK59: 3018894
A60: CDC-12021 | B60: Rede | C60: - | D60: - | E60: CABO ETHERNET | F60: - | G60: 1 | H60: 10 | I60: 10 | J60: REDE | K60: SWT-120-105 (30LV) | L60: PC TRISTATION P1 | M60: --- | N60: --- | O60: --- | P60: --- | Q60: 4.4.1 | R60: =SUMIF('Lançamento de Cabos'!$B:$B,Tabela1[[#This Row],[Tag do Cabo]],'Lançamento de Cabos'!$C:$C) -> 10 | S60: =VLOOKUP(Tabela1[[#This Row],[Tag do Cabo]],'Diagramas Ligações'!A:V,14,0) -> 2 | T60: BK-SP54-0900A-LC-90-00004_00000 | U60: 2 | V60: N/A | W60: INST-2170 | X60: 44120 | Y60: 44133 | Z60: 28/10/2020: Resposta da Solicitação | AA60: 191 | AB60: =IF(AND(Tabela1[[#This Row],[Data de Solcitação do Cabo]]<>0,Tabela1[[#This Row],[Bobina]]<>0),"Disponível",IF(AND(Tabela1[[#This Row],[Data de Solcitação do Cabo]]<>0,Tabela1[[#This Row],[Data de Liberação dos Cabos]]=""),"Pend. Resp.",IF(AND(Tabela1[[#This Row],[Data de Solcitação do Cabo]]<>0,Tabela1[[#This Row],[Bobina]]=""),"Pend. Compra","Não Solic."))) -> Disponível | AC60: PR-LC-0009 | AD60: =IF(Tabela1[[#This Row],[Qtde. Lançada]]>Tabela1[[#This Row],[Comprimento Total]],Tabela1[[#This Row],[Qtde. Lançada]],Tabela1[[#This Row],[Comprimento Total]]) -> 10 | AE60: - | AF60: 30LV | AG60: =SUMIF('Lançamento de Cabos'!AE:AK,Tabela1[[#This Row],[Tag do Cabo]],'Lançamento de Cabos'!AG:AG) -> 0 | AH60: =IFERROR(VLOOKUP(Tabela1[[#This Row],[Tag do Cabo]],'Lançamento de Cabos'!AE:AK,7,0),0) -> 0 | AI60: BK-SP54-00200-DP-90-00023 | AJ60: 1 | AK60: 3186329
A61: CDC-12022 | B61: Rede | C61: - | D61: - | E61: CABO ETHERNET | F61: - | G61: 1 | H61: 10 | I61: 10 | J61: REDE | K61: SWT-120-105 (30LV) | L61: NET 2 SWITCH | M61: --- | N61: --- | O61: --- | P61: --- | Q61: 4.4.1 | R61: =SUMIF('Lançamento de Cabos'!$B:$B,Tabela1[[#This Row],[Tag do Cabo]],'Lançamento de Cabos'!$C:$C) -> 10 | S61: =VLOOKUP(Tabela1[[#This Row],[Tag do Cabo]],'Diagramas Ligações'!A:V,14,0) -> 2 | T61: BK-SP54-0900A-LC-90-00004_00000 | U61: 2 | V61: N/A | W61: INST-2170 | X61: 44120 | Y61: 44133 | Z61: 28/10/2020: Resposta da Solicitação | AA61: 191 | AB61: =IF(AND(Tabela1[[#This Row],[Data de Solcitação do Cabo]]<>0,Tabela1[[#This Row],[Bobina]]<>0),"Disponível",IF(AND(Tabela1[[#This Row],[Data de Solcitação do Cabo]]<>0,Tabela1[[#This Row],[Data de Liberação dos Cabos]]=""),"Pend. Resp.",IF(AND(Tabela1[[#This Row],[Data de Solcitação do Cabo]]<>0,Tabela1[[#This Row],[Bobina]]=""),"Pend. Compra","Não Solic."))) -> Disponível | AC61: PR-LC-0009 | AD61: =IF(Tabela1[[#This Row],[Qtde. Lançada]]>Tabela1[[#This Row],[Comprimento Total]],Tabela1[[#This Row],[Qtde. Lançada]],Tabela1[[#This Row],[Comprimento Total]]) -> 10 | AE61: - | AF61: 30LV | AG61: =SUMIF('Lançamento de Cabos'!AE:AK,Tabela1[[#This Row],[Tag do Cabo]],'Lançamento de Cabos'!AG:AG) -> 0 | AH61: =IFERROR(VLOOKUP(Tabela1[[#This Row],[Tag do Cabo]],'Lançamento de Cabos'!AE:AK,7,0),0) -> 0 | AI61: BK-SP54-00200-DP-90-00023 | AJ61: 1 | AK61: 3186329
A62: CDC-12023 | B62: Rede | C62: - | D62: - | E62: CABO ETHERNET | F62: - | G62: 1 | H62: 17 | I62: 17 | J62: REDE | K62: SWT-120-105 (30LV) | L62: NET 1 GB-1201 | M62: --- | N62: --- | O62: --- | P62: --- | Q62: 4.4.1 | R62: =SUMIF('Lançamento de Cabos'!$B:$B,Tabela1[[#This Row],[Tag do Cabo]],'Lançamento de Cabos'!$C:$C) -> 17 | S62: =VLOOKUP(Tabela1[[#This Row],[Tag do Cabo]],'Diagramas Ligações'!A:V,14,0) -> 2 | T62: BK-SP54-0900A-LC-90-00004_00000 | U62: 2 | V62: N/A | W62: INST-2170 | X62: 44120 | Y62: 44133 | Z62: 28/10/2020: Resposta da Solicitação | AA62: 191 | AB62: =IF(AND(Tabela1[[#This Row],[Data de Solcitação do Cabo]]<>0,Tabela1[[#This Row],[Bobina]]<>0),"Disponível",IF(AND(Tabela1[[#This Row],[Data de Solcitação do Cabo]]<>0,Tabela1[[#This Row],[Data de Liberação dos Cabos]]=""),"Pend. Resp.",IF(AND(Tabela1[[#This Row],[Data de Solcitação do Cabo]]<>0,Tabela1[[#This Row],[Bobina]]=""),"Pend. Compra","Não Solic."))) -> Disponível | AC62: PR-LC-0001 | AD62: =IF(Tabela1[[#This Row],[Qtde. Lançada]]>Tabela1[[#This Row],[Comprimento Total]],Tabela1[[#This Row],[Qtde. Lançada]],Tabela1[[#This Row],[Comprimento Total]]) -> 17 | AE62: - | AF62: 30LV | AG62: =SUMIF('Lançamento de Cabos'!AE:AK,Tabela1[[#This Row],[Tag do Cabo]],'Lançamento de Cabos'!AG:AG) -> 0 | AH62: =IFERROR(VLOOKUP(Tabela1[[#This Row],[Tag do Cabo]],'Lançamento de Cabos'!AE:AK,7,0),0) -> 0 | AI62: BK-SP54-00200-DP-90-00023 | AJ62: 1 | AK62: 3186329
A63: CDC-12024 | B63: Rede | C63: - | D63: - | E63: CABO ETHERNET | F63: - | G63: 1 | H63: 10 | I63: 10 | J63: REDE | K63: SWT-120-105 (30LV) | L63: NET 1 GB-1203 | M63: --- | N63: --- | O63: --- | P63: --- | Q63: 4.4.1 | R63: =SUMIF('Lançamento de Cabos'!$B:$B,Tabela1[[#This Row],[Tag do Cabo]],'Lançamento de Cabos'!$C:$C) -> 10 | S63: =VLOOKUP(Tabela1[[#This Row],[Tag do Cabo]],'Diagramas Ligações'!A:V,14,0) -> 2 | T63: BK-SP54-0900A-LC-90-00004_00000 | U63: 2 | V63: N/A | W63: INST-2170 | X63: 44120 | Y63: 44133 | Z63: 28/10/2020: Resposta da Solicitação | AA63: 191 | AB63: =IF(AND(Tabela1[[#This Row],[Data de Solcitação do Cabo]]<>0,Tabela1[[#This Row],[Bobina]]<>0),"Disponível",IF(AND(Tabela1[[#This Row],[Data de Solcitação do Cabo]]<>0,Tabela1[[#This Row],[Data de Liberação dos Cabos]]=""),"Pend. Resp.",IF(AND(Tabela1[[#This Row],[Data de Solcitação do Cabo]]<>0,Tabela1[[#This Row],[Bobina]]=""),"Pend. Compra","Não Solic."))) -> Disponível | AC63: PR-LC-0001 | AD63: =IF(Tabela1[[#This Row],[Qtde. Lançada]]>Tabela1[[#This Row],[Comprimento Total]],Tabela1[[#This Row],[Qtde. Lançada]],Tabela1[[#This Row],[Comprimento Total]]) -> 10 | AE63: - | AF63: 30LV | AG63: =SUMIF('Lançamento de Cabos'!AE:AK,Tabela1[[#This Row],[Tag do Cabo]],'Lançamento de Cabos'!AG:AG) -> 0 | AH63: =IFERROR(VLOOKUP(Tabela1[[#This Row],[Tag do Cabo]],'Lançamento de Cabos'!AE:AK,7,0),0) -> 0 | AI63: BK-SP54-00200-DP-90-00023 | AJ63: 1 | AK63: 3186329
A64: CDC-12025 | B64: Rede | C64: - | D64: - | E64: CABO ETHERNET | F64: - | G64: 1 | H64: 17 | I64: 17 | J64: REDE | K64: SWT-120-105 (30LV) | L64: NET 1 GB-1204 | M64: --- | N64: --- | O64: --- | P64: --- | Q64: 4.4.1 | R64: =SUMIF('Lançamento de Cabos'!$B:$B,Tabela1[[#This Row],[Tag do Cabo]],'Lançamento de Cabos'!$C:$C) -> 17 | S64: =VLOOKUP(Tabela1[[#This Row],[Tag do Cabo]],'Diagramas Ligações'!A:V,14,0) -> 2 | T64: BK-SP54-0900A-LC-90-00004_00000 | U64: 2 | V64: N/A | W64: INST-2170 | X64: 44120 | Y64: 44133 | Z64: 28/10/2020: Resposta da Solicitação | AA64: 192 | AB64: =IF(AND(Tabela1[[#This Row],[Data de Solcitação do Cabo]]<>0,Tabela1[[#This Row],[Bobina]]<>0),"Disponível",IF(AND(Tabela1[[#This Row],[Data de Solcitação do Cabo]]<>0,Tabela1[[#This Row],[Data de Liberação dos Cabos]]=""),"Pend. Resp.",IF(AND(Tabela1[[#This Row],[Data de Solcitação do Cabo]]<>0,Tabela1[[#This Row],[Bobina]]=""),"Pend. Compra","Não Solic."))) -> Disponível | AC64: PR-LC-0001 | AD64: =IF(Tabela1[[#This Row],[Qtde. Lançada]]>Tabela1[[#This Row],[Comprimento Total]],Tabela1[[#This Row],[Qtde. Lançada]],Tabela1[[#This Row],[Comprimento Total]]) -> 17 | AE64: - | AF64: 30LV | AG64: =SUMIF('Lançamento de Cabos'!AE:AK,Tabela1[[#This Row],[Tag do Cabo]],'Lançamento de Cabos'!AG:AG) -> 0 | AH64: =IFERROR(VLOOKUP(Tabela1[[#This Row],[Tag do Cabo]],'Lançamento de Cabos'!AE:AK,7,0),0) -> 0 | AI64: BK-SP54-00200-DP-90-00023 | AJ64: 1 | AK64: 3186329
A65: CDC-12026 | B65: Rede | C65: - | D65: - | E65: CABO ETHERNET | F65: - | G65: 1 | H65: 10 | I65: 10 | J65: REDE | K65: SWT-120-105 (30LV) | L65: PC TRILOGGER P1 | M65: --- | N65: --- | O65: --- | P65: --- | Q65: 4.4.1 | R65: =SUMIF('Lançamento de Cabos'!$B:$B,Tabela1[[#This Row],[Tag do Cabo]],'Lançamento de Cabos'!$C:$C) -> 10 | S65: =VLOOKUP(Tabela1[[#This Row],[Tag do Cabo]],'Diagramas Ligações'!A:V,14,0) -> 2 | T65: BK-SP54-0900A-LC-90-00004_00000 | U65: 2 | V65: N/A | W65: INST-2170 | X65: 44120 | Y65: 44133 | Z65: 28/10/2020: Resposta da Solicitação | AA65: 192 | AB65: =IF(AND(Tabela1[[#This Row],[Data de Solcitação do Cabo]]<>0,Tabela1[[#This Row],[Bobina]]<>0),"Disponível",IF(AND(Tabela1[[#This Row],[Data de Solcitação do Cabo]]<>0,Tabela1[[#This Row],[Data de Liberação dos Cabos]]=""),"Pend. Resp.",IF(AND(Tabela1[[#This Row],[Data de Solcitação do Cabo]]<>0,Tabela1[[#This Row],[Bobina]]=""),"Pend. Compra","Não Solic."))) -> Disponível | AC65: PR-LC-0009 | AD65: =IF(Tabela1[[#This Row],[Qtde. Lançada]]>Tabela1[[#This Row],[Comprimento Total]],Tabela1[[#This Row],[Qtde. Lançada]],Tabela1[[#This Row],[Comprimento Total]]) -> 10 | AE65: - | AF65: 30LV | AG65: =SUMIF('Lançamento de Cabos'!AE:AK,Tabela1[[#This Row],[Tag do Cabo]],'Lançamento de Cabos'!AG:AG) -> 0 | AH65: =IFERROR(VLOOKUP(Tabela1[[#This Row],[Tag do Cabo]],'Lançamento de Cabos'!AE:AK,7,0),0) -> 0 | AI65: BK-SP54-00200-DP-90-00023 | AJ65: 1 | AK65: 3186329
A66: CDC-12027 | B66: Rede | C66: - | D66: - | E66: CABO ETHERNET | F66: - | G66: 1 | H66: 10 | I66: 10 | J66: REDE | K66: SWT-120-105 (30LV) | L66: PC TRISTATION P2 | M66: --- | N66: --- | O66: --- | P66: --- | Q66: 4.4.1 | R66: =SUMIF('Lançamento de Cabos'!$B:$B,Tabela1[[#This Row],[Tag do Cabo]],'Lançamento de Cabos'!$C:$C) -> 10 | S66: =VLOOKUP(Tabela1[[#This Row],[Tag do Cabo]],'Diagramas Ligações'!A:V,14,0) -> 2 | T66: BK-SP54-0900A-LC-90-00004_00000 | U66: 2 | V66: N/A | W66: INST-2170 | X66: 44120 | Y66: 44133 | Z66: 28/10/2020: Resposta da Solicitação | AA66: 192 | AB66: =IF(AND(Tabela1[[#This Row],[Data de Solcitação do Cabo]]<>0,Tabela1[[#This Row],[Bobina]]<>0),"Disponível",IF(AND(Tabela1[[#This Row],[Data de Solcitação do Cabo]]<>0,Tabela1[[#This Row],[Data de Liberação dos Cabos]]=""),"Pend. Resp.",IF(AND(Tabela1[[#This Row],[Data de Solcitação do Cabo]]<>0,Tabela1[[#This Row],[Bobina]]=""),"Pend. Compra","Não Solic."))) -> Disponível | AC66: PR-LC-0009 | AD66: =IF(Tabela1[[#This Row],[Qtde. Lançada]]>Tabela1[[#This Row],[Comprimento Total]],Tabela1[[#This Row],[Qtde. Lançada]],Tabela1[[#This Row],[Comprimento Total]]) -> 10 | AE66: - | AF66: 30LV | AG66: =SUMIF('Lançamento de Cabos'!AE:AK,Tabela1[[#This Row],[Tag do Cabo]],'Lançamento de Cabos'!AG:AG) -> 0 | AH66: =IFERROR(VLOOKUP(Tabela1[[#This Row],[Tag do Cabo]],'Lançamento de Cabos'!AE:AK,7,0),0) -> 0 | AI66: BK-SP54-00200-DP-90-00023 | AJ66: 1 | AK66: 3186329
A67: CDC-12028 | B67: Rede | C67: - | D67: - | E67: CABO ETHERNET | F67: - | G67: 1 | H67: 10 | I67: 10 | J67: REDE | K67: SWT-120-105 (30LV) | L67: PC TRILOGGER P2 | M67: --- | N67: --- | O67: --- | P67: --- | Q67: 4.4.1 | R67: =SUMIF('Lançamento de Cabos'!$B:$B,Tabela1[[#This Row],[Tag do Cabo]],'Lançamento de Cabos'!$C:$C) -> 10 | S67: =VLOOKUP(Tabela1[[#This Row],[Tag do Cabo]],'Diagramas Ligações'!A:V,14,0) -> 2 | T67: BK-SP54-0900A-LC-90-00004_00000 | U67: 2 | V67: N/A | W67: INST-2170 | X67: 44120 | Y67: 44133 | Z67: 28/10/2020: Resposta da Solicitação | AA67: 192 | AB67: =IF(AND(Tabela1[[#This Row],[Data de Solcitação do Cabo]]<>0,Tabela1[[#This Row],[Bobina]]<>0),"Disponível",IF(AND(Tabela1[[#This Row],[Data de Solcitação do Cabo]]<>0,Tabela1[[#This Row],[Data de Liberação dos Cabos]]=""),"Pend. Resp.",IF(AND(Tabela1[[#This Row],[Data de Solcitação do Cabo]]<>0,Tabela1[[#This Row],[Bobina]]=""),"Pend. Compra","Não Solic."))) -> Disponível | AC67: PR-LC-0009 | AD67: =IF(Tabela1[[#This Row],[Qtde. Lançada]]>Tabela1[[#This Row],[Comprimento Total]],Tabela1[[#This Row],[Qtde. Lançada]],Tabela1[[#This Row],[Comprimento Total]]) -> 10 | AE67: - | AF67: 30LV | AG67: =SUMIF('Lançamento de Cabos'!AE:AK,Tabela1[[#This Row],[Tag do Cabo]],'Lançamento de Cabos'!AG:AG) -> 0 | AH67: =IFERROR(VLOOKUP(Tabela1[[#This Row],[Tag do Cabo]],'Lançamento de Cabos'!AE:AK,7,0),0) -> 0 | AI67: BK-SP54-00200-DP-90-00023 | AJ67: 1 | AK67: 3186329
A68: PI-1201-RCK120-103-001F | B68: Força | C68: 110 | D68: 0,6/1 | E68: 1x1x3/C#4 | F68: 4 | G68: 1 | H68: 30 | I68: 30 | J68: 30LV | K68: PI-1201 | L68: ALIMENTAÇÃO RCK-120-103 | M68: Sim | N68: ="Sim" -> Sim | O68: --- | P68: --- | Q68: 5.10.2 | R68: =SUMIF('Lançamento de Cabos'!$B:$B,Tabela1[[#This Row],[Tag do Cabo]],'Lançamento de Cabos'!$C:$C) -> 30 | S68: =VLOOKUP(Tabela1[[#This Row],[Tag do Cabo]],'Diagramas Ligações'!A:V,14,0) -> 6 | T68: BK-SP54-0900A-LC-74-00001_00000 | U68: 5 | W68: ELE-3090 | X68: 44177 | Y68: 44218 | Z68: 22/01/2021: Liberação da Bobina | AA68: NE 3206802 | AB68: =IF(AND(Tabela1[[#This Row],[Data de Solcitação do Cabo]]<>0,Tabela1[[#This Row],[Bobina]]<>0),"Disponível",IF(AND(Tabela1[[#This Row],[Data de Solcitação do Cabo]]<>0,Tabela1[[#This Row],[Data de Liberação dos Cabos]]=""),"Pend. Resp.",IF(AND(Tabela1[[#This Row],[Data de Solcitação do Cabo]]<>0,Tabela1[[#This Row],[Bobina]]=""),"Pend. Compra","Não Solic."))) -> Disponível | AC68: PR-LC-0009 | AD68: =IF(Tabela1[[#This Row],[Qtde. Lançada]]>Tabela1[[#This Row],[Comprimento Total]],Tabela1[[#This Row],[Qtde. Lançada]],Tabela1[[#This Row],[Comprimento Total]]) -> 30 | AE68: - | AF68: 30LV | AG68: =SUMIF('Lançamento de Cabos'!AE:AK,Tabela1[[#This Row],[Tag do Cabo]],'Lançamento de Cabos'!AG:AG) -> 6 | AH68: =IFERROR(VLOOKUP(Tabela1[[#This Row],[Tag do Cabo]],'Lançamento de Cabos'!AE:AK,7,0),0) -> 1 | AI68: Não Localizado | AK68: 320680
A69: PI-1203-RCK120-103-001F | B69: Força | C69: 110 | D69: 0,6/1 | E69: 1x1x3/C#4 | F69: 4 | G69: 1 | H69: 30 | I69: 30 | J69: 30LV | K69: PI-1203 | L69: ALIMENTAÇÃO RCK-120-103 | M69: Sim | N69: ="Sim" -> Sim | O69: --- | P69: --- | Q69: 5.10.2 | R69: =SUMIF('Lançamento de Cabos'!$B:$B,Tabela1[[#This Row],[Tag do Cabo]],'Lançamento de Cabos'!$C:$C) -> 30 | S69: =VLOOKUP(Tabela1[[#This Row],[Tag do Cabo]],'Diagramas Ligações'!A:V,14,0) -> 6 | T69: BK-SP54-0900A-LC-74-00001_00000 | U69: 5 | W69: ELE-3090 | X69: 44177 | Y69: 44218 | Z69: 22/01/2021: Liberação da Bobina | AA69: NE 3206802 | AB69: =IF(AND(Tabela1[[#This Row],[Data de Solcitação do Cabo]]<>0,Tabela1[[#This Row],[Bobina]]<>0),"Disponível",IF(AND(Tabela1[[#This Row],[Data de Solcitação do Cabo]]<>0,Tabela1[[#This Row],[Data de Liberação dos Cabos]]=""),"Pend. Resp.",IF(AND(Tabela1[[#This Row],[Data de Solcitação do Cabo]]<>0,Tabela1[[#This Row],[Bobina]]=""),"Pend. Compra","Não Solic."))) -> Disponível | AC69: PR-LC-0009 | AD69: =IF(Tabela1[[#This Row],[Qtde. Lançada]]>Tabela1[[#This Row],[Comprimento Total]],Tabela1[[#This Row],[Qtde. Lançada]],Tabela1[[#This Row],[Comprimento Total]]) -> 30 | AE69: - | AF69: 30LV | AG69: =SUMIF('Lançamento de Cabos'!AE:AK,Tabela1[[#This Row],[Tag do Cabo]],'Lançamento de Cabos'!AG:AG) -> 6 | AH69: =IFERROR(VLOOKUP(Tabela1[[#This Row],[Tag do Cabo]],'Lançamento de Cabos'!AE:AK,7,0),0) -> 1 | AI69: Não Localizado | AK69: 320680
A70: U-12574 | B70: Controle | C70: - | D70: - | E70: 4P#1,0mm²+SHI+SHC (N.I.S.) | F70: 1 | G70: 1 | H70: 90 | I70: 90 | J70: 30LV | K70: JBI-120-102X | L70: 30LV/UCP LI-1201A | M70: Sim | N70: ="Sim" -> Sim | O70: --- | P70: --- | Q70: 4.6.1 | R70: =SUMIF('Lançamento de Cabos'!$B:$B,Tabela1[[#This Row],[Tag do Cabo]],'Lançamento de Cabos'!$C:$C) -> 120 | S70: =VLOOKUP(Tabela1[[#This Row],[Tag do Cabo]],'Diagramas Ligações'!A:V,14,0) -> 12 | T70: BK-SP54-01200-LC-80-00004_00000 | U70: 10 | V70: Controle 1/18 | W70: INST-2170 | X70: 44120 | Y70: 44130 | Z70: 26/10/2020: Resposta para liberação 04/11/2020: Revisada planta de instrumentação, nova rota de cabos 18/11/2020: Pendente fornecimento de parafusos cabeça lentilha, para fixação das eletrocalhas. | AA70: 127 | AB70: =IF(AND(Tabela1[[#This Row],[Data de Solcitação do Cabo]]<>0,Tabela1[[#This Row],[Bobina]]<>0),"Disponível",IF(AND(Tabela1[[#This Row],[Data de Solcitação do Cabo]]<>0,Tabela1[[#This Row],[Data de Liberação dos Cabos]]=""),"Pend. Resp.",IF(AND(Tabela1[[#This Row],[Data de Solcitação do Cabo]]<>0,Tabela1[[#This Row],[Bobina]]=""),"Pend. Compra","Não Solic."))) -> Disponível | AC70: PR-LC-0001 | AD70: =IF(Tabela1[[#This Row],[Qtde. Lançada]]>Tabela1[[#This Row],[Comprimento Total]],Tabela1[[#This Row],[Qtde. Lançada]],Tabela1[[#This Row],[Comprimento Total]]) -> 120 | AE70: Digital (N.I.S.) | AF70: 30LVxGB-1201 | AG70: =SUMIF('Lançamento de Cabos'!AE:AK,Tabela1[[#This Row],[Tag do Cabo]],'Lançamento de Cabos'!AG:AG) -> 0 | AH70: =IFERROR(VLOOKUP(Tabela1[[#This Row],[Tag do Cabo]],'Lançamento de Cabos'!AE:AK,7,0),0) -> 0 | AI70: SOK0898307 | AJ70: 20 | AK70: 1423312
A71: U-12575 | B71: Controle | C71: - | D71: - | E71: 1P#1,0mm²+SHI (N.I.S.) | F71: 1 | G71: 1 | H71: 90 | I71: 90 | J71: 30LV | K71: JB LEAKAGE DETECTOR (LSH-12008X) | L71: 30LV/UCP LI-1201A | M71: Sim | N71: ="Sim" -> Sim | O71: --- | P71: --- | Q71: 4.6.1 | R71: =SUMIF('Lançamento de Cabos'!$B:$B,Tabela1[[#This Row],[Tag do Cabo]],'Lançamento de Cabos'!$C:$C) -> 120 | S71: =VLOOKUP(Tabela1[[#This Row],[Tag do Cabo]],'Diagramas Ligações'!A:V,14,0) -> 4 | T71: BK-SP54-01200-LC-80-00004_00000 | U71: 10 | V71: Controle 1/18 | W71: INST-2170 | X71: 44120 | Y71: 44130 | Z71: 26/10/2020: Resposta para liberação 04/11/2020: Revisada planta de instrumentação, nova rota de cabos 18/11/2020: Pendente fornecimento de parafusos cabeça lentilha, para fixação das eletrocalhas. | AA71: 182 | AB71: =IF(AND(Tabela1[[#This Row],[Data de Solcitação do Cabo]]<>0,Tabela1[[#This Row],[Bobina]]<>0),"Disponível",IF(AND(Tabela1[[#This Row],[Data de Solcitação do Cabo]]<>0,Tabela1[[#This Row],[Data de Liberação dos Cabos]]=""),"Pend. Resp.",IF(AND(Tabela1[[#This Row],[Data de Solcitação do Cabo]]<>0,Tabela1[[#This Row],[Bobina]]=""),"Pend. Compra","Não Solic."))) -> Disponível | AC71: PR-LC-0001 | AD71: =IF(Tabela1[[#This Row],[Qtde. Lançada]]>Tabela1[[#This Row],[Comprimento Total]],Tabela1[[#This Row],[Qtde. Lançada]],Tabela1[[#This Row],[Comprimento Total]]) -> 120 | AE71: Digital (N.I.S.) | AF71: 30LVxGB-1201 | AG71: =SUMIF('Lançamento de Cabos'!AE:AK,Tabela1[[#This Row],[Tag do Cabo]],'Lançamento de Cabos'!AG:AG) -> 0 | AH71: =IFERROR(VLOOKUP(Tabela1[[#This Row],[Tag do Cabo]],'Lançamento de Cabos'!AE:AK,7,0),0) -> 0 | AI71: SOK0898307 | AJ71: 20 | AK71: 306860
A72: U-12576 | B72: Controle | C72: - | D72: - | E72: 12P#1,0mm²+SHI+SHC (I.S.) | F72: 1 | G72: 1 | H72: 80 | I72: 80 | J72: 30LV | K72: EJB-12506X | L72: 30LV/UCP LI-1201A | M72: Sim | N72: ="Sim" -> Sim | O72: --- | P72: --- | Q72: 4.4.1 | R72: =SUMIF('Lançamento de Cabos'!$B:$B,Tabela1[[#This Row],[Tag do Cabo]],'Lançamento de Cabos'!$C:$C) -> 110 | S72: =VLOOKUP(Tabela1[[#This Row],[Tag do Cabo]],'Diagramas Ligações'!A:V,14,0) -> 28 | T72: BK-SP54-01200-LC-80-00004_00000 | U72: 10 | V72: Controle 1/18 | W72: INST-2170 | X72: 44120 | Y72: 44130 | Z72: 26/10/2020: Resposta para liberação 04/11/2020: Revisada planta de instrumentação, nova rota de cabos 18/11/2020: Pendente fornecimento de parafusos cabeça lentilha, para fixação das eletrocalhas. | AA72: 94 | AB72: =IF(AND(Tabela1[[#This Row],[Data de Solcitação do Cabo]]<>0,Tabela1[[#This Row],[Bobina]]<>0),"Disponível",IF(AND(Tabela1[[#This Row],[Data de Solcitação do Cabo]]<>0,Tabela1[[#This Row],[Data de Liberação dos Cabos]]=""),"Pend. Resp.",IF(AND(Tabela1[[#This Row],[Data de Solcitação do Cabo]]<>0,Tabela1[[#This Row],[Bobina]]=""),"Pend. Compra","Não Solic."))) -> Disponível | AC72: PR-LC-0001 | AD72: =IF(Tabela1[[#This Row],[Qtde. Lançada]]>Tabela1[[#This Row],[Comprimento Total]],Tabela1[[#This Row],[Qtde. Lançada]],Tabela1[[#This Row],[Comprimento Total]]) -> 110 | AE72: Analógico (I.S.) | AF72: 30LVxGB-1201 | AG72: =SUMIF('Lançamento de Cabos'!AE:AK,Tabela1[[#This Row],[Tag do Cabo]],'Lançamento de Cabos'!AG:AG) -> 0 | AH72: =IFERROR(VLOOKUP(Tabela1[[#This Row],[Tag do Cabo]],'Lançamento de Cabos'!AE:AK,7,0),0) -> 0 | AI72: SOK0898307 | AJ72: 13 | AK72: 3087804
A73: U-12592 | B73: Controle | C73: - | D73: - | E73: 1T#1,0mm²+SHI (I.S.) | F73: 1 | G73: 1 | H73: 90 | I73: 90 | J73: 30LV | K73: JBI-120-103X | L73: 30LV/UCP LI-1201A | M73: Sim | N73: ="Sim" -> Sim | O73: --- | P73: --- | Q73: 4.6.1 | R73: =SUMIF('Lançamento de Cabos'!$B:$B,Tabela1[[#This Row],[Tag do Cabo]],'Lançamento de Cabos'!$C:$C) -> 90 | S73: =VLOOKUP(Tabela1[[#This Row],[Tag do Cabo]],'Diagramas Ligações'!A:V,14,0) -> 6 | T73: BK-SP54-01200-LC-80-00004_00000 | U73: 10 | V73: Controle 1/18 | W73: INST-2170 | X73: 44120 | Y73: 44166 | Z73: 26/10/2020: Cabos estão para compra 15/01/2021: Liberação da Bobina | AA73: 220 | AB73: =IF(AND(Tabela1[[#This Row],[Data de Solcitação do Cabo]]<>0,Tabela1[[#This Row],[Bobina]]<>0),"Disponível",IF(AND(Tabela1[[#This Row],[Data de Solcitação do Cabo]]<>0,Tabela1[[#This Row],[Data de Liberação dos Cabos]]=""),"Pend. Resp.",IF(AND(Tabela1[[#This Row],[Data de Solcitação do Cabo]]<>0,Tabela1[[#This Row],[Bobina]]=""),"Pend. Compra","Não Solic."))) -> Disponível | AC73: PR-LC-0001 | AD73: =IF(Tabela1[[#This Row],[Qtde. Lançada]]>Tabela1[[#This Row],[Comprimento Total]],Tabela1[[#This Row],[Qtde. Lançada]],Tabela1[[#This Row],[Comprimento Total]]) -> 90 | AE73: Analógico (I.S.) | AF73: 30LVxGB-1201 | AG73: =SUMIF('Lançamento de Cabos'!AE:AK,Tabela1[[#This Row],[Tag do Cabo]],'Lançamento de Cabos'!AG:AG) -> 0 | AH73: =IFERROR(VLOOKUP(Tabela1[[#This Row],[Tag do Cabo]],'Lançamento de Cabos'!AE:AK,7,0),0) -> 0 | AI73: SOK0898307 | AJ73: 6 | AK73: 2009461
A74: U-12593 | B74: Controle | C74: - | D74: - | E74: 8P#1,0mm²+SHI+SHC (I.S.) | F74: 1 | G74: 1 | H74: 90 | I74: 90 | J74: 30LV | K74: EJB-12505X | L74: 30LV/UCP LI-1201A | M74: Sim | N74: ="Sim" -> Sim | O74: --- | P74: --- | Q74: 4.4.1 | R74: =SUMIF('Lançamento de Cabos'!$B:$B,Tabela1[[#This Row],[Tag do Cabo]],'Lançamento de Cabos'!$C:$C) -> 120 | S74: =VLOOKUP(Tabela1[[#This Row],[Tag do Cabo]],'Diagramas Ligações'!A:V,14,0) -> 24 | T74: BK-SP54-01200-LC-80-00004_00000 | U74: 10 | V74: Controle 1/18 | W74: INST-2170 | X74: 44120 | Y74: 44130 | Z74: 26/10/2020: Resposta para liberação 04/11/2020: Revisada planta de instrumentação, nova rota de cabos 18/11/2020: Pendente fornecimento de parafusos cabeça lentilha, para fixação das eletrocalhas. | AA74: 124 | AB74: =IF(AND(Tabela1[[#This Row],[Data de Solcitação do Cabo]]<>0,Tabela1[[#This Row],[Bobina]]<>0),"Disponível",IF(AND(Tabela1[[#This Row],[Data de Solcitação do Cabo]]<>0,Tabela1[[#This Row],[Data de Liberação dos Cabos]]=""),"Pend. Resp.",IF(AND(Tabela1[[#This Row],[Data de Solcitação do Cabo]]<>0,Tabela1[[#This Row],[Bobina]]=""),"Pend. Compra","Não Solic."))) -> Disponível | AC74: PR-LC-0001 | AD74: =IF(Tabela1[[#This Row],[Qtde. Lançada]]>Tabela1[[#This Row],[Comprimento Total]],Tabela1[[#This Row],[Qtde. Lançada]],Tabela1[[#This Row],[Comprimento Total]]) -> 120 | AE74: Analógico (I.S.) | AF74: 30LVxGB-1201 | AG74: =SUMIF('Lançamento de Cabos'!AE:AK,Tabela1[[#This Row],[Tag do Cabo]],'Lançamento de Cabos'!AG:AG) -> 0 | AH74: =IFERROR(VLOOKUP(Tabela1[[#This Row],[Tag do Cabo]],'Lançamento de Cabos'!AE:AK,7,0),0) -> 0 | AI74: SOK0898307 | AJ74: 12 | AK74: 923841
A75: U-12793 | B75: Controle | C75: - | D75: - | E75: 12P#1,0mm²+SHI+SHC (I.S.) | F75: 1 | G75: 1 | H75: 90 | I75: 90 | J75: 30LV | K75: JBI-120-101X | L75: 30LV/UCP LI-1201A | M75: Sim | N75: ="Sim" -> Sim | O75: --- | P75: --- | Q75: 4.4.1 | R75: =SUMIF('Lançamento de Cabos'!$B:$B,Tabela1[[#This Row],[Tag do Cabo]],'Lançamento de Cabos'!$C:$C) -> 120 | S75: =VLOOKUP(Tabela1[[#This Row],[Tag do Cabo]],'Diagramas Ligações'!A:V,14,0) -> 32 | T75: BK-SP54-01200-LC-80-00004_00000 | U75: 10 | V75: Controle 1/18 | W75: INST-2170 | X75: 44120 | Y75: 44130 | Z75: 26/10/2020: Resposta para liberação 04/11/2020: Revisada planta de instrumentação, nova rota de cabos 18/11/2020: Pendente fornecimento de parafusos cabeça lentilha, para fixação das eletrocalhas. | AA75: 94 | AB75: =IF(AND(Tabela1[[#This Row],[Data de Solcitação do Cabo]]<>0,Tabela1[[#This Row],[Bobina]]<>0),"Disponível",IF(AND(Tabela1[[#This Row],[Data de Solcitação do Cabo]]<>0,Tabela1[[#This Row],[Data de Liberação dos Cabos]]=""),"Pend. Resp.",IF(AND(Tabela1[[#This Row],[Data de Solcitação do Cabo]]<>0,Tabela1[[#This Row],[Bobina]]=""),"Pend. Compra","Não Solic."))) -> Disponível | AC75: PR-LC-0001 | AD75: =IF(Tabela1[[#This Row],[Qtde. Lançada]]>Tabela1[[#This Row],[Comprimento Total]],Tabela1[[#This Row],[Qtde. Lançada]],Tabela1[[#This Row],[Comprimento Total]]) -> 120 | AE75: Analógico (I.S.) | AF75: 30LVxGB-1201 | AG75: =SUMIF('Lançamento de Cabos'!AE:AK,Tabela1[[#This Row],[Tag do Cabo]],'Lançamento de Cabos'!AG:AG) -> 0 | AH75: =IFERROR(VLOOKUP(Tabela1[[#This Row],[Tag do Cabo]],'Lançamento de Cabos'!AE:AK,7,0),0) -> 0 | AI75: SOK0898307 | AJ75: 36 | AK75: 3087804
A76: U-12564 | B76: Controle | C76: - | D76: - | E76: 4P#1,0mm²+SHI+SHC (N.I.S.) | F76: 1 | G76: 1 | H76: 80 | I76: 80 | J76: 30LV | K76: JBI-120-107X | L76: 30LV/UCP LI-1203A | M76: Sim | N76: ="Sim" -> Sim | O76: --- | P76: --- | Q76: 4.6.1 | R76: =SUMIF('Lançamento de Cabos'!$B:$B,Tabela1[[#This Row],[Tag do Cabo]],'Lançamento de Cabos'!$C:$C) -> 110 | S76: =VLOOKUP(Tabela1[[#This Row],[Tag do Cabo]],'Diagramas Ligações'!A:V,14,0) -> 16 | T76: BK-SP54-01200-LC-80-00004_00000 | U76: 10 | V76: Controle 1/18 | W76: INST-2170 | X76: 44120 | Y76: 44130 | Z76: 26/10/2020: Resposta para liberação 04/11/2020: Revisada planta de instrumentação, nova rota de cabos 18/11/2020: Pendente fornecimento de parafusos cabeça lentilha, para fixação das eletrocalhas. | AA76: 127 | AB76: =IF(AND(Tabela1[[#This Row],[Data de Solcitação do Cabo]]<>0,Tabela1[[#This Row],[Bobina]]<>0),"Disponível",IF(AND(Tabela1[[#This Row],[Data de Solcitação do Cabo]]<>0,Tabela1[[#This Row],[Data de Liberação dos Cabos]]=""),"Pend. Resp.",IF(AND(Tabela1[[#This Row],[Data de Solcitação do Cabo]]<>0,Tabela1[[#This Row],[Bobina]]=""),"Pend. Compra","Não Solic."))) -> Disponível | AC76: PR-LC-0001 | AD76: =IF(Tabela1[[#This Row],[Qtde. Lançada]]>Tabela1[[#This Row],[Comprimento Total]],Tabela1[[#This Row],[Qtde. Lançada]],Tabela1[[#This Row],[Comprimento Total]]) -> 110 | AE76: Digital (N.I.S.) | AF76: 30LVxGB-1203 | AG76: =SUMIF('Lançamento de Cabos'!AE:AK,Tabela1[[#This Row],[Tag do Cabo]],'Lançamento de Cabos'!AG:AG) -> 0 | AH76: =IFERROR(VLOOKUP(Tabela1[[#This Row],[Tag do Cabo]],'Lançamento de Cabos'!AE:AK,7,0),0) -> 0 | AI76: SOK0898310/SOK0898307 | AJ76: 39/19 | AK76: 1423312
A77: U-12565 | B77: Controle | C77: - | D77: - | E77: 1P#1,0mm²+SHI (N.I.S.) | F77: 1 | G77: 1 | H77: 80 | I77: 80 | J77: 30LV | K77: JB LEAKAGE DETECTOR (LSH-12005X) | L77: 30LV/UCP LI-1203A | M77: Sim | N77: ="Sim" -> Sim | O77: --- | P77: --- | Q77: 4.6.1 | R77: =SUMIF('Lançamento de Cabos'!$B:$B,Tabela1[[#This Row],[Tag do Cabo]],'Lançamento de Cabos'!$C:$C) -> 110 | S77: =VLOOKUP(Tabela1[[#This Row],[Tag do Cabo]],'Diagramas Ligações'!A:V,14,0) -> 4 | T77: BK-SP54-01200-LC-80-00004_00000 | U77: 10 | V77: Controle 1/18 | W77: INST-2170 | X77: 44120 | Y77: 44130 | Z77: 26/10/2020: Resposta para liberação 04/11/2020: Revisada planta de instrumentação, nova rota de cabos 18/11/2020: Pendente fornecimento de parafusos cabeça lentilha, para fixação das eletrocalhas. | AA77: 182 | AB77: =IF(AND(Tabela1[[#This Row],[Data de Solcitação do Cabo]]<>0,Tabela1[[#This Row],[Bobina]]<>0),"Disponível",IF(AND(Tabela1[[#This Row],[Data de Solcitação do Cabo]]<>0,Tabela1[[#This Row],[Data de Liberação dos Cabos]]=""),"Pend. Resp.",IF(AND(Tabela1[[#This Row],[Data de Solcitação do Cabo]]<>0,Tabela1[[#This Row],[Bobina]]=""),"Pend. Compra","Não Solic."))) -> Disponível | AC77: PR-LC-0001 | AD77: =IF(Tabela1[[#This Row],[Qtde. Lançada]]>Tabela1[[#This Row],[Comprimento Total]],Tabela1[[#This Row],[Qtde. Lançada]],Tabela1[[#This Row],[Comprimento Total]]) -> 110 | AE77: Digital (N.I.S.) | AF77: 30LVxGB-1203 | AG77: =SUMIF('Lançamento de Cabos'!AE:AK,Tabela1[[#This Row],[Tag do Cabo]],'Lançamento de Cabos'!AG:AG) -> 0 | AH77: =IFERROR(VLOOKUP(Tabela1[[#This Row],[Tag do Cabo]],'Lançamento de Cabos'!AE:AK,7,0),0) -> 0 | AI77: SOK0898310 | AJ77: 39 | AK77: 306860
A78: U-12675 | B78: Controle | C78: - | D78: - | E78: 12P#1,5mm²+SHI+SHC (I.S.) | F78: 1.5 | G78: 1 | H78: 130 | I78: 130 | J78: 30LV | K78: 7HV/GBM-1203-INV | L78: 30LV/UCP LI-1203A | M78: Sim | N78: ="Sim" -> Sim | O78: --- | P78: --- | Q78: 4.4.1 | R78: =SUMIF('Lançamento de Cabos'!$B:$B,Tabela1[[#This Row],[Tag do Cabo]],'Lançamento de Cabos'!$C:$C) -> 136 | S78: =VLOOKUP(Tabela1[[#This Row],[Tag do Cabo]],'Diagramas Ligações'!A:V,14,0) -> 32 | T78: BK-SP54-01200-LC-80-00004_00000 | U78: 10 | V78: Controle 1/18 | W78: INST-2170 | X78: 44120 | Y78: 44130 | Z78: 26/10/2020: Resposta para liberação 04/11/2020: Revisada planta de instrumentação, nova rota de cabos 18/11/2020: Pendente fornecimento de parafusos cabeça lentilha, para fixação das eletrocalhas. | AA78: 126 | AB78: =IF(AND(Tabela1[[#This Row],[Data de Solcitação do Cabo]]<>0,Tabela1[[#This Row],[Bobina]]<>0),"Disponível",IF(AND(Tabela1[[#This Row],[Data de Solcitação do Cabo]]<>0,Tabela1[[#This Row],[Data de Liberação dos Cabos]]=""),"Pend. Resp.",IF(AND(Tabela1[[#This Row],[Data de Solcitação do Cabo]]<>0,Tabela1[[#This Row],[Bobina]]=""),"Pend. Compra","Não Solic."))) -> Disponível | AC78: PR-LC-0001 | AD78: =IF(Tabela1[[#This Row],[Qtde. Lançada]]>Tabela1[[#This Row],[Comprimento Total]],Tabela1[[#This Row],[Qtde. Lançada]],Tabela1[[#This Row],[Comprimento Total]]) -> 136 | AE78: Digital (I.S.) | AF78: 30LVxGB-1203 | AG78: =SUMIF('Lançamento de Cabos'!AE:AK,Tabela1[[#This Row],[Tag do Cabo]],'Lançamento de Cabos'!AG:AG) -> 0 | AH78: =IFERROR(VLOOKUP(Tabela1[[#This Row],[Tag do Cabo]],'Lançamento de Cabos'!AE:AK,7,0),0) -> 0 | AI78: SOK0898310 | AJ78: 42 | AK78: 922346
A79: U-12676 | B79: Controle | C79: - | D79: - | E79: 12P#1,0mm²+SHI+SHC (I.S.) | F79: 1 | G79: 1 | H79: 80 | I79: 80 | J79: 30LV | K79: EJB-12606X | L79: 30LV/UCP LI-1203A | M79: Sim | N79: ="Sim" -> Sim | O79: --- | P79: --- | Q79: 4.6.1 | R79: =SUMIF('Lançamento de Cabos'!$B:$B,Tabela1[[#This Row],[Tag do Cabo]],'Lançamento de Cabos'!$C:$C) -> 110 | S79: =VLOOKUP(Tabela1[[#This Row],[Tag do Cabo]],'Diagramas Ligações'!A:V,14,0) -> 36 | T79: BK-SP54-01200-LC-80-00004_00000 | U79: 10 | V79: Controle 1/18 | W79: INST-2170 | X79: 44120 | Y79: 44130 | Z79: 26/10/2020: Resposta para liberação 04/11/2020: Revisada planta de instrumentação, nova rota de cabos 18/11/2020: Pendente fornecimento de parafusos cabeça lentilha, para fixação das eletrocalhas. | AA79: 182 | AB79: =IF(AND(Tabela1[[#This Row],[Data de Solcitação do Cabo]]<>0,Tabela1[[#This Row],[Bobina]]<>0),"Disponível",IF(AND(Tabela1[[#This Row],[Data de Solcitação do Cabo]]<>0,Tabela1[[#This Row],[Data de Liberação dos Cabos]]=""),"Pend. Resp.",IF(AND(Tabela1[[#This Row],[Data de Solcitação do Cabo]]<>0,Tabela1[[#This Row],[Bobina]]=""),"Pend. Compra","Não Solic."))) -> Disponível | AC79: PR-LC-0001 | AD79: =IF(Tabela1[[#This Row],[Qtde. Lançada]]>Tabela1[[#This Row],[Comprimento Total]],Tabela1[[#This Row],[Qtde. Lançada]],Tabela1[[#This Row],[Comprimento Total]]) -> 110 | AE79: Analógico (I.S.) | AF79: 30LVxGB-1203 | AG79: =SUMIF('Lançamento de Cabos'!AE:AK,Tabela1[[#This Row],[Tag do Cabo]],'Lançamento de Cabos'!AG:AG) -> 0 | AH79: =IFERROR(VLOOKUP(Tabela1[[#This Row],[Tag do Cabo]],'Lançamento de Cabos'!AE:AK,7,0),0) -> 0 | AI79: SOK0898310 | AJ79: 15 | AK79: 3005082
A80: U-12678 | B80: Controle | C80: - | D80: - | E80: 8T#1,0mm²+SHI+SHC (I.S.) | F80: 1 | G80: 1 | H80: 80 | I80: 80 | J80: 30LV | K80: JBI-120-105X | L80: 30LV/UCP LI-1203A | M80: Sim | N80: ="Sim" -> Sim | O80: --- | P80: --- | Q80: 4.6.1 | R80: =SUMIF('Lançamento de Cabos'!$B:$B,Tabela1[[#This Row],[Tag do Cabo]],'Lançamento de Cabos'!$C:$C) -> 110 | S80: =VLOOKUP(Tabela1[[#This Row],[Tag do Cabo]],'Diagramas Ligações'!A:V,14,0) -> 42 | T80: BK-SP54-01200-LC-80-00004_00000 | U80: 10 | V80: Controle 1/18 | W80: INST-2170 | X80: 44120 | Y80: 44130 | Z80: 26/10/2020: Resposta para liberação 04/11/2020: Revisada planta de instrumentação, nova rota de cabos 18/11/2020: Pendente fornecimento de parafusos cabeça lentilha, para fixação das eletrocalhas. | AA80: 130 | AB80: =IF(AND(Tabela1[[#This Row],[Data de Solcitação do Cabo]]<>0,Tabela1[[#This Row],[Bobina]]<>0),"Disponível",IF(AND(Tabela1[[#This Row],[Data de Solcitação do Cabo]]<>0,Tabela1[[#This Row],[Data de Liberação dos Cabos]]=""),"Pend. Resp.",IF(AND(Tabela1[[#This Row],[Data de Solcitação do Cabo]]<>0,Tabela1[[#This Row],[Bobina]]=""),"Pend. Compra","Não Solic."))) -> Disponível | AC80: PR-LC-0001 | AD80: =IF(Tabela1[[#This Row],[Qtde. Lançada]]>Tabela1[[#This Row],[Comprimento Total]],Tabela1[[#This Row],[Qtde. Lançada]],Tabela1[[#This Row],[Comprimento Total]]) -> 110 | AE80: Analógico (I.S.) | AF80: 30LVxGB-1203 | AG80: =SUMIF('Lançamento de Cabos'!AE:AK,Tabela1[[#This Row],[Tag do Cabo]],'Lançamento de Cabos'!AG:AG) -> 0 | AH80: =IFERROR(VLOOKUP(Tabela1[[#This Row],[Tag do Cabo]],'Lançamento de Cabos'!AE:AK,7,0),0) -> 0 | AI80: SOK0898310 | AJ80: 6 | AK80: 923851
A81: U-12690 | B81: Controle | C81: - | D81: - | E81: 12P#1,0mm²+SHI+SHC (I.S.) | F81: 1 | G81: 1 | H81: 80 | I81: 80 | J81: 30LV | K81: JBI-120-104X | L81: 30LV/UCP LI-1203A | M81: Sim | N81: ="Sim" -> Sim | O81: --- | P81: --- | Q81: 4.4.1 | R81: =SUMIF('Lançamento de Cabos'!$B:$B,Tabela1[[#This Row],[Tag do Cabo]],'Lançamento de Cabos'!$C:$C) -> 110 | S81: =VLOOKUP(Tabela1[[#This Row],[Tag do Cabo]],'Diagramas Ligações'!A:V,14,0) -> 46 | T81: BK-SP54-01200-LC-80-00004_00000 | U81: 10 | V81: Controle 1/18 | W81: INST-2170 | X81: 44120 | Y81: 44130 | Z81: 26/10/2020: Resposta para liberação 04/11/2020: Revisada planta de instrumentação, nova rota de cabos 18/11/2020: Pendente fornecimento de parafusos cabeça lentilha, para fixação das eletrocalhas. | AA81: 126 | AB81: =IF(AND(Tabela1[[#This Row],[Data de Solcitação do Cabo]]<>0,Tabela1[[#This Row],[Bobina]]<>0),"Disponível",IF(AND(Tabela1[[#This Row],[Data de Solcitação do Cabo]]<>0,Tabela1[[#This Row],[Data de Liberação dos Cabos]]=""),"Pend. Resp.",IF(AND(Tabela1[[#This Row],[Data de Solcitação do Cabo]]<>0,Tabela1[[#This Row],[Bobina]]=""),"Pend. Compra","Não Solic."))) -> Disponível | AC81: PR-LC-0001 | AD81: =IF(Tabela1[[#This Row],[Qtde. Lançada]]>Tabela1[[#This Row],[Comprimento Total]],Tabela1[[#This Row],[Qtde. Lançada]],Tabela1[[#This Row],[Comprimento Total]]) -> 110 | AE81: Analógico (I.S.) | AF81: 30LVxGB-1203 | AG81: =SUMIF('Lançamento de Cabos'!AE:AK,Tabela1[[#This Row],[Tag do Cabo]],'Lançamento de Cabos'!AG:AG) -> 0 | AH81: =IFERROR(VLOOKUP(Tabela1[[#This Row],[Tag do Cabo]],'Lançamento de Cabos'!AE:AK,7,0),0) -> 0 | AI81: SOK0898310 | AJ81: 21/22/24 | AK81: 3005082
A82: U-12697 | B82: Controle | C82: - | D82: - | E82: 4P#1,0mm²+SHI+SHC (I.S.) | F82: 1 | G82: 1 | H82: 80 | I82: 80 | J82: 30LV | K82: JBI-120-106X | L82: 30LV/UCP LI-1203A | M82: Sim | N82: ="Sim" -> Sim | O82: --- | P82: --- | Q82: 4.6.1 | R82: =SUMIF('Lançamento de Cabos'!$B:$B,Tabela1[[#This Row],[Tag do Cabo]],'Lançamento de Cabos'!$C:$C) -> 110 | S82: =VLOOKUP(Tabela1[[#This Row],[Tag do Cabo]],'Diagramas Ligações'!A:V,14,0) -> 20 | T82: BK-SP54-01200-LC-80-00004_00000 | U82: 10 | V82: Controle 1/18 | W82: INST-2170 | X82: 44120 | Y82: 44130 | Z82: 26/10/2020: Resposta para liberação 04/11/2020: Revisada planta de instrumentação, nova rota de cabos 18/11/2020: Pendente fornecimento de parafusos cabeça lentilha, para fixação das eletrocalhas. | AA82: 127 | AB82: =IF(AND(Tabela1[[#This Row],[Data de Solcitação do Cabo]]<>0,Tabela1[[#This Row],[Bobina]]<>0),"Disponível",IF(AND(Tabela1[[#This Row],[Data de Solcitação do Cabo]]<>0,Tabela1[[#This Row],[Data de Liberação dos Cabos]]=""),"Pend. Resp.",IF(AND(Tabela1[[#This Row],[Data de Solcitação do Cabo]]<>0,Tabela1[[#This Row],[Bobina]]=""),"Pend. Compra","Não Solic."))) -> Disponível | AC82: PR-LC-0001 | AD82: =IF(Tabela1[[#This Row],[Qtde. Lançada]]>Tabela1[[#This Row],[Comprimento Total]],Tabela1[[#This Row],[Qtde. Lançada]],Tabela1[[#This Row],[Comprimento Total]]) -> 110 | AE82: Analógico (I.S.) | AF82: 30LVxGB-1203 | AG82: =SUMIF('Lançamento de Cabos'!AE:AK,Tabela1[[#This Row],[Tag do Cabo]],'Lançamento de Cabos'!AG:AG) -> 0 | AH82: =IFERROR(VLOOKUP(Tabela1[[#This Row],[Tag do Cabo]],'Lançamento de Cabos'!AE:AK,7,0),0) -> 0 | AI82: SOK0898310 | AJ82: 12 | AK82: 1423312
A83: U-12698 | B83: Controle | C83: - | D83: - | E83: 2P#1,0mm²+SHI+SHC (N.I.S.) | F83: 1 | G83: 1 | H83: 80 | I83: 80 | J83: 30LV | K83: JBI-120-106X | L83: 30LV/UCP LI-1203A | M83: Sim | N83: ="Sim" -> Sim | O83: --- | P83: --- | Q83: 4.6.1 | R83: =SUMIF('Lançamento de Cabos'!$B:$B,Tabela1[[#This Row],[Tag do Cabo]],'Lançamento de Cabos'!$C:$C) -> 110 | S83: =VLOOKUP(Tabela1[[#This Row],[Tag do Cabo]],'Diagramas Ligações'!A:V,14,0) -> 8 | T83: BK-SP54-01200-LC-80-00004_00000 | U83: 10 | V83: Controle 1/18 | W83: INST-2170 | X83: 44120 | Y83: 44130 | Z83: 26/10/2020: Resposta para liberação 04/11/2020: Revisada planta de instrumentação, nova rota de cabos 18/11/2020: Pendente fornecimento de parafusos cabeça lentilha, para fixação das eletrocalhas. | AA83: 73 | AB83: =IF(AND(Tabela1[[#This Row],[Data de Solcitação do Cabo]]<>0,Tabela1[[#This Row],[Bobina]]<>0),"Disponível",IF(AND(Tabela1[[#This Row],[Data de Solcitação do Cabo]]<>0,Tabela1[[#This Row],[Data de Liberação dos Cabos]]=""),"Pend. Resp.",IF(AND(Tabela1[[#This Row],[Data de Solcitação do Cabo]]<>0,Tabela1[[#This Row],[Bobina]]=""),"Pend. Compra","Não Solic."))) -> Disponível | AC83: PR-LC-0001 | AD83: =IF(Tabela1[[#This Row],[Qtde. Lançada]]>Tabela1[[#This Row],[Comprimento Total]],Tabela1[[#This Row],[Qtde. Lançada]],Tabela1[[#This Row],[Comprimento Total]]) -> 110 | AE83: Digital (N.I.S.) | AF83: 30LVxGB-1203 | AG83: =SUMIF('Lançamento de Cabos'!AE:AK,Tabela1[[#This Row],[Tag do Cabo]],'Lançamento de Cabos'!AG:AG) -> 0 | AH83: =IFERROR(VLOOKUP(Tabela1[[#This Row],[Tag do Cabo]],'Lançamento de Cabos'!AE:AK,7,0),0) -> 0 | AI83: SOK0898310 | AJ83: 8, 12 | AK83: 205637
A84: U-12700 | B84: Controle | C84: - | D84: - | E84: 4T#1,0mm²+SHI+SHC (I.S.) | F84: 1 | G84: 1 | H84: 80 | I84: 80 | J84: 30LV | K84: JBI-120-104X | L84: 30LV/UCP LI-1203A | M84: Sim | N84: ="Sim" -> Sim | O84: --- | P84: --- | Q84: 4.6.1 | R84: =SUMIF('Lançamento de Cabos'!$B:$B,Tabela1[[#This Row],[Tag do Cabo]],'Lançamento de Cabos'!$C:$C) -> 110 | S84: =VLOOKUP(Tabela1[[#This Row],[Tag do Cabo]],'Diagramas Ligações'!A:V,14,0) -> 18 | T84: BK-SP54-01200-LC-80-00004_00000 | U84: 10 | V84: Controle 1/18 | W84: INST-2170 | X84: 44120 | Y84: 44130 | Z84: 26/10/2020: Resposta para liberação 04/11/2020: Revisada planta de instrumentação, nova rota de cabos 18/11/2020: Pendente fornecimento de parafusos cabeça lentilha, para fixação das eletrocalhas. | AA84: 133 | AB84: =IF(AND(Tabela1[[#This Row],[Data de Solcitação do Cabo]]<>0,Tabela1[[#This Row],[Bobina]]<>0),"Disponível",IF(AND(Tabela1[[#This Row],[Data de Solcitação do Cabo]]<>0,Tabela1[[#This Row],[Data de Liberação dos Cabos]]=""),"Pend. Resp.",IF(AND(Tabela1[[#This Row],[Data de Solcitação do Cabo]]<>0,Tabela1[[#This Row],[Bobina]]=""),"Pend. Compra","Não Solic."))) -> Disponível | AC84: PR-LC-0001 | AD84: =IF(Tabela1[[#This Row],[Qtde. Lançada]]>Tabela1[[#This Row],[Comprimento Total]],Tabela1[[#This Row],[Qtde. Lançada]],Tabela1[[#This Row],[Comprimento Total]]) -> 110 | AE84: Analógico (I.S.) | AF84: 30LVxGB-1203 | AG84: =SUMIF('Lançamento de Cabos'!AE:AK,Tabela1[[#This Row],[Tag do Cabo]],'Lançamento de Cabos'!AG:AG) -> 0 | AH84: =IFERROR(VLOOKUP(Tabela1[[#This Row],[Tag do Cabo]],'Lançamento de Cabos'!AE:AK,7,0),0) -> 0 | AI84: SOK0898310 | AJ84: 5 | AK84: 3184799
A85: 7HV FS-C001 | B85: Controle | C85: - | D85: - | E85: 1x1x3xC#1,5 | F85: 1.5 | G85: 1 | H85: 30 | I85: 30 | J85: 7HV | K85: CELLAR AREA (7HV-FS-01) | L85: E-HOUSE (PA-7HV-COM) | M85: Sim | N85: ="Sim" -> Sim | O85: --- | P85: --- | Q85: 4.6.1 | R85: =SUMIF('Lançamento de Cabos'!$B:$B,Tabela1[[#This Row],[Tag do Cabo]],'Lançamento de Cabos'!$C:$C) -> 30 | S85: =VLOOKUP(Tabela1[[#This Row],[Tag do Cabo]],'Diagramas Ligações'!A:V,14,0) -> 6 | T85: E5WP000490-C-001-LC004 | U85: 2 | V85: Já impresso | W85: - | X85: - | Y85: - | Z85: - | AA85: - | AB85: =IF(AND(Tabela1[[#This Row],[Data de Solcitação do Cabo]]<>0,Tabela1[[#This Row],[Bobina]]<>0),"Disponível",IF(AND(Tabela1[[#This Row],[Data de Solcitação do Cabo]]<>0,Tabela1[[#This Row],[Data de Liberação dos Cabos]]=""),"Pend. Resp.",IF(AND(Tabela1[[#This Row],[Data de Solcitação do Cabo]]<>0,Tabela1[[#This Row],[Bobina]]=""),"Pend. Compra","Não Solic."))) -> Disponível | AC85: PR-LC-0000 | AD85: =IF(Tabela1[[#This Row],[Qtde. Lançada]]>Tabela1[[#This Row],[Comprimento Total]],Tabela1[[#This Row],[Qtde. Lançada]],Tabela1[[#This Row],[Comprimento Total]]) -> 30 | AE85: - | AF85: 7HV | AG85: =SUMIF('Lançamento de Cabos'!AE:AK,Tabela1[[#This Row],[Tag do Cabo]],'Lançamento de Cabos'!AG:AG) -> 9 | AH85: =IFERROR(VLOOKUP(Tabela1[[#This Row],[Tag do Cabo]],'Lançamento de Cabos'!AE:AK,7,0),0) -> 1.5 | AI85: E5WP000490-C-002-DE004 | AJ85: 5 | AK85: -
A86: 7HV FS-C002 | B86: Controle | C86: - | D86: - | E86: 1x1x3xC#1,5 | F86: 1.5 | G86: 1 | H86: 30 | I86: 30 | J86: 7HV | K86: CELLAR AREA (7HV-FS-01) | L86: E-HOUSE (PA-7HV-COM) | M86: Sim | N86: ="Sim" -> Sim | O86: --- | P86: --- | Q86: 4.6.1 | R86: =SUMIF('Lançamento de Cabos'!$B:$B,Tabela1[[#This Row],[Tag do Cabo]],'Lançamento de Cabos'!$C:$C) -> 30 | S86: =VLOOKUP(Tabela1[[#This Row],[Tag do Cabo]],'Diagramas Ligações'!A:V,14,0) -> 2 | T86: E5WP000490-C-001-LC004 | U86: 2 | V86: Já impresso | W86: - | X86: - | Y86: - | Z86: - | AA86: - | AB86: =IF(AND(Tabela1[[#This Row],[Data de Solcitação do Cabo]]<>0,Tabela1[[#This Row],[Bobina]]<>0),"Disponível",IF(AND(Tabela1[[#This Row],[Data de Solcitação do Cabo]]<>0,Tabela1[[#This Row],[Data de Liberação dos Cabos]]=""),"Pend. Resp.",IF(AND(Tabela1[[#This Row],[Data de Solcitação do Cabo]]<>0,Tabela1[[#This Row],[Bobina]]=""),"Pend. Compra","Não Solic."))) -> Disponível | AC86: PR-LC-0000 | AD86: =IF(Tabela1[[#This Row],[Qtde. Lançada]]>Tabela1[[#This Row],[Comprimento Total]],Tabela1[[#This Row],[Qtde. Lançada]],Tabela1[[#This Row],[Comprimento Total]]) -> 30 | AE86: - | AF86: 7HV | AG86: =SUMIF('Lançamento de Cabos'!AE:AK,Tabela1[[#This Row],[Tag do Cabo]],'Lançamento de Cabos'!AG:AG) -> 2 | AH86: =IFERROR(VLOOKUP(Tabela1[[#This Row],[Tag do Cabo]],'Lançamento de Cabos'!AE:AK,7,0),0) -> 1 | AI86: Não Localizado | AJ86: - | AK86: -
A87: 7HV-M001 | B87: Força | C87: 13800 | D87: 8,7/15 | E87: 1x3x1/C#70 | F87: 70 | G87: 3 | H87: 8 | I87: 24 | J87: 7HV | K87: E-HOUSE (7HV) | L87: CELLAR AREA (TR-09A) | M87: Sim | N87: --- | O87: Sim | P87: Sim | Q87: 5.2.4 | R87: =SUMIF('Lançamento de Cabos'!$B:$B,Tabela1[[#This Row],[Tag do Cabo]],'Lançamento de Cabos'!$C:$C) -> 24 | S87: =VLOOKUP(Tabela1[[#This Row],[Tag do Cabo]],'Diagramas Ligações'!A:V,14,0) -> 6 | T87: E5WP000490-C-001-LC003 | U87: 2 | V87: Já impresso | W87: - | X87: - | Y87: - | Z87: - | AA87: - | AB87: =IF(AND(Tabela1[[#This Row],[Data de Solcitação do Cabo]]<>0,Tabela1[[#This Row],[Bobina]]<>0),"Disponível",IF(AND(Tabela1[[#This Row],[Data de Solcitação do Cabo]]<>0,Tabela1[[#This Row],[Data de Liberação dos Cabos]]=""),"Pend. Resp.",IF(AND(Tabela1[[#This Row],[Data de Solcitação do Cabo]]<>0,Tabela1[[#This Row],[Bobina]]=""),"Pend. Compra","Não Solic."))) -> Disponível | AC87: PR-LC-0000 | AD87: =IF(Tabela1[[#This Row],[Qtde. Lançada]]>Tabela1[[#This Row],[Comprimento Total]],Tabela1[[#This Row],[Qtde. Lançada]],Tabela1[[#This Row],[Comprimento Total]]) -> 24 | AE87: - | AF87: 7HV | AG87: =SUMIF('Lançamento de Cabos'!AE:AK,Tabela1[[#This Row],[Tag do Cabo]],'Lançamento de Cabos'!AG:AG) -> 6 | AH87: =IFERROR(VLOOKUP(Tabela1[[#This Row],[Tag do Cabo]],'Lançamento de Cabos'!AE:AK,7,0),0) -> 1 | AI87: E5WP000490-C-002-DE003 | AJ87: 2 | AK87: -
A88: 7HV-M002 | B88: Força | C88: 13800 | D88: 8,7/15 | E88: 1x3x1/C#70 | F88: 70 | G88: 3 | H88: 6 | I88: 18 | J88: 7HV | K88: E-HOUSE (7HV) | L88: CELLAR AREA (TR-09B) | M88: Sim | N88: --- | O88: Sim | P88: Sim | Q88: 5.2.4 | R88: =SUMIF('Lançamento de Cabos'!$B:$B,Tabela1[[#This Row],[Tag do Cabo]],'Lançamento de Cabos'!$C:$C) -> 18 | S88: =VLOOKUP(Tabela1[[#This Row],[Tag do Cabo]],'Diagramas Ligações'!A:V,14,0) -> 6 | T88: E5WP000490-C-001-LC003 | U88: 2 | V88: Já impresso | W88: - | X88: - | Y88: - | Z88: - | AA88: - | AB88: =IF(AND(Tabela1[[#This Row],[Data de Solcitação do Cabo]]<>0,Tabela1[[#This Row],[Bobina]]<>0),"Disponível",IF(AND(Tabela1[[#This Row],[Data de Solcitação do Cabo]]<>0,Tabela1[[#This Row],[Data de Liberação dos Cabos]]=""),"Pend. Resp.",IF(AND(Tabela1[[#This Row],[Data de Solcitação do Cabo]]<>0,Tabela1[[#This Row],[Bobina]]=""),"Pend. Compra","Não Solic."))) -> Disponível | AC88: PR-LC-0000 | AD88: =IF(Tabela1[[#This Row],[Qtde. Lançada]]>Tabela1[[#This Row],[Comprimento Total]],Tabela1[[#This Row],[Qtde. Lançada]],Tabela1[[#This Row],[Comprimento Total]]) -> 18 | AE88: - | AF88: 7HV | AG88: =SUMIF('Lançamento de Cabos'!AE:AK,Tabela1[[#This Row],[Tag do Cabo]],'Lançamento de Cabos'!AG:AG) -> 6 | AH88: =IFERROR(VLOOKUP(Tabela1[[#This Row],[Tag do Cabo]],'Lançamento de Cabos'!AE:AK,7,0),0) -> 1 | AI88: E5WP000490-C-002-DE003 | AJ88: 2 | AK88: -
A89: 7HV-M003 | B89: Força | C89: 13800 | D89: 8,7/15 | E89: 1x3x1/C#70 | F89: 70 | G89: 3 | H89: 18 | I89: 54 | J89: 7HV | K89: E-HOUSE (7HV) | L89: CELLAR AREA (TR-27) | M89: Sim | N89: --- | O89: Sim | P89: Sim | Q89: 5.2.4 | R89: =SUMIF('Lançamento de Cabos'!$B:$B,Tabela1[[#This Row],[Tag do Cabo]],'Lançamento de Cabos'!$C:$C) -> 54 | S89: =VLOOKUP(Tabela1[[#This Row],[Tag do Cabo]],'Diagramas Ligações'!A:V,14,0) -> 6 | T89: E5WP000490-C-001-LC003 | U89: 2 | V89: Já impresso | W89: - | X89: - | Y89: - | Z89: - | AA89: - | AB89: =IF(AND(Tabela1[[#This Row],[Data de Solcitação do Cabo]]<>0,Tabela1[[#This Row],[Bobina]]<>0),"Disponível",IF(AND(Tabela1[[#This Row],[Data de Solcitação do Cabo]]<>0,Tabela1[[#This Row],[Data de Liberação dos Cabos]]=""),"Pend. Resp.",IF(AND(Tabela1[[#This Row],[Data de Solcitação do Cabo]]<>0,Tabela1[[#This Row],[Bobina]]=""),"Pend. Compra","Não Solic."))) -> Disponível | AC89: PR-LC-0000 | AD89: =IF(Tabela1[[#This Row],[Qtde. Lançada]]>Tabela1[[#This Row],[Comprimento Total]],Tabela1[[#This Row],[Qtde. Lançada]],Tabela1[[#This Row],[Comprimento Total]]) -> 54 | AE89: - | AF89: 7HV | AG89: =SUMIF('Lançamento de Cabos'!AE:AK,Tabela1[[#This Row],[Tag do Cabo]],'Lançamento de Cabos'!AG:AG) -> 6 | AH89: =IFERROR(VLOOKUP(Tabela1[[#This Row],[Tag do Cabo]],'Lançamento de Cabos'!AE:AK,7,0),0) -> 1 | AI89: E5WP000490-C-002-DE003 | AJ89: 2 | AK89: -
A90: 7HV-M004 | B90: Força | C90: 13800 | D90: 8,7/15 | E90: 1x3x1/C#70 | F90: 70 | G90: 3 | H90: 12 | I90: 36 | J90: 7HV | K90: E-HOUSE (7HV) | L90: CELLAR AREA (TR-08A/B) | M90: Sim | N90: --- | O90: Sim | P90: Sim | Q90: 5.2.4 | R90: =SUMIF('Lançamento de Cabos'!$B:$B,Tabela1[[#This Row],[Tag do Cabo]],'Lançamento de Cabos'!$C:$C) -> 36 | S90: =VLOOKUP(Tabela1[[#This Row],[Tag do Cabo]],'Diagramas Ligações'!A:V,14,0) -> 6 | T90: E5WP000490-C-001-LC003 | U90: 2 | V90: Já impresso | W90: - | X90: - | Y90: - | Z90: - | AA90: - | AB90: =IF(AND(Tabela1[[#This Row],[Data de Solcitação do Cabo]]<>0,Tabela1[[#This Row],[Bobina]]<>0),"Disponível",IF(AND(Tabela1[[#This Row],[Data de Solcitação do Cabo]]<>0,Tabela1[[#This Row],[Data de Liberação dos Cabos]]=""),"Pend. Resp.",IF(AND(Tabela1[[#This Row],[Data de Solcitação do Cabo]]<>0,Tabela1[[#This Row],[Bobina]]=""),"Pend. Compra","Não Solic."))) -> Disponível | AC90: PR-LC-0000 | AD90: =IF(Tabela1[[#This Row],[Qtde. Lançada]]>Tabela1[[#This Row],[Comprimento Total]],Tabela1[[#This Row],[Qtde. Lançada]],Tabela1[[#This Row],[Comprimento Total]]) -> 36 | AE90: - | AF90: 7HV | AG90: =SUMIF('Lançamento de Cabos'!AE:AK,Tabela1[[#This Row],[Tag do Cabo]],'Lançamento de Cabos'!AG:AG) -> 6 | AH90: =IFERROR(VLOOKUP(Tabela1[[#This Row],[Tag do Cabo]],'Lançamento de Cabos'!AE:AK,7,0),0) -> 1 | AI90: E5WP000490-C-002-DE003 | AJ90: 2 | AK90: -
A91: 7HV-M005 | B91: Força | C91: 13800 | D91: 8,7/15 | E91: 1x3x1/C#70 | F91: 70 | G91: 3 | H91: 4 | I91: 12 | J91: 7HV | K91: E-HOUSE (7HV) | L91: CELLAR AREA (TR-24A) | M91: Sim | N91: --- | O91: Sim | P91: Sim | Q91: 5.2.4 | R91: =SUMIF('Lançamento de Cabos'!$B:$B,Tabela1[[#This Row],[Tag do Cabo]],'Lançamento de Cabos'!$C:$C) -> 12 | S91: =VLOOKUP(Tabela1[[#This Row],[Tag do Cabo]],'Diagramas Ligações'!A:V,14,0) -> 6 | T91: E5WP000490-C-001-LC003 | U91: 2 | V91: Já impresso | W91: - | X91: - | Y91: - | Z91: - | AA91: - | AB91: =IF(AND(Tabela1[[#This Row],[Data de Solcitação do Cabo]]<>0,Tabela1[[#This Row],[Bobina]]<>0),"Disponível",IF(AND(Tabela1[[#This Row],[Data de Solcitação do Cabo]]<>0,Tabela1[[#This Row],[Data de Liberação dos Cabos]]=""),"Pend. Resp.",IF(AND(Tabela1[[#This Row],[Data de Solcitação do Cabo]]<>0,Tabela1[[#This Row],[Bobina]]=""),"Pend. Compra","Não Solic."))) -> Disponível | AC91: PR-LC-0000 | AD91: =IF(Tabela1[[#This Row],[Qtde. Lançada]]>Tabela1[[#This Row],[Comprimento Total]],Tabela1[[#This Row],[Qtde. Lançada]],Tabela1[[#This Row],[Comprimento Total]]) -> 12 | AE91: - | AF91: 7HV | AG91: =SUMIF('Lançamento de Cabos'!AE:AK,Tabela1[[#This Row],[Tag do Cabo]],'Lançamento de Cabos'!AG:AG) -> 6 | AH91: =IFERROR(VLOOKUP(Tabela1[[#This Row],[Tag do Cabo]],'Lançamento de Cabos'!AE:AK,7,0),0) -> 1 | AI91: E5WP000490-C-002-DE003 | AJ91: 2 | AK91: -
